Workbook

Sheet hotels IST
A1: Collection | B1: hotels "IST"
A2: Remarks | B2: Hotels
A3: Date / Update | B3: 46203
A5: Special field type | B5: field_key Directus | C5: data_type | D5: interface (characters max) | E5: Relation (Sub-Collection) | F5: Label DE | G5: Label GB | H5: Label NL | I5: Info-Text (below the field) | K5: Yes / No | L5: Naming Translation-Collection
A6: Field hidden | B6: id | C6: uuid | D6: input | K6: No
A7: Field hidden | B7: sort | C7: integer | D7: input | K7: No
A8: Field hidden | B8: user_created | C8: uuid | D8: select-dropdown-m2o | E8: directus_users | K8: No
A9: Field hidden | B9: date_created | C9: timestamp | D9: datetime | K9: No
A10: Above Tabs | B10: header | C10: alias | D10: header | K10: No
A11: Tab-Navigation | B11: hotel_tabs | C11: alias | D11: group-tabs | K11: No
A12: Tab | B12: master_data_group | C12: alias | D12: group-raw | F12: Stammdaten | G12: Master Data | H12: Stamgegevens | K12: No
A13: Block | B13: accordion-obvxyf | C13: alias | D13: group-raw | K13: No
A14: Section | B14: travel_id_group | C14: alias | D14: group-detail | F14: Name & Veröffentlichung | G14: Name & Publication | H14: Naam & Publicatie | K14: No
B15: name | C15: string | D15: input | F15: Hotelname | G15: Hotel Name | H15: Hotelnaam | K15: No
B16: season | C16: integer | D16: select-dropdown-m2o | E16: seasons | F16: Saisonzeit | G16: Season | H16: Seizoen | K16: No
A17: Field hidden | B17: object_info | C17: string | D17: input | K17: No
B18: object_id | C18: integer | D18: input | F18: Objekt-ID | G18: Object-ID | H18: Object-ID | I18: $t:hotels_object_id_note | K18: No
B19: status_primarix | C19: string | D19: select-dropdown | F19: Status Primarix | G19: Status Primarix | H19: Status Primarix | K19: No
B20: internal_remarks | C20: text | D20: input-multiline | F20: Interne Hinweise | G20: Internal Remarks | H20: Interne opmerking | I20: $t:hotel_internal_remarks_note | K20: No
A21: Field hidden | B21: date_updated | C21: timestamp | D21: datetime | F21: Zuletzt aktualisiert | G21: Last Update | H21: Laatste update | K21: No
A22: Field hidden | B22: user_updated | C22: uuid | D22: select-dropdown-m2o | E22: directus_users | F22: von | G22: by | H22: door | K22: No
A23: Section | B23: partner_group | C23: alias | D23: group-detail | F23: Partner Filter | G23: Partner Filter | H23: Partner Filter | K23: No
B24: partner_type | C24: string | D24: select-radio | F24: Auswahl BOTG Partner | G24: Choice BOTG Partner | K24: No
B25: partner | C25: alias | D25: list-m2m | E25: partner | F25: Ausgewählte Partner | G25: Chosen Partner(s) | K25: No
A26: Block | B26: main_group | C26: alias | D26: group-raw | K26: No
A27: Section | B27: master_data | C27: alias | D27: group-detail | F27: Adresse Hotel | G27: Address Hotel | H27: Adres Hotel | K27: No
B28: hotel_group | C28: uuid | D28: select-dropdown-m2o | E28: hotel_group | F28: Hotelkette | G28: Hotel Group | H28: Hotelketen | I28: $t:hotels_hotel_group_note | K28: No
B29: street | C29: string | D29: input | F29: Straße | G29: Street | H29: Straat | K29: No
B30: street_number | C30: string | D30: input | F30: Hausnummer | G30: Street Number | H30: Huisnummer | K30: No
B31: zip_code | C31: string | D31: input | F31: PLZ | G31: Postal Code | H31: Postcode | K31: No
B32: place | C32: integer | D32: cascading-individual-select | E32: places | F32: Ort | G32: City/Town | H32: Plaats | I32: $t:hotels_place | K32: No
B33: location_tour32 | C33: integer | D33: cascading-individual-select | E33: locations_tour32 | F33: Suchort (Tour User only) | G33: Search Location (Tour User only) | H33: Zoeklocatie (Tour User only) | K33: No
B34: state | C34: integer | D34: cascading-individual-select | E34: states | F34: Zustand | G34: State | H34: Staat | K34: No
B35: region | C35: integer | D35: cascading-individual-select | E35: regions | G35: Region | H35: Regio | K35: No
B36: country | C36: integer | D36: cascading-individual-select | E36: countries | F36: Land | G36: Country | H36: Land | I36: $t:hotels_country | K36: No
B37: phone_general | C37: string | D37: input | F37: Telefon (allgemein) | G37: Phone (general) | H37: Telefoon (algemeen) | K37: No
B38: phone_ah | C38: string | D38: input | F38: Telefon (after hours) | G38: Phone (after hours) | H38: Telefoon (na kantooruren) | K38: No
B39: email_general | C39: string | D39: input | F39: Email (allgemein) | G39: E-mail (general) | H39: Email (algemeen) | K39: No
B40: website | C40: string | D40: input | F40: Webseite | G40: Web Site | H40: Homepage | K40: No
A41: Block | B41: partner_raw_group | C41: alias | D41: group-raw | G41: Partner Filter | K41: No
A42: Accordion ⚠ | B42: accordion-cob52j | C42: alias | D42: group-accordion | F42: Chosen Partners | G42: Partner Filter | K42: No
A43: Block | B43: reservation_main_group | C43: alias | D43: group-raw | K43: No
A44: Section | B44: reservation_group | C44: alias | D44: group-detail | F44: Reservierung | G44: Reservation | H44: Reservering | K44: No
B45: booking_partner | C45: string | D45: select-radio | F45: Buchung über | G45: Booking Partner | K45: No
A46: Field hidden | B46: booking | C46: uuid | D46: select-dropdown-m2o | E46: booking_partners | F46: Buchung über | G46: Booking via | H46: Boeking via | K46: No
B47: id_tour_user | C47: string | D47: input | F47: Leistungsträger (Tour32 only) | G47: Service Provider (Tour32 only) | H47: Dienstverlener (Tour32 only) | I47: $t:hotels_id_tour_user_note | K47: No
B48: haupt_id_tour_user | C48: string | D48: input | F48: Haupt-Leistungsträger (Tour32 only) | G48: Main Service Provider (Tour32 only) | H48: Hoofddienstverlener (Tour32 only) | I48: $t:hotels_haupt_id_tour_user_note | K48: No
A49: Field hidden | B49: booking_email | C49: string | D49: input | F49: Email Reservierung | G49: E-Mail Reservation | H49: Email reservering | K49: No
A50: Field hidden | B50: booking_info | C50: text | D50: input-multiline | F50: Interne Buchungsinfos /-Hinweise | G50: Internal Reservation Infos / Remarks | H50: Interne boekingsinfo / -opmerkingen | I50: $t:hotels_booking_info_note | K50: No
A51: Tab | B51: descriptons_group | C51: alias | D51: group-raw | F51: Beschreibung | G51: Description | H51: Beschrijving | K51: No
B52: accommodation_type | C52: alias | D52: list-m2m | E52: accommodation_types | F52: Unterkunftsart | G52: Accommodation Type | H52: Type accommodatie | K52: No
B53: hotel_classification | C53: uuid | D53: select-dropdown-m2o | E53: hotel_classifications | F53: Klassifizierung | G53: Classification | H53: Classificatie | K53: No
B54: hotel_activities | C54: alias | D54: list-m2m | E54: activities | F54: Aktivitäten | G54: Activities | H54: Activiteiten | K54: No
B55: hotel_descriptions_translations | C55: alias | D55: ai-translations | E55: hotels_translations | F55: Hotelbeschreibung übersetzbare Inhalte | G55: Translatable Fields | H55: Hotelbeschrijving: vertaalbare inhoud | K55: No
A56: ↳ i18n | B56: subline_location | C56: text | D56: input | F56: Ort (in Sub-Unterschrift) | G56: Location (within Subline) | H56: Locatie (in subtitel) | I56: $t:free_text_entry_for_sub_title_of_the_hotel | K56: Yes | L56: hotels_translations
A57: ↳ i18n | B57: teaser | C57: text | D57: input-multiline | F57: Einleitungstext | G57: Teaser Text | H57: Teaser text | I57: $t:hotels_description_teaser_note | K57: Yes | L57: hotels_translations
A58: ↳ i18n | B58: description_short | C58: text | D58: input-multiline | F58: Hotelbeschreibung | G58: Description | H58: Omschrijving | I58: $t:hotels_description_description_short_note | K58: Yes | L58: hotels_translations
A59: ↳ i18n | B59: description_surrounding | C59: text | D59: input-multiline | F59: Lagebeschreibung | G59: Location Description | H59: Locatiebeschrijving | K59: Yes | L59: hotels_translations
A60: ↳ i18n | B60: description_rooms | C60: text | D60: input-multiline | F60: Allgem. Zimmerbeschreibung | G60: Overall Room Description | H60: Algemene kamerbeschrijving | I60: $t:hotels_description_description_rooms_note | K60: Yes | L60: hotels_translations
A61: ↳ i18n | B61: total_number_of_rooms | C61: integer | D61: input | F61: Anzahl Zimmer | G61: Number of Rooms | H61: Aantal kamers | I61: $t:will_be_transferred_to_other_languages_automatically | K61: Yes | L61: hotels_translations
A62: ↳ i18n | B62: remarks_arrival | C62: text | D62: input-multiline | F62: Anreisehinweise | G62: Transfer / Access Info | H62: Bereikbaarheid | K62: Yes | L62: hotels_translations
A63: ↳ i18n | B63: description_supplementary | C63: json | D63: list | F63: Ergänzende Beschreibungen | G63: Supplementary Descriptions | H63: Aanvullende beschrijvingen | K63: Yes | L63: hotels_translations
A64: Tab | B64: price_infos_group | C64: alias | D64: group-raw | F64: Pricing Info | G64: Price Infos | H64: Prijsinfo | K64: No
B65: price_info_translations | C65: alias | D65: ai-translations | E65: hotels_translations_3 | K65: No
A66: ↳ i18n | B66: services_included | C66: text | D66: input-multiline | F66: Eingeschlossene Leistungen | G66: Included Services | H66: Inbegrepen diensten | K66: Yes | L66: hotels_translations_3
A67: ↳ i18n | B67: services_not_included | C67: text | D67: input-multiline | F67: Nicht eingeschlossene Leistungen | G67: Services not Included | H67: Niet-inbegrepen diensten | K67: Yes | L67: hotels_translations_3
A68: ↳ i18n | B68: service_highlights | C68: text | D68: input-multiline | F68: Indirekte Vorteile | G68: Indirect Benefits | H68: Indirecte voordelen | I68: aka "Smilie" | K68: Yes | L68: hotels_translations_3
A69: ↳ i18n | B69: minimum_stay | C69: string | D69: select-dropdown | F69: Mindestaufenthalt | G69: Minimum Stay | H69: Minimumverblijf | K69: Yes | L69: hotels_translations_3
A70: ↳ i18n | B70: minimum_stay_additions | C70: string | D70: input | F70: Alternative Text | G70: Alternative Text | H70: Alternative Text | K70: Yes | L70: hotels_translations_3
A71: ↳ i18n | B71: deviating_cancelation_terms | C71: text | D71: input-multiline | F71: Abweichende Stornobedingungen? | G71: Deviating Cancellation Conditions? | H71: Afwijkende annuleringsvoorwaarden? | K71: Yes | L71: hotels_translations_3
A72: ↳ i18n | B72: children_policy | C72: text | D72: input-multiline | F72: Kinder-Policy des Hotels | G72: Children Policy of Hotel | H72: Kinderbeleid van het hotel | K72: Yes | L72: hotels_translations_3
A73: ↳ i18n | B73: children_free_age | C73: integer | D73: input | F73: Max. Kindesalter kostenfrei | G73: Max. Child Age | H73: Max. kinderleeftijd | I73: $t:hotels_children_free_age | K73: Yes | L73: hotels_translations_3
A74: ↳ i18n | B74: children_free_number | C74: integer | D74: input | F74: Anzahl Kinder kostenfrei | G74: Number of Children Free of Charge | H74: Aantal kinderen gratis | I74: $t:hotels_children_free_number | K74: Yes | L74: hotels_translations_3
A75: ↳ i18n | B75: important_information | C75: text | D75: input-multiline | F75: Wichtige Informationen | G75: Important Information | H75: Belangrijke informatie | K75: Yes | L75: hotels_translations_3
A76: ↳ i18n | B76: price_infos_supplementary | C76: json | D76: list | F76: Ergänzende Beschreibungen | G76: Supplementary Descriptions | H76: Aanvullende beschrijvingen | K76: Yes | L76: hotels_translations_3
A77: ↳ i18n | B77: mobility_advice_text | C77: text | D77: input-multiline | F77: Text Mobilitätshinweis | G77: Text Mobility Advice | H77: Tekst mobiliteitsadvies | I77: $t:hotels_mobility_text_advice | K77: Yes | L77: hotels_translations_3
A78: Tab | B78: price_basic_group | C78: alias | D78: group-raw | F78: Kalkulationsbasics | G78: Calculation Basics | H78: Calculatiebasics | K78: No
A79: Section | B79: accordion-tjw07v | C79: alias | D79: group-detail | F79: Preis-Grundlagen | G79: Price Basics | H79: Prijsgrondslagen | K79: No
B80: room_categories | C80: alias | D80: list-o2m | E80: room_categories | F80: Zimmer-Kategorien | G80: Room Categories | H80: Kamercategorieën | K80: No
A81: ↳ o2m: room_categories | B81: room_category | C81: string | D81: input | F81: Zimmer-Kategorie | G81: Room Category | H81: Kamercategorie | K81: No
A82: ↳ o2m: room_categories | B82: price_start | C82: boolean | D82: boolean | F82: Vom preis | G82: From price | K82: No
A83: ↳ o2m: room_categories | B83: translations | C83: alias | D83: translations | E83: translations | K83: No
A84: ↳ o2m: room_categories | B84: room_category_booking_code | C84: string | D84: input | F84: Supplier Buchungscode | G84: Supplier Booking Code | H84: Supplier Boekingscode | K84: No
A85: ↳ o2m: room_categories | B85: room_category_tour32_name | C85: string | D85: input | F85: Bezeichnung TOUR32 | G85: Name TOUR32 | H85: Benaming TOUR32 | I85: Einheitlicher Name zur Verknüpfung verschiedener Wochentagspreise. | K85: No
A86: ↳ o2m: room_categories | B86: room_category_catering | C86: uuid | D86: select-dropdown-m2o | E86: catering_services | F86: Verpflegung | G86: Board Type | H86: Maaltijdregeling | K86: No
A87: ↳ o2m: room_categories | B87: room_category_calc_type | C87: string | D87: select-radio | F87: Berechnungsart (für IT-Systeme) | G87: Calculation Method (for IT Systems) | H87: Berekeningswijze (voor IT-systemen) | K87: No
A88: ↳ o2m: room_categories | B88: room_category_valid_weekdays | C88: alias | D88: list-m2m | E88: valid_on_weekdays | K88: No
A89: ↳ o2m: room_categories | B89: days_repeater | C89: json | D89: list | F89: Tagesrepetition | G89: Days Repeater | H89: Dagen repeater | K89: No
A90: ↳ o2m: room_categories | B90: sharedId | C90: string | D90: input | K90: No
A91: ↳ o2m: room_categories | B91: is_syncing | C91: boolean | D91: boolean | K91: No
A92: ↳ o2m: room_categories | B92: publication_divider | C92: alias | D92: presentation-divider | K92: No
A93: ↳ o2m: room_categories | B93: status | C93: string | D93: select-dropdown | K93: No
A94: ↳ o2m: room_categories | B94: publish_start | C94: dateTime | D94: datetime | I94: Optional. Room category becomes active from this date. | K94: No
A95: ↳ o2m: room_categories | B95: publish_end | C95: dateTime | D95: datetime | I95: Optional. Room category becomes inactive from this date. | K95: No
A96: (Divider) | B96: divider_1 | C96: alias | D96: presentation-divider | K96: No
B97: price_dates | C97: alias | D97: list-o2m | E97: price_dates | F97: Preisdaten | G97: Price Dates | H97: Prijs data | K97: No
A98: ↳ o2m: price_dates | B98: start_date | C98: date | D98: datetime | F98: Startdatum | G98: Start date | K98: No
A99: ↳ o2m: price_dates | B99: end_date | C99: date | D99: datetime | F99: Enddatum | G99: End date | K99: No
A100: ↳ o2m: price_dates | B100: from_price | C100: boolean | D100: boolean | F100: Vom preis | G100: From price | K100: No
A101: ↳ o2m: price_dates | B101: name | C101: string | D101: input | I101: $t:price_date_name_empty | K101: No
...

Sheet hotels SOLL
A1: Collection | B1: hotels IDEAL STATE
A2: Remarks | B2: Hotels
A3: Date / Update | B3: 46203
A4: Legend | B4: Checked | C4: Changes | D4: Analysis done | E4: Analysis tbd
A6: Details for Directus Set-up | K6: Translatable? | N6: Import Details "hotels" | U6: Remarks / Comments | X6: Legacy | Y6: Stakeholder Notes
A7: Special field type | B7: field_key Directus | C7: data_type | D7: interface (characters max) | E7: Relation (Sub-Collection) | F7: Label DE | G7: Label GB | H7: Label NL | I7: Info-Text (below the field) | K7: Yes / No | L7: Naming Translation-Collection | M7: Δ / Hinweis (IST↔SOLL) | N7: fieldid Primarix | O7: parent table | U7: Remarks for DEV (field set-up and Import) | V7: Remarks + Tasks internal | X7: tbd after import | Y7: TOPS Bernd | Z7: TOPs Birgit | AA7: Notes Client
A9: Above Tabs | B9: sell_prices_status | C9: string | D9: select-dropdown | F9: Verkaufspreis-Status | G9: Sell Prices Status | H9: Verkoopprijsstatus | I9: Tracks async sell price calculation state | K9: No | U9: hidden, root sync field
A10: Above Tabs | B10: sell_prices_updated_at | C10: timestamp | D10: datetime | F10: Aktualisiert am | G10: Sell Prices Updated At | H10: Bijgewerkt op | I10: Last successful sell price calculation | K10: No | U10: hidden, root sync field
A11: Tab-Navigation | B11: ui_tabs | C11: alias | D11: tabs | F11: - | G11: - | H11: -
A13: Tab | B13: tab_master_data | C13: alias | D13: group-raw | F13: Stammdaten | G13: Master Data | H13: Stamgegevens
A14: Block | B14: block_publication | C14: alias | D14: group-raw | F14: - | G14: - | H14: -
A15: Section (open) | B15: section_id_status | C15: alias | D15: group-detail | F15: Status & Veröffentlichung | G15: Status & Publication | H15: Status & publicatie
B16: object_id | C16: integer | D16: numerical | F16: Objekt-ID | G16: Object-ID | H16: Object-ID | I16: Automatically set. | K16: No | N16: oid | O16: hotels
B17: object_info_primarix | C17: string | D17: text input | F17: Objekt Titel Primarix | G17: Object Title Primarix | H17: Objecttitel Primarix | K17: No | M17: IST: object_info (umbenennen) | N17: object_info | U17: Non editable field
B18: season | C18: integer | D18: many to one | E18: seasons | F18: Saison-Gültigkeit | G18: Season Validity | H18: Seizoengeldigheid | K18: No | N18: season | U18: Transformed value from "object info": "25_" = "2025"
B19: status_primarix | C19: string | D19: select-dropdown | F19: Status Primarix | G19: Status Primarix | H19: Status Primarix | K19: No | N19: status (?) | O19: ?
B20: internal_remarks | C20: text | D20: text area | F20: Interne Hinweise | G20: Internal Remarks | H20: Interne opmerking | I20: Internal Remarks from Primarix. - Please consider for the future the "Comments"-Feature (Icon on right side). | K20: No | N20: field_131_1 | O20: hotels | U20: IMPORTANT: The field is in future NOT translatable. Within the import you need all "internal_remarks" into this field (also from other languages).
B21: date_updated | C21: dateTime | D21: date | F21: Zuletzt aktualisiert | G21: Last Update | H21: Laatste update | K21: No | N21: (?) | U21: Pls show the last update date if possible
B22: user_updated | F22: von | G22: by | H22: door | K22: No | U22: Pls show the last editor if possible (in case information is not available in Primarix show "unknown" or similar)
A24: Section (open) | B24: section_botg_filter | C24: alias | D24: group-detail | F24: BOTG-Firmen-Zuordnung | G24: BOTG Company Assignment | H24: BOTG-bedrijfstoewijzing
B25: partner_visibility | C25: string | D25: radio | K25: No | M25: IST: partner_type (umbenennen); Label bewusst leer (Radio – Info steckt in den Optionen)
B26: partner_selected | C26: integer | D26: many to one | E26: partner | K26: No | M26: IST: partner (umbenennen); E bereinigt; Label bewusst leer (M2O, gekoppelt an das partner_visibility-Radio) | N26: field_1144_1 | O26: hotels
A28: Block | B28: block_contacts | C28: alias | D28: group-raw | F28: - | G28: - | H28: -
A29: Section (open) | B29: section_address | C29: alias | D29: group-detail | F29: Adresse Hotel | G29: Hotel Address | H29: Adres hotel
B30: name_hotel | C30: string | D30: text input | F30: Hotelname | G30: Hotel Name | H30: Hotelnaam | K30: No | M30: IST: name (umbenennen) | N30: field_41_1 | O30: hotels
B31: hotel_group | C31: integer | D31: many to one | E31: hotel_groups | F31: Hotelkette | G31: Hotel Group | H31: Hotelketen | I31: Chose only if the hotel is part of a group. | K31: No | M31: DEV-IST: Collection heißt hotel_group (Singular, Abweichler) → SOLL hotel_groups (C1 Plural); Feld bleibt hotel_group. Directus-Rename = neue Collection + Migration + alte löschen | N31: field_1405_1 | O31: hotels
B32: street | C32: string | D32: text input | F32: Straße | G32: Street | H32: Straat | K32: No | N32: field_26_1 | O32: hotels
B33: street_number | C33: string | D33: text input | F33: Hausnummer | G33: Street Number | H33: Huisnummer | K33: No | N33: field_27_1 | O33: hotels
B34: zip_code | C34: string | D34: text input | F34: PLZ | G34: Postal Code | H34: Postcode | K34: No | N34: field_171_1 | O34: hotels
B35: place | C35: string | D35: auto complete | E35: places | F35: Ort | G35: City / Town | H35: Plaats | I35: Defines further geographical details (country, state, region). | K35: No | N35: field_28_1 | O35: hotels | U35: Please adapt import: Actually this field contains text inputs - these need to be matched to the entry in to the new collection "places"
B36: location_tour32 | C36: integer | D36: many to one | E36: locations_tour32 | F36: Suchort (Tour User only) | G36: Search Location (Tour User only) | H36: Zoeklocatie (Tour User only) | K36: No | N36: field_1342_1 | O36: hotels | U36: Please adapt import: Actually this field contains text inputs - these need to be matched to the entry in to the new collection "locations_tour32"
B37: country | C37: integer | D37: many to one | E37: countries | F37: Land | G37: Country | H37: Land | I37: Defined by "Place" | K37: No | N37: field_1031_1 | O37: hotels | U37: Pls integrate new logic "Geographies".
B38: state | C38: integer | D38: many to one | E38: states | F38: Staat / Bundesland | G38: State / Province | H38: Staat / Provincie | K38: No | N38: field_29_1 | O38: hotels | U38: New logic for geographies
B39: state_short | F39: Bundesland kurz | G39: State code | H39: Provincie kort | K39: No | N39: field_1017_1 | O39: hotels | U39: NOT to be imported!
B40: region | C40: integer | D40: many to one | E40: regions | F40: Region | G40: Region | H40: Regio | K40: No | M40: NL korrigiert: Regio (war „Region" – Brief-Tippfehler); DEV führt bereits Regio. | N40: field_1032_1 | O40: hotels | U40: New logic for geographies
B41: phone_general | C41: string | D41: phone number | F41: Telefon (allgemein) | G41: Phone (general) | H41: Telefoon (algemeen) | K41: No | N41: field_31_1 | O41: hotels | V41: ggf. als "repeater (json)"
B42: phone_after_hours | C42: string | D42: phone number | F42: Telefon (after hours) | G42: Phone (after hours) | H42: Telefoon (na kantooruren) | K42: No | M42: IST: phone_ah (umbenennen) | N42: field_218_1 | O42: hotels
B43: fax_general | D43: - | F43: Fax (allgemein) | G43: Fax (General) | H43: Fax (algemeen) | K43: No | N43: field_32_1 | O43: hotels | U43: NOT to be imported!
B44: email_general | C44: string | D44: mail | F44: Email (allgemein) | G44: E-mail (general) | H44: Email (algemeen) | K44: No | N44: field_42_1 | O44: hotels
B45: website | C45: string | D45: url | F45: Webseite | G45: Web Site | H45: Homepage | K45: No | N45: field_36_1 | O45: hotels
A47: Section (open) | B47: section_reservation | C47: alias | D47: group-detail | F47: Reservierung | G47: Reservation | H47: Reservering
B48: booking_channel | C48: string | D48: radio | K48: No | M48: IST: booking_partner (umbenennen); E geleert (Radio; war fälschlich booking_partners); Label bewusst leer (Radio – Info steckt in den Optionen) | N48: NEW | U48: Partner Booking OR Direct Booking
B49: booking_partner | C49: integer | D49: many to one | E49: booking_partners | F49: Buchung über | G49: Booking via | H49: Boeking via | K49: No | M49: IST: booking (umbenennen) | N49: field_365_1 | O49: hotels | U49: "Direct" = px_feldlisten: ID 7462 | AA49: 07.04.: "Inbounder" könnten an Relevanz gewinnen. Ergo: Mail-Adresse erhalten (9%) + 1 Feld (Text Area) für Rest.
B50: id_service_provider_tour32 | C50: string | D50: text input | F50: Leistungsträger (Tour32 only) | G50: Service Provider (Tour32 only) | H50: Dienstverlener (Tour32 only) | K50: No | M50: IST: id_tour_user (umbenennen) | N50: field_1178_1 | O50: hotels
B51: id_main_service_provider_tour32 | C51: string | D51: text input | F51: Haupt-Leistungsträger (Tour32 only) | G51: Main Service Provider (Tour32 only) | H51: Hoofddienstverlener (Tour32 only) | K51: No | M51: IST: haupt_id_tour_user (umbenennen) | N51: field_1383_1 | O51: hotels
A53: COMMENT | B53: Following fields if radio "Direct Booking":
B54: res_phone | D54: - | F54: Reservierung: Telefon | G54: Reservation: Telephone | H54: Reservering: Telefoon | N54: field_49_1 | O54: hotels | U54: No seperate field anymore. Import into field "booking_info".
B55: res_fax | D55: - | F55: Reservierung: Fax | G55: Reservation: Fax | H55: Reservering: Fax | N55: field_50_1 | O55: hotels | U55: NOT to be imported!
B56: email_booking | C56: string | D56: email | F56: Email Reservierung | G56: E-Mail Reservation | H56: Email reservering | K56: No | M56: IST: booking_email (umbenennen) | N56: field_51_1 | O56: hotels
B57: res_email2 | D57: - | F57: Reservierung: Email 2 | G57: Reservation: E-mail 2 | H57: Reservering: Email 2 | N57: field_56_1 | O57: hotels | U57: No seperate field anymore. Import into field "booking_info".
B58: contact_title | D58: - | F58: Reservierung: Kontakt Titel | G58: Reservation: Contact Title | H58: Reservering: Contactpersoon Titel | N58: field_52_1 | O58: hotels | U58: No seperate field anymore. Import into field "booking_info".
B59: contact_greeting | D59: - | F59: Reservierung: Kontakt Anrede | G59: Reservation: Contact Salutation | H59: Reservering: Contactpersoon Aanhef | N59: field_53_1 | O59: hotels | U59: No seperate field anymore. Import into field "booking_info".
B60: contact_firstname | D60: - | F60: Reservierung: Kontakt Vorname | G60: Reservation: Contact First Name | H60: Reservering: Contactpersoon Voornaam | N60: field_54_1 | O60: hotels | U60: No seperate field anymore. Import into field "booking_info".
B61: contact_name | D61: - | F61: Reservierung: Kontakt Name | G61: Reservation: Contact Surname | H61: Reservering: Contactpersoon Naam | N61: field_55_1 | O61: hotels | U61: No seperate field anymore. Import into field "booking_info".
B62: internal_remarks_reservation | C62: text | D62: text area | F62: Interne Buchungsinfos /-Hinweise | G62: Internal Reservation Infos / Remarks | H62: Interne boekingsinfo / -opmerkingen | K62: No | M62: IST: booking_info (umbenennen) | N62: field_1030_1 | O62: hotels | U62: Here all data fused from this field and the ones above. - <br> as separation. | Y62: Nur 46x befüllt - siehe Word
B63: it_code | D63: - | F63: Supplier Booking Code | G63: Supplier Booking Code | H63: Supplier Boekingscode | N63: field_40_1 | U63: NOT to be imported! | Primarix: 'Löschen.' (Entscheidung offen) | Y63: Nur 14x befüllt - siehe Word
A65: Tab | B65: tab_description | C65: alias | D65: group-raw | F65: Beschreibung | G65: Description | H65: Beschrijving
A66: Section (open) | B66: section_classification | C66: alias | D66: group-detail | F66: Klassifizierung | G66: Classification | H66: Indeling
B67: accommodation_types | C67: alias | D67: many to many | E67: accommodation_types | F67: Unterkunftsart | G67: Accommodation Type | H67: Type accommodatie | K67: No (*) | M67: IST: accommodation_type (umbenennen); E korrigiert: accomodation_types→accommodation_types | N67: field_74_1 | O67: hotels
B68: hotel_classification | C68: integer | D68: many to one | E68: hotel_classifications | F68: Klassifizierung | G68: Classification | H68: Classificatie | K68: No | M68: E korrigiert: hotels_classifications→hotel_classifications | N68: field_75_1 | O68: hotels
B69: hotel_activities | C69: integer | D69: many to one | E69: activities | F69: Aktivitäten | G69: Activities | H69: Activiteiten | K69: No (*) | N69: field_1402_1 | O69: hotels | U69: Import but hide this field. | AA69: 07.04.: Bestätigung, dass "hiding" ok
A70: COMMENT: Following field was down the side; therefore DEV implemented a Flow. Parking it here now make it easier to deal with the "Non"-Translation
B71: total_number_of_rooms | C71: integer | D71: numerical | F71: Anzahl Zimmer | G71: Number of Rooms | H71: Aantal kamers | K71: No | M71: IST in hotels_translations | N71: field_1376_1 | O71: hotels | U71: 30.06.26: NEW ORDER for this field
B72: web_price_calculator | E72: NO Import! | F72: Web Preisrechner Ja/Nein | G72: Web Price Calculator Yes/No | H72: Web price calculator ja/nee | N72: field_1335_1 | O72: hotels | AA72: 08.04.: Nicht benötigt.
B73: colour | E73: NO Import! | F73: Farbwahl | G73: Colour Choice | H73: kleur | N73: field_665_1 | O73: hotels
B74: brox_category | E74: NO Import! | F74: Rubrik | G74: Heading | H74: Rubriek | N74: field_804_1 | O74: hotels
B75: brox_headline | E75: NO Import! | F75: Headline | G75: Headline | H75: Headline | N75: field_661_1 | O75: hotels
B76: brox_subline | E76: NO Import! | F76: Subline | G76: Sub-line | H76: Subline | N76: field_662_1 | O76: hotels
B77: url_alias | E77: NO Import! | F77: URL Alias | G77: URL Alias | H77: URL Alias | N77: field_1459_1 | O77: hotels
A79: Section (open) | B79: section_descriptions | C79: alias | D79: group-detail | F79: Beschreibung Hotel | G79: Hotel Description | H79: Beschrijving hotel
B80: subline_location | C80: string | D80: text input | F80: Ort (in Sub-Unterschrift) | G80: Location (within Subline) | H80: Locatie (in subtitel) | I80: Ortsangabe für Sub-Unterschrift zum Hotel. | K80: Yes | L80: hotels_descriptions_translations | M80: IST in hotels_translations | N80: field_57_1 | O80: hotels | AA80: 07.04.: Muss erhalten bleiben.
B81: teaser | C81: text | D81: text area | F81: Einleitungstext | G81: Teaser Text | H81: Teaser text | I81: Max. 2 Sätze zur Beschreibung: Art und USPs. | K81: Yes | L81: hotels_descriptions_translations | M81: IST in hotels_translations | N81: field_58_1 | O81: hotels
B82: description_short | C82: text | D82: text area | F82: Hotelbeschreibung | G82: Description | H82: Omschrijving | I82: Ausführlichere Beschreibung des Hotels (Vermeidung von Dopplungen zum Teaser). | K82: Yes | L82: hotels_descriptions_translations | M82: IST in hotels_translations | N82: field_169_1 | O82: hotels
B83: description_surrounding | C83: text | D83: text area | F83: Lagebeschreibung | G83: Location Description | H83: Locatiebeschrijving | K83: Yes | L83: hotels_descriptions_translations | M83: IST in hotels_translations | N83: field_59_1 | O83: hotels
B84: description_rooms | C84: text | D84: text area | F84: Allgem. Zimmerbeschreibung | G84: Overall Room Description | H84: Algemene kamerbeschrijving | I84: Note: Actually no import into Tour32. | K84: Yes | L84: hotels_descriptions_translations | M84: IST in hotels_translations | N84: field_60_1 | O84: hotels
B85: remarks_arrival | C85: text | D85: text area | F85: Anreisehinweise | G85: Transfer / Access Info | H85: Bereikbaarheid | K85: Yes | L85: hotels_descriptions_translations | M85: IST in hotels_translations | N85: field_61_1 | O85: hotels
A87: Builder (layer right side) | B87: description_supplementary | C87: json | D87: repeater (json) | F87: Ergänzende Beschreibungen | G87: Supplementary Descriptions | H87: Aanvullende beschrijvingen | M87: IST: description_supplementary (JSON) | AA87: 07.04. "Ergänzende Beischreibungen" - KEIN Rich Text Editor.
B88: headline | D88: text area (in repeater) | F88: Überschrift | G88: Headline | H88: Koptekst | K88: Yes | L88: hotels_descriptions_translations | M88: Supplementary: SOLL als JSON-Repeater description_supplementary in hotels_descriptions_translations (Felder headline/text, §Kurzregel); DEV-IST: headline_and_text (kombiniert)
B89: text | D89: text input (in repeater) | F89: Text | G89: Text | H89: Tekst | K89: Yes | L89: hotels_descriptions_translations | M89: Supplementary: SOLL als JSON-Repeater description_supplementary in hotels_descriptions_translations (Felder headline/text, §Kurzregel); DEV-IST: headline_and_text (kombiniert)
A91: Tab | B91: tab_price_infos | C91: alias | D91: group-raw | F91: Preis-Infos | G91: Price Info | H91: Prijsinformatie
A92: Section (open) | B92: section_price_infos | C92: alias | D92: group-detail | F92: Preis-relevante Infos | G92: Price-relevant Information | H92: Prijsrelevante informatie
B93: services_included | C93: text | D93: text area | F93: Eingeschlossene Leistungen | G93: Included Services | H93: Inbegrepen diensten | K93: Yes | L93: hotels_price_infos_translations | M93: IST in hotels_translations_3 | N93: field_63_1 | O93: hotels
B94: services_not_included | C94: text | D94: text area | F94: Nicht eingeschlossene Leistungen | G94: Services not Included | H94: Niet-inbegrepen diensten | K94: Yes | L94: hotels_price_infos_translations | M94: IST in hotels_translations_3 | N94: field_64_1 | O94: hotels
B95: service_highlights | C95: text | D95: text area | F95: Indirekte Vorteile | G95: Indirect Benefits | H95: Indirecte voordelen | I95: aka "Smilie" | K95: Yes | L95: hotels_price_infos_translations | M95: IST in hotels_translations_3 | N95: field_364_1 | O95: hotels | AA95: 07.04.: "Indirekte Vorteile."
B96: minimum_stay | C96: string | D96: drop down | F96: Mindestaufenthalt | G96: Minimum Stay | H96: Minimumverblijf | K96: No (*) | M96: IST in hotels_translations_3 | N96: NEW | O96: hotels | U96: see sheet "Field lists"
B97: minimum_stay_additions | C97: string | D97: text input | F97: Alternativer Text | G97: Alternative Text | H97: Alternatieve tekst | K97: Yes | L97: hotels_price_infos_translations | M97: IST in hotels_translations_3 | N97: field_65_1 | O97: hotels | U97: Import all exisiting data into this field.
B98: deviating_cancellation_terms | C98: text | D98: text area | F98: Abweichende Stornobedingungen? | G98: Deviating Cancellation Conditions? | H98: Afwijkende annuleringsvoorwaarden? | K98: Yes | L98: hotels_price_infos_translations | M98: IST: deviating_cancelation_terms (umbenennen); IST in hotels_translations_3 | N98: field_1390_1 | O98: hotels | V98: siehe https://kono.getoutline.com/doc/hotels-feld-analysen-nPVDgvm1Mp#h-empfehlungen-1
B99: children_policy | C99: text | D99: text area | F99: Kinder-Policy des Hotels | G99: Children Policy of Hotel | H99: Kinderbeleid van het hotel | K99: Yes | L99: hotels_price_infos_translations | M99: IST in hotels_translations_3 | N99: field_68_1 | O99: hotels | V99: ggf. Textbausteine? (vgl. "Trinkgeld")
B100: important_information | C100: text | D100: text area | F100: Wichtige Informationen | G100: Important Information | H100: Belangrijke informatie | K100: Yes | L100: hotels_price_infos_translations | M100: K-Casing; IST in hotels_translations_3 | N100: field_67_1 | O100: hotels
B101: mobility_advice_text | D101: see comment | F101: Text Mobilitätshinweis | G101: Text Mobility Advice | H101: Tekst mobiliteitsadvies | I101: Text is being set under "Global Data" > "Mobility Advice Text". | K101: No (*) | M101: E geleert (übersetzbares Feld); IST in hotels_translations_3 | N101: field_1529_1 | O101: hotels | AA101: 07.04.: 1 Text für alle Hotels - nur in DE nötig.
A103: Builder (layer right side) | B103: price_infos_supplementary | C103: json | D103: repeater (json) | F103: Ergänzende Beschreibungen | G103: Supplementary Descriptions | H103: Aanvullende beschrijvingen | AA103: 07.04. "Ergänzende Beischreibungen" - KEIN Rich Text Editor.
B104: headline | D104: text area (in repeater) | F104: Überschrift | G104: Headline | H104: Koptekst | K104: Yes | L104: hotels_price_infos_translations | M104: Supplementary: SOLL als JSON-Repeater price_info_supplementary in hotels_price_infos_translations (Felder headline/text, §Kurzregel); DEV-IST: headline_and_text (kombiniert)
B105: text | D105: text input (in repeater) | F105: Text | G105: Text | H105: Tekst | K105: Yes | L105: hotels_price_infos_translations | M105: Supplementary: SOLL als JSON-Repeater price_info_supplementary in hotels_price_infos_translations (Felder headline/text, §Kurzregel); DEV-IST: headline_and_text (kombiniert)
A107: Section (open) | B107: section_attributes | C107: alias | D107: group-detail | F107: Merkmale (IT-Systeme) | G107: Attributes (System Inputs) | H107: Kenmerken (systeeminvoer)
B108: children_free_age | C108: integer | D108: numeric (length max: 2) | F108: Max. Kindesalter kostenfrei | G108: Max. Child Age | H108: Max. kinderleeftijd | I108: Maximales Alter (in Jahren) bis zu dem Kinder kostenlos mitreisen. | K108: No | M108: IST in hotels_translations_3 | N108: field_1375_1 | O108: hotels | U108: - | V108: Was machen wir hier bei bzgl. Übersetzungen?
B109: children_free_number | C109: integer | D109: numeric (length max: 1) | F109: Anzahl Kinder kostenfrei | G109: Number of Children Free of Charge | H109: Aantal kinderen gratis | I109: Anzahl der Kinder die kostenlos mitreisen können. | K109: No | M109: IST in hotels_translations_3 | N109: field_1378_1 | O109: hotels | U109: -
A111: Tab | B111: tab_calculator_inputs | C111: alias | D111: group-raw | F111: Kalkulations-Grunddaten | G111: Calculation Basics | H111: Calculatie-basis
A112: Block | B112: block_price_basics | C112: alias | D112: group-raw | F112: - | G112: - | H112: -
A113: Section (closed) | B113: section_price_basics | C113: alias | D113: group-detail | F113: Preisgrundlagen | G113: Price Basics | H113: Prijsgrondslagen
A114: Builder (layer right side) | B114: room_categories | C114: json | D114: repeater (json) | F114: Zimmer-Kategorien | G114: Room Categories | H114: Kamercategorieën | M114: Key ergänzt: room_categories
...

Sheet #2 cruises
A1: Collection | B1: cruises
A2: Remarks | B2: Cruises / Kreuzfahrten
A3: Date / Update | B3: 2026-06-29
A4: Legend | B4: Checked | C4: Changes | D4: Analysis done | E4: Analysis tbd
A6: Details for Directus Set-up | K6: Translatable? | N6: Import Details "kreuzfahrten" | U6: Remarks / Comments | X6: Legacy | Y6: Stakeholder Notes
A7: Special field type | B7: field_key Directus | C7: data_type | D7: interface (characters max) | E7: Relation (Sub-Collection) | F7: Label DE | G7: Label GB | H7: Label NL | I7: Info-Text (below the field) | K7: Yes / No | L7: Naming Translation-Collection | N7: fieldid Primarix | O7: parent table | U7: Remarks for DEV (field set-up and Import) | V7: Remarks + Tasks internal | X7: tbd after import | Y7: TOPS Bernd | Z7: TOPs Birgit | AA7: Notes Client
A9: Above Tabs | B9: header | C9: alias | D9: header (presentation) | F9: — | G9: — | H9: — | I9: Page header above the tabs. Shows title + subtitle; no own label. | K9: No | U9: Hidden Standard (hotels): interface "header", special [alias,no-data], group: null. options.title="{{name}}", options.subtitle="{{object_id}} - {{season.season}}". Condition "Hide on create" (id _null -> hidden, clear_hidden_value_on_save).
A10: Above Tabs | B10: sell_prices_status | C10: string | D10: select-dropdown | F10: Verkaufspreis-Status | G10: Sell Prices Status | H10: Verkoopprijsstatus | I10: Tracks async sell price calculation state | K10: No | U10: hidden, root sync field
A11: Above Tabs | B11: sell_prices_updated_at | C11: timestamp | D11: datetime | F11: Aktualisiert am | G11: Sell Prices Updated At | H11: Bijgewerkt op | I11: Last successful sell price calculation | K11: No | U11: hidden, root sync field
A12: Tab-Navigation | B12: ui_tabs | C12: alias | D12: tabs | F12: - | G12: - | H12: -
A14: Tab | B14: tab_master_data | C14: alias | D14: group-raw | F14: Stammdaten | G14: Master Data | H14: Stamgegevens
A15: Block | B15: block_publication | C15: alias | D15: group-raw | F15: - | G15: - | H15: -
A16: Section (open) | B16: section_id_status | C16: alias | D16: group-detail | F16: Status & Veröffentlichung | G16: Status & Publication | H16: Status & publicatie
B17: object_id | C17: integer | D17: integer | E17: numerical | F17: Objekt-ID | G17: Object-ID | H17: Object-ID | I17: Automatically set. | K17: No | N17: oid | O17: kreuzfahrten
B18: object_info_primarix | C18: string | D18: string | E18: text input | F18: Objekt Titel Primarix | G18: Object Title Primarix | H18: Objecttitel Primarix | K18: No | N18: object_info | O18: kreuzfahrten | U18: Non editable field
B19: season | C19: integer | D19: integer | E19: M2O | F19: Saison-Gültigkeit | G19: Season Validity | H19: Seizoengeldigheid | K19: No | N19: season | O19: tours | U19: Transformed value from "object info": "25_" = "2025"
B20: status_primarix | C20: string | D20: select-dropdown | F20: Status Primarix | G20: Status Primarix | H20: Status Primarix | I20: 4 Werte: Draft / Published / Unpublished / Archived (Field-Configs §1.1) | K20: No | N20: status (?) | O20: kreuzfahrten
B21: date_updated | C21: dateTime | D21: date | F21: Zuletzt aktualisiert | G21: Last Update | H21: Laatste update | K21: No | N21: (?) | O21: kreuzfahrten
B22: user_updated | C22: uuid | D22: M2O | E22: directus_users | F22: von | G22: by | H22: door | K22: No | N22: (?) | O22: kreuzfahrten | U22: Pls show the last editor if possible (in case information is not available in Primarix show "unknown" or similar)
A24: Section (open) | B24: section_botg_filter | C24: alias | D24: group-detail | F24: BOTG-Firmen-Zuordnung | G24: BOTG Company Assignment | H24: BOTG-bedrijfstoewijzing
B25: partner_visibility | C25: string | D25: radio | K25: No | L25: hotel
B26: partner_selected | C26: integer | D26: M2O | E26: partner | K26: No | L26: hotel | N26: NEW | O26: tours
A28: Block | B28: block_contacts | C28: alias | D28: group-raw | F28: - | G28: - | H28: -
A29: Section (open) | B29: section_reservation | C29: alias | D29: group-detail | F29: Reservierung | G29: Reservation | H29: Reservering
B30: travel_id_karawane | C30: string | D30: text field | E30: - | F30: Reisenummer | G30: Trip Number | H30: Reisnummer | K30: No | N30: field_677_1 | O30: kreuzfahrten | U30: Import but hide this field.
B31: id_tour32 | C31: string | D31: text field | E31: - | F31: ID Tour32 | G31: ID Tour32 | H31: ID Tour32 | I31: Tour-Angebots-Nr. (falls vorhanden) | K31: No | N31: field_678_1 | O31: kreuzfahrten
A33: Tab | B33: tab_description | C33: alias | D33: group-raw | F33: Beschreibung | G33: Description | H33: Beschrijving
A34: Section (open) | B34: section_classification | C34: alias | D34: group-detail | F34: Klassifizierung | G34: Classification | H34: Indeling
D35: — | F35: Rubrik | N35: field_759_1 | O35: kreuzfahrten | U35: NO Import
B36: countries | C36: alias | D36: M2M | E36: countries | F36: Länder | G36: Countries | H36: Landen | K36: No | N36: field_680_1 | O36: kreuzfahrten | U36: Adapt import: Actually field contains text inputs. Match to entry in new collection. Report missing data separatly!
B37: destinations | C37: alias | D37: M2M | E37: destination | F37: Kontinente | G37: Continents | H37: Continenten | K37: No | N37: field_679_1 | O37: kreuzfahrten | U37: Adapt import: Actually field contains text inputs. Match to entry in new collection. Report missing data separatly!
B38: cruise_types | C38: alias | D38: M2M | E38: cruise_types | F38: Art der Kreuzfahrt | G38: Cruise Type | H38: Cruisetype | K38: No | N38: field_681_1 | O38: kreuzfahrten | U38: see sheet "Field lists Karawane"
B39: real_url | C39: string | D39: text input | F39: Real URL der Reise | G39: Real URL of Trip | H39: Real URL van de reis | K39: No | N39: field_793_1 | O39: kreuzfahrten | U39: Import but hide this field. | V39: Mit TravelUp zu klären.
D40: — | F40: Domainzuordnung | N40: field_682_1 | O40: kreuzfahrten | U40: NO Import
B41: travel_expert | C41: integer | D41: drop down (many to one) | E41: travel_expert | F41: Reiseexperte | G41: Travel Expert | H41: Reisexpert | K41: No | N41: field_1369_1 | O41: kreuzfahrten | U41: NO Import! | V41: Wird für Kreuzfahrten über Website gelöst. In Studienreisen aber erforderlich.
A43: Section (open) | B43: section_descriptions | C43: alias | D43: group-detail | F43: Beschreibung Kreuzfahrt | G43: Cruise Description | H43: Beschrijving cruise
B44: headline | C44: string | D44: text input | F44: Überschrift | G44: Headline | H44: Koptekst | K44: Yes | L44: cruises_descriptions_translations | N44: field_683_1 | O44: kreuzfahrten
B45: subline | C45: string | D45: text input | F45: Untertitel | G45: Subtitle | H45: Ondertitel | K45: Yes | L45: cruises_descriptions_translations | N45: field_684_1 | O45: kreuzfahrten
B46: teaser | C46: text | D46: text area | F46: Einleitung | G46: Introduction | H46: Inleiding | K46: Yes | L46: cruises_descriptions_translations | N46: field_685_1 | O46: kreuzfahrten
B47: ship | C47: text | D47: md-editor | F47: Schiffsbeschreibung (Ihr Schiff) | G47: Ship Description (Your Ship) | H47: Scheepsbeschrijving (Uw schip) | K47: Yes | L47: cruises_descriptions_translations | N47: field_791_1 | O47: kreuzfahrten | U47: Import: Change HTML- to MD-Format
B48: at_a_glance | C48: text | D48: md-editor | F48: Auf einen Blick | G48: At a Glance | H48: In één oogopslag | K48: Yes | L48: cruises_descriptions_translations | N48: field_789_1 | O48: kreuzfahrten | U48: Import: Change HTML- to MD-Format
A50: Tab | B50: tab_travel_programme | C50: alias | D50: group-raw | F50: Reiseprogramm | G50: Travel Programme | H50: Reisprogramma
A51: Section (open) | B51: section_travel_programme | C51: alias | D51: group-detail | F51: Reiseprogramm | G51: Travel Programme | H51: Reisprogramma
B52: travel_itinerary | C52: text | D52: text area? | F52: Reiseverlauf | G52: Itinerary | H52: Reisverloop | N52: field_756_1 | O52: kreuzfahrten | U52: NO Import!
A54: Builder (layer right side) | C54: json | D54: repeater (json) | F54: Reiseprogramm | G54: Travel Programme | H54: Reisprogramma
B55: day_destinations | D55: repeater: text field | F55: Tagesziele (Ort/Region) | G55: Daily Destinations (place/region) | H55: Dagbestemmingen (plaats/regio) | K55: Yes | L55: cruises_programme_translations | N55: field_695_1 to 781_1 | O55: kreuzfahrten
B56: day_description | D56: repeater: text area | F56: Beschreibung Tagesprogramm | G56: Daily Programme Description | H56: Beschrijving dagprogramma | K56: Yes | L56: cruises_programme_translations | N56: field_695_1 to 781_1 | O56: kreuzfahrten
B57: day_accommodation_note | D57: repeater: text area | F57: Übernachtungshinweis | G57: Accommodation Note | H57: Overnachtingsinfo | K57: Yes | L57: cruises_programme_translations | N57: field_695_3 to 781_1 | O57: kreuzfahrten
A59: Tab | B59: tab_price_infos | C59: alias | D59: group-raw | F59: Preis-Infos | G59: Price Info | H59: Prijsinformatie
A60: Section (open) | B60: section_price_infos | C60: alias | D60: group-detail | F60: Preis-relevante Infos | G60: Price-relevant Information | H60: Prijsrelevante informatie
B61: name_cruise | C61: text | D61: text area | F61: Reisetitel | G61: Trip Title | H61: Reistitel | K61: Yes | L61: cruises_price_infos_translations | N61: field_688_1 | O61: kreuzfahrten | U61: Import but hide this field.
B62: departure_arrival | C62: text | D62: text area | F62: Reise ab/bis | G62: Trip from/to | H62: Reis van/naar | K62: Yes | L62: cruises_price_infos_translations | N62: field_761_1 | O62: kreuzfahrten
B63: bord_languages | C63: json | D63: drop down json | F63: Bordsprache | G63: Language on Board | H63: Boordtaal | K63: Yes | L63: cruises_price_infos_translations | N63: NEW | O63: kreuzfahrten | U63: Values: Deutsch; Deutsch / Englisch; Englisch; Englisch / Deutsch; Englisch / Französisch; Norwegisch / Englisch; Russisch | V63: Nachzupflegen nach Import!
B64: bord_languages_additions | C64: text | D64: text area | F64: Ergänzender Text | G64: Supplementary Text | H64: Aanvullende tekst | K64: Yes | L64: cruises_price_infos_translations | N64: field_689_1 | O64: kreuzfahrten | V64: Überschreibbare Text-Vorschläge möglich? - Alternativ wie bei "Reservierung"
B65: surcharges | C65: text | D65: text area | F65: Zuschläge pro Person (€) | G65: Surcharges per Person (€) | H65: Toeslagen per persoon (€) | I65: Hier nur Zuschlags-Leistungen eingeben. | K65: Yes | L65: cruises_price_infos_translations | N65: field_690_1 | O65: kreuzfahrten
B66: services_included | C66: text | D66: md-editor | F66: Eingeschlossene Leistungen | G66: Included Services | H66: Inbegrepen diensten | K66: Yes | L66: cruises_price_infos_translations | N66: field_691_1 | O66: kreuzfahrten | U66: Import: Change HTML- to MD-Format
B67: services_not_included | C67: text | D67: text area | F67: Nicht eingeschlossene Leistungen | G67: Services not Included | H67: Niet-inbegrepen diensten | I67: Aufzählung, mit Komma getrennt (z.B. Reiserücktrittversicherung, Visagebühren) | K67: Yes | L67: cruises_price_infos_translations | N67: field_692_1 | O67: kreuzfahrten
B68: onboard_gratuities | C68: json | D68: drop down json | F68: Trinkgelder an Bord | G68: Gratuities on Board | H68: Fooien aan boord | K68: Yes | L68: cruises_price_infos_translations | N68: NEW | O68: kreuzfahrten | U68: Values: Trinkgelder werden nicht erwartet.; Trinkgelder sind bereits im Reisepreis eingeschlossen.; Trinkgelder sind bereits im Reisepreis eingeschlossen. | V68: Nachzupflegen nach Import!
B69: onboard_gratuities_additions | C69: text | D69: text area | F69: Ergänzender Text | G69: Supplementary Text | H69: Aanvullende tekst | K69: Yes | L69: cruises_price_infos_translations | N69: field_800_1 | O69: kreuzfahrten | V69: Überschreibbare Text-Vorschläge möglich? - Alternativ wie bei "Reservierung"
D70: — | F70: Reisepreise | N70: field_763_1 | O70: kreuzfahrten | U70: NO Import
B71: important_information | C71: text | D71: md-editor | F71: Wichtige Informationen | G71: Important Information | H71: Belangrijke informatie | K71: Yes | L71: cruises_price_infos_translations | N71: field_694_1 | O71: kreuzfahrten | U71: Import: Change HTML- to MD-Format
B72: good_to_know | C72: text | D72: md-editor | F72: Gut zu wissen | G72: Good to Know | H72: Goed om te weten | I72: Hinweise, Rabatte, Wichtiges | K72: Yes | L72: cruises_price_infos_translations | N72: field_728_1 | O72: kreuzfahrten | U72: Import: Change HTML- to MD-Format
B73: occupancy_single | C73: string | D73: text field | F73: Alleinnutzung | G73: Single Occupancy | H73: Eenpersoons gebruik | K73: Yes | L73: cruises_price_infos_translations | N73: field_762_1 | O73: kreuzfahrten
B74: participants_legacy | C74: text | D74: text area | F74: Teilnehmer (ALT) | G74: Participants (OLD) | H74: Deelnemers (OUD) | I74: Bitte Angaben nur noch unter "Merkmake IT-Systeme" | K74: Yes | L74: cruises_price_infos_translations | N74: field_693_1 | O74: kreuzfahrten | U74: Default Text: Bis [n] Wochen vor Reisebeginn zu erreichende Teilnehmerzahl: [n]. | V74: Min-Wert für Tour 32 erforderlich?
B75: deviating_cancellation_terms_selector | C75: json | D75: drop down json | F75: Abweichende Stornobedingungen? | G75: Deviating Cancellation Conditions? | H75: Afwijkende annuleringsvoorwaarden? | K75: Yes | L75: cruises_price_infos_translations | N75: NEW | U75: Values: Keine; Für diese Reise gelten abweichende Stornogebühren.; Es gelten besondere Storno- und Umbuchungsbedingungen gemäß den AGB der Reederei.; Storno- und Zahlungsbedingungen: www.karawane.de/kreuzfahrt-agb. | V75: Nachzupflegen nach Import!
B76: deviating_cancellation_terms_text | C76: text | D76: text area | F76: Stornobedingungen: Ergänzender Text | G76: Supplementary Text | H76: Aanvullende tekst | K76: Yes | L76: cruises_price_infos_translations | N76: field_767_1 | O76: kreuzfahrten | V76: Überschreibbare Text-Vorschläge möglich? - Alternativ wie bei "Reservierung"
B77: mobility_advice_text | C77: text | D77: text area (readonly) | E77: — | F77: Text Mobilitätshinweis | G77: Text Mobility Advice | H77: Tekst mobiliteitsadvies | I77: Text wird unter "Global Data" gesetzt (readonly). Gespeichert in cruises_price_infos_translations. | K77: No (*) | N77: field_1375_1 | O77: kreuzfahrten | U77: Non editable field. - Automatically active. - Texts defined in seperate collections we'll use for all products - see sheet "Field lists Karawane"
A79: Section (open) | B79: section_attributes | C79: alias | D79: group-detail | F79: Merkmale (IT-Systeme) | G79: Attributes (System Inputs) | H79: Kenmerken (systeeminvoer)
B80: participants_min | C80: integer | D80: numeric | F80: Mindestanzahl Teilnehmer | G80: Minimum Number of Participants | H80: Minimum aantal deelnemers | I80: Bis N Wochen vor Reisebeginn zu erreichende Teilnehmerzahl: X. | K80: No | N80: field_693_1 | O80: kreuzfahrten | U80: Default Text: Bis [n] Wochen vor Reisebeginn zu erreichende Teilnehmerzahl: [n]. | V80: Min-Wert für Tour 32 erforderlich?
B81: participants_max | C81: integer | D81: numeric | F81: Maximalanzahl Teilnehmer | G81: Maximum Number of Participants | H81: Maximaal aantal deelnemers | K81: No | N81: NEW
B82: week_min_before_start | C82: integer | D82: numeric | F82: Min. Teilnehmer bis x Wochen vor Reiseantritt | G82: Min. Participants up to x Weeks before Departure | H82: Min. deelnemers tot x weken voor vertrek | K82: No | N82: NEW
A84: Tab | B84: tab_calculator_inputs | C84: alias | D84: group-raw | F84: Kalkulations-Grunddaten | G84: Calculation Basics | H84: Calculatie-basis
A85: Block | B85: block_price_basics | C85: alias | D85: group-raw | F85: - | G85: - | H85: -
A86: Section (closed) | B86: section_price_basics | C86: alias | D86: group-detail | F86: Preisgrundlagen | G86: Price Basics | H86: Prijsgrondslagen
A88: Builder (layer right side) | C88: json | D88: repeater (json) | F88: Kabinen-Kategorien | G88: Cabin Categories | H88: Hutcategorieën
A89: COMMENT only | B89: "cruises_cabin_categories" - defines the "blocks" within calculator (like "room_categories" in hotels)
B90: cabin_category | C90: integer | D90: many to one | E90: cruise_cabin_categories | F90: Kabinen-Kategorie | G90: Cabin Category | H90: Hutcategorie | K90: No | N90: field_730_1 | O90: kreuzfahrten_reisekat_zb_kabkat
B91: cabin_category_additions | C91: string | D91: text input | E91: cruises_cabin_categories | F91: Alternative Bezeichnung | G91: Alternative Name | H91: Alternatieve benaming | K91: Yes | L91: cruises_cabin_categories_translations
B92: cabin_category_description | C92: text | D92: text area | E92: cruises_cabin_categories | F92: Beschreibung Kabinenkategorie | G92: Description Cabin Category | H92: Omschrijving hutcategorie | K92: Yes | L92: cruises_cabin_categories_translations
B93: cabin_category_booking_code | C93: string | D93: text input | E93: cruises_cabin_categories | F93: Buchungscode Supplier | G93: Supplier Booking Code | H93: Supplier boekingscode | K93: No
B94: cabin_category_tour32_name | C94: string | D94: text input | E94: cruises_cabin_categories | F94: Bezeichnung TOUR32 | G94: Name TOUR32 | H94: Benaming TOUR32 | K94: No
B95: cabin_category_from | C95: boolean | D95: checkbox (boolean) | E95: cruises_cabin_categories | F95: Ab-Preis | G95: Starting Price | H95: Vanafprijs | K95: No
A96: COMMENT | B96: Sortierung = Directus-System-Feld `sort` (kein eigenes Feld) | V96: Umbenannt 4.3: _rank -> _sort (Directus-Standard-Sortierfeld)
A98: Builder (layer right side) | C98: json | D98: repeater (json) | F98: Preis-Termine | G98: Price Dates | H98: Prijsdata
A99: COMMENT only | B99: "cruises_price_dates" - defines the "rows" within calculator (same as "price_periods" in hotels)
C100: integer | D100: numerical | F100: Abfahrtsnummer | G100: Departure Number | H100: Vertreknummer | K100: No | N100: field_760_1 | O100: kreuzfahrten_reisetermine | U100: NO Import!
B101: departure_frequencies | C101: alias | D101: multi select | E101: cruises_frequencies | F101: Abfahrts-Frequenzen | G101: Departure Frequencies | H101: Vertrekfrequenties | I101: M2M zu separater Sub-Collection cruises_frequencies (vorläufig, statt trips_frequencies). | K101: No (*) | N101: field_745_1 | O101: kreuzfahrten_reisetermine | V101: Feld nach Import nochmals zu reduzieren.
B102: date_departure | C102: dateTime | D102: date | E102: cruises_price_dates | F102: Abfahrtsdatum | G102: Departure Date | H102: Vertrekdatum | K102: No | N102: field_746_1 | O102: kreuzfahrten_reisetermine
B103: date_arrival | C103: dateTime | D103: date | E103: cruises_price_dates | F103: Ankunftsdatum | G103: Arrival Date | H103: Aankomstdatum | K103: No | N103: field_746_2 | O103: kreuzfahrten_reisetermine
A104: COMMENT | B104: Sortierung = Directus-System-Feld `sort` (kein eigenes Feld) | V104: Umbenannt 4.3: _rank -> _sort (Directus-Standard-Sortierfeld)
A106: Builder (layer right side) | C106: json | D106: repeater (json) | F106: Belegungen | G106: Occupancies | H106: Bezettingen
A107: COMMENT only | B107: "cruises_occupancies" - defines the "columns" within calculator (same as "occupancy" in hotels)
B108: occupancy | C108: integer | D108: many to one | E108: cruise_occupancies | F108: Belegung | G108: Cabin Occupancy | H108: Bezetting | K108: No | N108: field_773_1 | O108: kreuzfahrten_belegung | U108: 2 values: Doppelbelegung; Einzelbelegung | V108: Nachzupflegen nach Import! - Zu beachten, gf. Implikationen auf Kalkulator.
B109: occupancy_from | C109: boolean | D109: checkbox (boolean) | E109: cruises_occupancies | F109: Ab-Preis | G109: Starting Price | H109: Vanafprijs | K109: No
A110: COMMENT | B110: Sortierung = Directus-System-Feld `sort` (kein eigenes Feld) | V110: Umbenannt 4.3: _rank -> _sort (Directus-Standard-Sortierfeld)
A112: Tab | B112: tab_price_calculation | C112: alias | D112: group-raw | F112: Preise | G112: Prices | H112: Prijzen
A113: Section (open) | B113: section_units_margins | C113: alias | D113: group-detail | F113: Einheiten & Margen | G113: Units & Margins | H113: Eenheden & marges
B114: buy_price_type | C114: string | D114: select-dropdown | E114: cruises_price_calculation_translations | F114: Einkaufspreis-Typ | G114: Buy Price Type | H114: Inkoopprijstype | K114: No
B115: sell_price_type | C115: string | D115: select-dropdown | E115: cruises_price_calculation_translations | F115: Verkaufspreis-Typ | G115: Sell Price Type | H115: Verkoopprijstype | K115: No
B116: percentage_type | C116: string | D116: select-dropdown | E116: cruises_price_calculation_translations | F116: Prozent-Typ | G116: Percentage Type | H116: Percentagetype | K116: No
...

Sheet #3 excursions (aka daytrips)
A1: Collection | B1: excursions
A2: Remarks | B2: Daytrips / Tagestouren / Excursions.
A3: Date / Update | B3: 46195
A4: Legend | B4: Checked | C4: Changes | D4: Analysis done | E4: Analysis tbd
A6: Details for Directus Set-up | K6: Translatable? | N6: Import Details "tours" | U6: Remarks / Comments | X6: Legacy | Y6: Stakeholder Notes
A7: Special field type | B7: field_key Directus | C7: data_type | D7: interface (characters max) | E7: Relation (Sub-Collection) | F7: Label DE | G7: Label GB | H7: Label NL | I7: Info-Text (below the field) | K7: Yes / No | L7: Naming Translation-Collection | N7: fieldid Primarix | O7: parent table | U7: Remarks for DEV (field set-up and Import) | V7: Remarks + Tasks internal | X7: tbd after import | Y7: TOPS Bernd | Z7: TOPs Birgit | AA7: Notes Client
A9: Above Tabs | B9: header | C9: alias | D9: header (presentation) | F9: Header | G9: Header | H9: Header | I9: Page header above the tabs. Shows title + subtitle; no own label. | K9: No | U9: Hidden Standard (hotels): interface "header", special [alias,no-data], group: null. options.title="{{name}}", options.subtitle="{{object_id}} - {{season.season}}". Condition "Hide on create" (id _null -> hidden, clear_hidden_value_on_save).
A10: Above Tabs | B10: sell_prices_status | C10: string | D10: select-dropdown | F10: Verkaufspreis-Status | G10: Sell Prices Status | H10: Verkoopprijsstatus | I10: Tracks async sell price calculation state | K10: No | U10: hidden, root sync field
A11: Above Tabs | B11: sell_prices_updated_at | C11: timestamp | D11: datetime | F11: Aktualisiert am | G11: Sell Prices Updated At | H11: Bijgewerkt op | I11: Last successful sell price calculation | K11: No | U11: hidden, root sync field
A12: Tab-Navigation | B12: ui_tabs | C12: alias | D12: tabs | F12: - | G12: - | H12: -
A14: Tab | B14: tab_master_data | C14: alias | D14: group-raw | F14: Stammdaten | G14: Master Data | H14: Stamgegevens
A15: Block | B15: block_publication | C15: alias | D15: group-raw | F15: - | G15: - | H15: -
A16: Section (open) | B16: section_id_status | C16: alias | D16: group-detail | F16: Status & Veröffentlichung | G16: Status & Publication | H16: Status & publicatie
B17: object_id | C17: integer | D17: numerical | F17: Objekt-ID | G17: Object-ID | H17: Object-ID | I17: Automatically set. | K17: No | N17: oid | O17: tours
B18: object_info_primarix | C18: string | D18: text input | F18: Objekt Titel Primarix | G18: Object Title Primarix | H18: Objecttitel Primarix | K18: No | N18: object_info | O18: tours | U18: Non editable field
B19: season | C19: integer | D19: M2O | E19: seasons | F19: Saison-Gültigkeit | G19: Season Validity | H19: Seizoengeldigheid | K19: No | N19: season | O19: tours | U19: Transformed from "object_info": "25_" = "2025"
B20: status_primarix | C20: string | D20: dropdown | F20: Status Primarix | G20: Status Primarix | H20: Status Primarix | K20: No | N20: status (?) | O20: tours | U20: Type per Namenskonv. 4.5: string+dropdown (NOT M2O); source = freigabe (0/1) | V20: war M2O im Daytrips-Brief
B21: internal_remarks | C21: text | D21: text area | F21: Interne Hinweise | G21: Internal Remarks | H21: Interne opmerking | I21: Internal Remarks from Primarix. Consider future "Comments" feature. | K21: No | N21: field_1332_1 | O21: tours | U21: Field NOT translatable in future. Import all internal_remarks (also other languages) into this field.
B22: date_updated | C22: dateTime | D22: date | F22: Zuletzt aktualisiert | G22: Last Update | H22: Laatste update | K22: No | N22: (?) | O22: tours
B23: user_updated | C23: uuid | D23: M2O | E23: directus_users | F23: von | G23: by | H23: door | K23: No | N23: (?) | O23: tours | U23: Show last editor if possible; else "unknown".
A25: Section (open) | B25: section_botg_filter | C25: alias | D25: group-detail | F25: BOTG-Firmen-Zuordnung | G25: BOTG Company Assignment | H25: BOTG-bedrijfstoewijzing
B26: partner_visibility | C26: string | D26: radio button (all / selected) | K26: No | N26: NEW | V26: Umbenannt gem. Namenskonv. 4.6 (verbindlich): partner_type -> partner_visibility
B27: partner_selected | C27: alias | D27: M2M | E27: partner | K27: No | N27: field_1102_1 | O27: tours | U27: M2M only visible if radio != "all" (conditional). | V27: Umbenannt 4.6: partner -> partner_selected. OFFEN: Daytrips-Quelle war M2O; vehicles nutzt M2M - Kardinalitaet bestaetigen.
A29: Block | B29: block_contacts | C29: alias | D29: group-raw | F29: - | G29: - | H29: -
A30: Section (open) | B30: section_operator | C30: alias | D30: group-detail | F30: Adresse Veranstalter | G30: Operator Address | H30: Adres organisator
B31: operator_direct | C31: string | D31: radio button (Tour Operator / No Tour Operator) | F31: Veranstalter | G31: Travel Operator | H31: Reisorganisator | K31: No | N31: NEW | U31: No import (new field): "No" / "Yes". If "Yes": dropdown filtered from booking_partner. | Y31: wie Rundreisen?
B32: operator_linked | C32: integer | D32: many to one | E32: booking_partners | F32: Ausgewählter Tour Operator | G32: Chosen Tour Operator | H32: Gekozen touroperator | K32: No | N32: NEW | U32: No import (new field): dropdown with "Travel Operators" (new sub-category in booking_partners). | AA32: 07.04.: "Inbounder" könnten an Relevanz gewinnen. Ergo: Mail-Adresse erhalten (9%) + 1 Feld (Text Area) für Rest.
A34: COMMENT | B34: Following fields if radio "Direct Booking":
B35: name_operator | C35: string | D35: text input | F35: Name (Veranstalter) | G35: Name (Operator) | H35: Naam (organisator) | K35: No | N35: field_540_1 | O35: tours
B36: street | C36: string | D36: text input | F36: Straße | G36: Street | H36: Straat | K36: No | N36: field_541_1 | O36: tours
B37: street_number | C37: string | D37: text input | F37: Hausnummer | G37: Street Number | H37: Huisnummer | K37: No | N37: field_542_1 | O37: tours
B38: postcode | C38: string | D38: text input | F38: PLZ | G38: Postal Code | H38: Postcode | K38: No | N38: field_543_1 | O38: tours
B39: place | C39: string | D39: auto complete | E39: places | F39: Ort | G39: City / Town | H39: Plaats | I39: Defines further geographical details (country, state, region). | K39: No | N39: field_544_1 | O39: tours | U39: Adapt import: field is free text. Match to entry in new collection; report missing data.
B40: location_tour32 | C40: integer | D40: M2O | E40: locations_tour32 | F40: Suchort (Tour User only) | G40: Search Location (Tour User only) | H40: Zoeklocatie (Tour User only) | K40: No | N40: field_1346_1 | O40: tours | U40: Adapt import: free text -> match to collection; report missing data.
B41: state | C41: integer | D41: M2O | E41: states | F41: Staat / Bundesland | G41: State / Province | H41: Staat / Provincie | K41: No | N41: field_545_1 | O41: tours | U41: Adapt import: free text -> match to collection; report missing data.
B42: country | C42: integer | D42: M2O | E42: countries | F42: Land | G42: Country | H42: Land | I42: Defined by "Place" | K42: No | N42: field_546_1 | O42: tours | U42: Adapt import: free text -> match to collection; report missing data.
B43: postbox_number | F43: Postfach Nr | G43: PO Box No | H43: Postbus nr | N43: field_547_1 | O43: tours | U43: NOT to be imported!
B44: phone_general | C44: string | D44: phone number | F44: Telefon (allgemein) | G44: Phone (general) | H44: Telefoon (algemeen) | K44: No | N44: field_550_1 | O44: tours | V44: ggf. als repeater (json)
B45: phone_after_hours | C45: string | D45: phone number | F45: Telefon (after hours) | G45: Phone (after hours) | H45: Telefoon (na kantooruren) | K45: No | N45: field_551_1 | O45: tours | V45: Umbenannt 1.2/4.3: phone_ah -> phone_after_hours (keine Abkuerzung)
B46: fax_general | D46: - | F46: Fax (allgemein) | G46: Fax (general) | H46: Fax (algemeen) | N46: field_552_1 | O46: tours | U46: NOT to be imported!
B47: email_general | C47: string | D47: mail | F47: Email (allgemein) | G47: E-mail (general) | H47: Email (algemeen) | K47: No | N47: field_553_1 | O47: tours
B48: website | C48: string | D48: url | F48: Webseite | G48: Web Site | H48: Homepage | K48: No | N48: field_554_1 | O48: tours
A50: Section (open) | B50: section_reservation | C50: alias | D50: group-detail | F50: Reservierung | G50: Reservation | H50: Reservering
B51: booking_channel | C51: string | D51: radio button (Partner Booking / Direct Booking) | E51: booking_partners | K51: No | N51: NEW | U51: Partner Booking OR Direct Booking. (Namenskonv. E2: booking_partner gewinnt.)
B52: booking_partner | C52: integer | D52: M2O | E52: booking_partners | F52: Buchung über | G52: Booking via | H52: Boeking via | K52: No | N52: field_904_1 | O52: tours | AA52: 07.04.: "Inbounder" könnten an Relevanz gewinnen. Ergo: Mail-Adresse erhalten (9%) + 1 Feld (Text Area) für Rest.
B53: service_provider_id_tour32 | C53: string | D53: text input | F53: Leistungsträger (Tour32 only) | G53: Service Provider (Tour32 only) | H53: Dienstverlener (Tour32 only) | K53: No | N53: field_1180_1 | O53: tours | V53: OFFEN: Namenskonv. 4.4 verbietet id_<quelle>; Rollen-Praefix noetig (Pendant zu main_id_tour_user) - Entscheidung Tommy.
B54: main_service_provider_id_tour32 | C54: string | D54: text input | F54: Haupt-Leistungsträger (Tour32 only) | G54: Main Service Provider (Tour32 only) | H54: Hoofddienstverlener (Tour32 only) | K54: No | N54: field_1385_1 | O54: tours | V54: Umbenannt 4.4 (explizites Beispiel): haupt_id_tour_user -> main_id_tour_user
A56: COMMENT | B56: Following fields if radio "Direct Booking":
B57: res_phone | D57: - | F57: Reservierung: Telefon | G57: Reservation: Telephone | H57: Reservering: Telefoon | N57: field_570_1 | O57: tours | U57: No separate field anymore. Import into "internal_remarks_reservation".
B58: res_fax | D58: - | F58: Reservierung: Fax | G58: Reservation: Fax | H58: Reservering: Fax | N58: field_571_1 | O58: tours | U58: NOT to be imported!
B59: email_booking | C59: string | D59: email | F59: Email Reservierung | G59: E-Mail Reservation | H59: Email reservering | K59: No | N59: field_572_1 | O59: tours
B60: res_email2 | D60: - | F60: Reservierung: Email 2 | G60: Reservation: E-mail 2 | H60: Reservering: Email 2 | N60: field_573_1 | O60: tours | U60: No separate field anymore. Import into "internal_remarks_reservation".
B61: contact_title | D61: - | F61: Reservierung: Kontakt Titel | G61: Reservation: Contact Title | H61: Reservering: Contactpersoon Titel | N61: field_574_1 | O61: tours | U61: No separate field anymore. Import into "internal_remarks_reservation".
B62: contact_greeting | D62: - | F62: Reservierung: Kontakt Anrede | G62: Reservation: Contact Salutation | H62: Reservering: Contactpersoon Aanhef | N62: field_575_1 | O62: tours | U62: No separate field anymore. Import into "internal_remarks_reservation".
B63: contact_firstname | D63: - | F63: Reservierung: Kontakt Vorname | G63: Reservation: Contact First Name | H63: Reservering: Contactpersoon Voornaam | N63: field_576_1 | O63: tours | U63: No separate field anymore. Import into "internal_remarks_reservation".
B64: contact_name | D64: - | F64: Reservierung: Kontakt Name | G64: Reservation: Contact Surname | H64: Reservering: Contactpersoon Naam | N64: field_577_1 | O64: tours | U64: No separate field anymore. Import into "internal_remarks_reservation".
B65: internal_remarks_reservation | C65: text | D65: text area | F65: Interne Buchungsinfos /-Hinweise | G65: Internal Reservation Infos / Remarks | H65: Interne boekingsinfo / -opmerkingen | I65: Internal notes and additional contact details. | K65: No | N65: field_578_1 | O65: tours | U65: All data above fused into this field; <br> as separation.
A67: COMMENT | B67: All fields within Tab "Banking Details" will be not imported.
A69: Tab | B69: tab_description | C69: alias | D69: group-raw | F69: Beschreibung | G69: Description | H69: Beschrijving
A70: Section (open) | B70: section_classifications | C70: alias | D70: group-detail | F70: Klassifizierung | G70: Classification | H70: Indeling
B71: destination | C71: integer | D71: M2O | E71: destinations | F71: Kontinent | G71: Continent | H71: Continent | K71: No (*) | N71: field_910_1 | O71: tours
B72: countries | C72: alias | D72: M2M | E72: countries | F72: Länder | G72: Countries | H72: Landen | K72: No (*) | N72: field_1069_1 | O72: tours | U72: Countries (multiple) may differ from operator address above.
B73: travel_categories | C73: alias | D73: M2M | E73: travel_categories | F73: Reiseart | G73: Travel Type | H73: Type Reis | K73: No (*) | N73: field_556_1 | O73: tours
B74: colour | E74: NO Import! | F74: Farbwahl | G74: Colour Choice | H74: Kleur | N74: field_669_1 | O74: tours | U74: NO Import!
B75: brox_category | E75: NO Import! | F75: Rubrik | G75: Heading | H75: Rubriek | N75: field_807_1 | O75: tours | U75: NO Import! Legacy CMS field.
B76: brox_headline | E76: NO Import! | F76: Headline | G76: Headline | H76: Headline | N76: field_908_1 | O76: tours | U76: NO Import! Legacy CMS field.
B77: brox_subline | E77: NO Import! | F77: Subline | G77: Sub-line | H77: Subline | N77: field_909_1 | O77: tours | U77: NO Import! Legacy CMS field.
B78: url_alias | E78: NO Import! | F78: URL Alias | G78: URL Alias | H78: URL Alias | N78: field_1465_1 | O78: tours | U78: NO Import!
A80: Section (open) | B80: section_descriptions | C80: alias | D80: group-detail | F80: Beschreibung Ausflug | G80: Descriptions Excursion | H80: Beschrijving excursie
B81: name_excursion | C81: string | D81: text input | F81: Ausflugstitel | G81: Excursion Title | H81: Excursietitel | K81: Yes | L81: excursions_descriptions_translations | N81: field_557_1 | O81: tours | V81: eher nach oben…?
B82: subline | C82: string | D82: text input | F82: Unterzeile Rund-/Studienreise | G82: Round/Study Trip Subtitle | H82: Subregel rondreis/studiereis | K82: Yes | L82: excursions_descriptions_translations | N82: field_558_1 | O82: tours
B83: teaser | C83: text | D83: text area | F83: Einleitungstext | G83: Teaser Text | H83: Teaser text | I83: Max. 2 sentences describing: type and USPs. | K83: Yes | L83: excursions_descriptions_translations | N83: field_559_1 | O83: tours
B84: excursion_programme_disclaimer | C84: string | D84: text input | F84: Änderungsvorbehalt Reiseprogramm | G84: Disclaimer Travel Programme | H84: Voorbehoud wijzigingen reisprogramma | K84: Yes | L84: excursions_descriptions_translations | N84: field_1404_1 | O84: tours | U84: Need standard text per language (DE: "Änderungen vorbehalten."). | V84: Umbenannt 1.3: programm -> programme (kein Deutsch)
B85: excursion_programme | C85: text | D85: text area | F85: Ausflugsprogramm | G85: Excursion Programme | H85: Excursieprogramma | K85: Yes | L85: excursions_descriptions_translations | N85: field_560_1 | O85: tours | V85: Umbenannt 1.3: programm -> programme
B86: recommendations | C86: text | D86: text area | F86: Empfehlungen / Tipps | G86: Recommendations / Tips | H86: Aanbevelingen / Tips | I86: Optionale Empfehlung oder Zusatzhinweis zur Tour. Kurz und prägnant. | K86: Yes | L86: excursions_descriptions_translations | N86: field_561_1 | O86: tours
A88: Builder (layer right side) | B88: description_supplementary | C88: json | D88: repeater (json) | F88: Ergänzende Beschreibungen | G88: Supplementary Descriptions | H88: Aanvullende beschrijvingen | K88: Yes | U88: T1: O2M-Sub-Collection "excursions_description_supplementary" + eigenes _translations (headline, text uebersetzbar).
B89: headline | C89: text | D89: text input (in repeater) | F89: Überschrift | G89: Headline | H89: Headline | K89: Yes | L89: excursions_descriptions_translations | N89: field_1262_1 | O89: tours | V89: local repeater key
B90: text | C90: text | D90: text area (in repeater) | F90: Text | G90: Text | H90: Tekst | K90: Yes | L90: excursions_descriptions_translations | N90: field_1263_1 | O90: tours | V90: local repeater key (field_1292/1293 = weitere Repeater-Eintraege)
D91: text input (in repeater) | F91: Überschrift | G91: Headline | H91: Headline | K91: Yes | L91: excursions_descriptions_translations | N91: field_1292_1 | O91: tours
D92: text area (in repeater) | F92: Text | G92: Text | H92: Tekst | K92: Yes | L92: excursions_descriptions_translations | N92: field_1293_1 | O92: tours
A94: Tab | B94: tab_price_info | C94: alias | D94: group-raw | F94: Preis-Infos | G94: Price Info | H94: Prijsinformatie
A95: Section (open) | B95: section_price_info | C95: alias | D95: group-detail | F95: Preis-relevante Infos | G95: Price-relevant Information | H95: Prijsrelevante informatie
B96: supplier_product_code | C96: integer | D96: numeric (length max: 8) | F96: Buchungscode Supplier | G96: Supplier Booking Code | H96: Supplier boekingscode | K96: No | N96: field_912_1 | O96: tours | Y96: Tour 32?
B97: price_subline | C97: string | D97: text input | F97: Reise-Subline (Dauer + Tage) | G97: Trip Subline (Duration + Days) | H97: Reis-subline (duur + dagen) | N97: field_905_1 | O97: tours | U97: Import but hide this field. | V97: Roundtrips: 06.05. Import but hide
B98: price_sample_day_tour | N98: field_1428_1 | O98: tours | V98: OFFEN: Legacy "Musterpreis"-Felder (4.1: kein day_tour im key). Sammelbereinigung pruefen.
B99: price_sample_1_date_day_tour | N99: field_1429_1 | O99: tours | V99: s.o.
B100: price_sample_1_date_day_tour_2 | N100: field_1429_2 | O100: tours | V100: s.o.
B101: price_sample_2_date_day_trip | N101: field_1515_1 | O101: tours | V101: s.o.
B102: price_sample_2_date_day_trip_2 | N102: field_1515_2 | O102: tours | V102: s.o.
B103: price_sample_3_date_day_trip | N103: field_1516_1 | O103: tours | V103: s.o.
B104: price_sample_3_date_day_trip_2 | N104: field_1516_2 | O104: tours | V104: s.o.
B105: price_sample_footnote_day_tour | N105: field_1430_1 | O105: tours | V105: s.o.
B106: services_included | C106: text | D106: text area | F106: Eingeschlossene Leistungen | G106: Included Services | H106: Inbegrepen diensten | K106: Yes | L106: excursions_price_infos_translations | N106: field_563_1 | O106: tours | V106: Reihenfolge wg. Übersetzung beachten!
B107: services_not_included | C107: text | D107: text area | F107: Nicht eingeschlossene Leistungen | G107: Services not Included | H107: Niet-inbegrepen diensten | K107: Yes | L107: excursions_price_infos_translations | N107: field_564_1 | O107: tours
B108: additional_information | C108: text | D108: text area | F108: Sonstige Hinweise | G108: Additional Information | H108: Overige opmerkingen | I108: Ergänzende buchungsrelevante Hinweise zur Tour. | K108: Yes | L108: excursions_price_infos_translations | N108: field_568_1 | O108: tours | Y108: Wirkt auf mich "doppelt" zu "Tipps"…
B109: deviating_cancellation_terms | C109: text | D109: text area | F109: Abweichende Stornobedingungen? | G109: Deviating Cancellation Conditions? | H109: Afwijkende annuleringsvoorwaarden? | K109: Yes | L109: excursions_price_infos_translations | N109: field_566_1 | O109: tours | V109: Umbenannt (Tippfehler/4.3): cancelation -> cancellation
B110: children_policy | C110: text | D110: text area | F110: Kinder-Policy des Anbieters | G110: Provider Children Policy | H110: Kinderbeleid van de aanbieder | K110: Yes | L110: excursions_price_infos_translations | N110: field_1260_1 | O110: tours
B111: participants_text | C111: string | D111: text input | F111: Teilnehmer-Hinweise (Min/Max, Freitext) | G111: Participant Notes (Min/Max, free text) | H111: Deelnemers-info (min./max., vrije tekst) | K111: Yes | L111: excursions_price_infos_translations | N111: field_565_1 | O111: tours | Y111: Könnte man sich das nicht sparen?
B112: mobility_advice_text | C112: uuid | D112: select-dropdown-m2o | E112: mobility_advice_text | F112: Text Mobilitätshinweis | G112: Text Mobility Advice | H112: Tekst mobiliteitsadvies | I112: Text is being set under "Global Data" > "Mobility Advice Text". | K112: No (*) | N112: field_1537_1 | O112: tours | U112: Add field in sub-collection "Mobility Advice Text" with standard German text (see Daytrips brief).
A114: Builder (layer right side) | B114: price_info_supplementary | C114: json | D114: repeater (json) | F114: Ergänzende Beschreibungen | G114: Supplementary Descriptions | H114: Aanvullende beschrijvingen | K114: Yes | U114: T1: O2M-Sub-Collection "excursions_price_info_supplementary" + eigenes _translations (headline, text uebersetzbar).
...

Sheet #4 tours (aka roundtrips)
A1: Collection | B1: tours
A2: Remarks | B2: Rundreisen / Tours (geführte Reisen mit vordefiniertem Programm).
A3: Date / Update | B3: 46195
A4: Legend | B4: Checked | C4: Changes | D4: Analysis done | E4: Analysis tbd
A6: Details for Directus Set-up | K6: Translatable? | N6: Import Details "trips" | Q6: Import Details "studienreisen" (Karawane) | U6: Remarks / Comments | X6: Legacy | Y6: Stakeholder Notes
A7: Special field type | B7: field_key Directus | C7: data_type | D7: interface (characters max) | E7: Relation (Sub-Collection) | F7: Label DE | G7: Label GB | H7: Label NL | I7: Info-Text (below the field) | K7: Yes / No | L7: Naming Translation-Collection | N7: fieldid Primarix | O7: parent table | U7: Remarks for DEV (field set-up and Import) | V7: Remarks + Tasks internal | X7: tbd after import | Y7: TOPS Bernd | Z7: TOPs Birgit | AA7: Notes Client
A9: Above Tabs | B9: header | C9: alias | D9: header | F9: Header | G9: Header | H9: Header | I9: Page header above the tabs (title + subtitle) | K9: No
A10: Above Tabs | B10: sell_prices_status | C10: string | D10: select-dropdown | F10: Verkaufspreis-Status | G10: Sell Prices Status | H10: Verkoopprijsstatus | I10: Tracks async sell price calculation state | K10: No
A11: Above Tabs | B11: sell_prices_updated_at | C11: timestamp | D11: datetime | F11: Aktualisiert am | G11: Sell Prices Updated At | H11: Bijgewerkt op | I11: Last successful sell price calculation | K11: No
A12: Tab-Navigation | B12: ui_tabs | C12: alias | D12: tabs | F12: - | G12: - | H12: -
A14: Tab | B14: tab_master_data | C14: alias | D14: group-raw | F14: Stammdaten | G14: Master Data | H14: Stamgegevens
A15: Block | B15: block_publication | C15: alias | D15: group-raw | F15: - | G15: - | H15: -
A16: Section (open) | B16: section_publication | C16: alias | D16: group-detail | F16: Status & Veröffentlichung | G16: Status & Publication | H16: Status & publicatie
B17: object_id | C17: integer | D17: numerical | F17: Objekt-ID | G17: Object-ID | H17: Object-ID | I17: Automatically set. | K17: No | N17: oid | O17: trips
B18: object_info_primarix | C18: string | D18: text input | F18: Objekt Titel Primarix | G18: Object Title Primarix | H18: Objecttitel Primarix | K18: No | N18: object_info | O18: trips | U18: Non editable field
B19: season | C19: integer | D19: M2O | E19: seasons | F19: Saison-Gültigkeit | G19: Season Validity | H19: Seizoengeldigheid | K19: No | N19: season | O19: trips | U19: Transformed from "object_info": "25_" = "2025"
B20: status_primarix | C20: string | D20: dropdown | F20: Status Primarix | G20: Status Primarix | H20: Status Primarix | K20: No | N20: status (?) | O20: trips | U20: Type per Namenskonv. 4.5: string+dropdown (NOT M2O). | V20: war M2O im Brief
B21: internal_remarks | C21: text | D21: text area | F21: Interne Hinweise | G21: Internal Remarks | H21: Interne opmerking | I21: Internal Remarks from Primarix. Consider future "Comments" feature. | K21: No | N21: field_537_1 | O21: trips | U21: Field NOT translatable in future. Import all internal_remarks (also other languages) into this field.
B22: date_updated | C22: dateTime | D22: date | F22: Zuletzt aktualisiert | G22: Last Update | H22: Laatste update | K22: No | N22: (?) | O22: trips
B23: user_updated | C23: uuid | D23: M2O | E23: directus_users | F23: von | G23: by | H23: door | K23: No | N23: (?) | O23: trips | U23: Show last editor if possible; else "unknown".
A25: Section (open) | B25: section_botg_filter | C25: alias | D25: group-detail | F25: BOTG-Firmen-Zuordnung | G25: BOTG Company Assignment | H25: BOTG-bedrijfstoewijzing
B26: partner_visibility | C26: string | D26: radio button (all / selected) | K26: No | V26: Umbenannt 4.6: partner_type -> partner_visibility
B27: partner_selected | C27: alias | D27: M2M | E27: partner | K27: No | N27: field_1103_1 | O27: trips | U27: M2M only visible if radio != "all" (conditional). | V27: Umbenannt 4.6: partner -> partner_selected. OFFEN: Quelle war M2O; vehicles nutzt M2M - Kardinalitaet bestaetigen.
B28: is_axolot_export | C28: boolean | D28: radio | F28: Axolot-Export | G28: Axolot Export | H28: Axolot-export | N28: field_1538_1 | O28: trips | U28: "Axolot" = yes; "kein Export" = no. | V28: Umbenannt 4.3 (boolean is_): exportfilter -> is_axolot_export; ggf. allgemeiner export_channel? - Entscheidung Tommy.
A30: Block | B30: block_contacts | C30: alias | D30: group-raw | F30: - | G30: - | H30: -
A31: Section (open) | B31: section_operator | C31: alias | D31: group-detail | F31: Veranstalter | G31: Operator | H31: Organisator
B32: operator_direct | C32: string | D32: radio | F32: Veranstalter | G32: Travel Operator | H32: Reisorganisator | K32: No | N32: NEW | U32: No import (new field): "No" / "Yes". If "Yes": dropdown filtered from booking_partner.
B33: operator_linked | C33: integer | D33: many to one | E33: booking_partners | F33: Ausgewählter Tour Operator | G33: Chosen Tour Operator | H33: Gekozen touroperator | K33: No | N33: NEW | U33: No import (new field): dropdown with "Travel Operators" (new sub-category in booking_partners). | AA33: 07.04.: "Inbounder" könnten an Relevanz gewinnen. Ergo: Mail-Adresse erhalten (9%) + 1 Feld (Text Area) für Rest.
A35: COMMENT | B35: Following fields if radio "Yes":
B36: name_operator | C36: string | D36: text input | F36: Name (Veranstalter) | G36: Name (Operator) | H36: Naam (organisator) | K36: No | N36: field_493_1 | O36: trips
B37: street | C37: string | D37: text input | F37: Straße | G37: Street | H37: Straat | K37: No | N37: field_494_1 | O37: trips
B38: street_number | C38: string | D38: text input | F38: Hausnummer | G38: Street Number | H38: Huisnummer | K38: No | N38: field_495_1 | O38: trips
B39: postcode | C39: string | D39: text input | F39: PLZ | G39: Postal Code | H39: Postcode | K39: No | N39: field_496_1 | O39: trips
B40: place | C40: string | D40: auto complete | E40: places | F40: Ort | G40: City / Town | H40: Plaats | I40: Defines further geographical details (country, state, region). | K40: No | N40: field_497_1 | O40: trips | U40: Adapt import: free text -> match to collection; report missing data.
B41: location_tour32 | C41: integer | D41: M2O | E41: locations_tour32 | F41: Suchort (Tour User only) | G41: Search Location (Tour User only) | H41: Zoeklocatie (Tour User only) | K41: No | N41: field_1345_1 | O41: trips | U41: Adapt import: free text -> match to collection; report missing data.
B42: country | C42: integer | D42: M2O | E42: countries | F42: Land | G42: Country | H42: Land | I42: Defined by "Place" | K42: No | N42: field_499_1 | O42: trips | U42: Adapt import: free text -> match to collection; report missing data.
B43: postbox_number | F43: Postfach Nr | G43: PO Box No | H43: Postbus nr | N43: field_500_1 | O43: trips | V43: OFFEN: im Brief 3x identischer key/field_500 - Duplikate klaeren. | Y43: Erhalten od. weg?
B44: state | C44: integer | D44: M2O | E44: states | F44: Staat / Bundesland | G44: State / Province | H44: Staat / Provincie | K44: No | N44: field_498_1 | O44: trips | U44: Adapt import: free text -> match to collection; report missing data.
B45: phone_general | C45: string | D45: phone number | F45: Telefon (allgemein) | G45: Phone (general) | H45: Telefoon (algemeen) | K45: No | N45: field_503_1 | O45: trips | V45: ggf. als repeater (json)
B46: phone_after_hours | C46: string | D46: phone number | F46: Telefon (after hours) | G46: Phone (after hours) | H46: Telefoon (na kantooruren) | K46: No | N46: field_219_1 | O46: trips | V46: Umbenannt 4.3: phone_ah -> phone_after_hours
B47: fax_general | D47: - | F47: Fax (allgemein) | G47: Fax (general) | H47: Fax (algemeen) | N47: field_504_1 | O47: trips | U47: NOT to be imported!
B48: email_general | C48: string | D48: mail | F48: Email (allgemein) | G48: E-mail (general) | H48: Email (algemeen) | K48: No | N48: field_505_1 | O48: trips
B49: website | C49: string | D49: url | F49: Webseite | G49: Web Site | H49: Homepage | K49: No | N49: NEW | Y49: Mit vorsehen?
A51: Section (open) | B51: section_reservation | C51: alias | D51: group-detail | F51: Reservierung | G51: Reservation | H51: Reservering
B52: booking_channel | C52: string | D52: radio | E52: booking_partners | K52: No | N52: NEW | U52: Partner Booking OR Direct Booking. (E2: booking_partner gewinnt.) | V52: HINWEIS Memory: ggf. booking_channel - mit E2 abgleichen.
B53: booking_partner | C53: integer | D53: M2O | E53: booking_partners | F53: Buchung über | G53: Booking via | H53: Boeking via | K53: No | N53: field_220_1 | O53: trips | AA53: 07.04.: "Inbounder" könnten an Relevanz gewinnen. Ergo: Mail-Adresse erhalten (9%) + 1 Feld (Text Area) für Rest.
B54: id_service_provider_tour32 | C54: string | D54: text input | F54: Leistungsträger (Tour32 only) | G54: Service Provider (Tour32 only) | H54: Dienstverlener (Tour32 only) | K54: No | N54: field_1179_1 | O54: trips | V54: OFFEN: 4.4 verbietet id_<quelle>; Rollen-Praefix noetig - Entscheidung Tommy.
B55: id_main_service_provider_tour32 | C55: string | D55: text input | F55: Haupt-Leistungsträger (Tour32 only) | G55: Main Service Provider (Tour32 only) | H55: Hoofddienstverlener (Tour32 only) | K55: No | N55: field_1384_1 | O55: trips | V55: Umbenannt 4.4 (explizites Beispiel): haupt_id_tour_user -> main_id_tour_user
A57: COMMENT | B57: Following fields if radio "Direct Booking":
B58: res_phone | D58: - | F58: Reservierung: Telefon | G58: Reservation: Telephone | H58: Reservering: Telefoon | N58: field_514_1 | O58: trips | U58: No separate field anymore. Import into "booking_info".
B59: res_fax | D59: - | F59: Reservierung: Fax | G59: Reservation: Fax | H59: Reservering: Fax | N59: field_515_1 | O59: trips | U59: NOT to be imported!
B60: email_booking | C60: string | D60: email | F60: Email Reservierung | G60: E-Mail Reservation | H60: Email reservering | K60: No | N60: field_516_1 | O60: trips
B61: res_email2 | D61: - | F61: Reservierung: Email 2 | G61: Reservation: E-mail 2 | H61: Reservering: Email 2 | N61: field_517_1 | O61: trips | U61: No separate field anymore. Import into "booking_info".
B62: contact_title | D62: - | F62: Reservierung: Kontakt Titel | G62: Reservation: Contact Title | H62: Reservering: Contactpersoon Titel | N62: field_518_1 | O62: trips | U62: No separate field anymore. Import into "booking_info".
B63: contact_greeting | D63: - | F63: Reservierung: Kontakt Anrede | G63: Reservation: Contact Salutation | H63: Reservering: Contactpersoon Aanhef | N63: field_519_1 | O63: trips | U63: No separate field anymore. Import into "booking_info".
B64: contact_firstname | D64: - | F64: Reservierung: Kontakt Vorname | G64: Reservation: Contact First Name | H64: Reservering: Contactpersoon Voornaam | N64: field_520_1 | O64: trips | U64: No separate field anymore. Import into "booking_info".
B65: contact_name | D65: - | F65: Reservierung: Kontakt Name | G65: Reservation: Contact Surname | H65: Reservering: Contactpersoon Naam | N65: field_521_1 | O65: trips | U65: No separate field anymore. Import into "booking_info".
B66: internal_remarks_reservation | C66: text | D66: text area | F66: Interne Buchungsinfos /-Hinweise | G66: Internal Reservation Infos / Remarks | H66: Interne boekingsinfo / -opmerkingen | I66: Internal notes and additional contact details. | K66: No | N66: field_522_1 | O66: trips | U66: All data above fused into this field; <br> as separation. | Y66: Nur 46x befüllt - siehe Word
A68: COMMENT | B68: All fields within Tab "Banking Details" will be not imported.
A70: Tab | B70: tab_description | C70: alias | D70: group-raw | F70: Beschreibung | G70: Description | H70: Beschrijving
A71: Section (open) | B71: section_classification | C71: alias | D71: group-detail | F71: Klassifizierung | G71: Classification | H71: Indeling
B72: destinations | C72: alias | D72: M2M | E72: destinations | F72: Kontinente | G72: Continents | H72: Continenten | K72: No (*) | N72: field_216_1 | O72: trips | U72: Destinations (multiple) may differ from operator address. | Y72: Denkbar, dass es mehrere Kontoinente sind? >> ja
B73: countries | C73: alias | D73: M2M | E73: countries | F73: Länder | G73: Countries | H73: Landen | K73: No (*) | N73: field_1047_1 | O73: trips | U73: Countries (multiple) may differ from operator address.
B74: travel_categories | C74: alias | D74: M2M | E74: travel_categories | F74: Reiseart | G74: Tour Type | H74: Type Reis | K74: No (*) | N74: field_187_1 | O74: trips
B75: accommodation_types | C75: alias | D75: M2M | E75: accommodation_types | F75: Unterkunftsart | G75: Accommodation Type | H75: Type accommodatie | K75: No (*) | N75: field_186_1 | O75: trips | U75: Relation fix: accomodation_types -> accommodation_types | V75: ggf. Merge mit Karawane! ("cruise_types") | Y75: Warum eigentlich Unterkunftsart?
B76: colour | E76: NO Import! | F76: Farbwahl | G76: Colour Choice | H76: Kleur | N76: field_666_1 | O76: trips | U76: NO Import! | AA76: 24.02. nicht mehr erforderlich (Relevanz für Katalogproduktion)
B77: brox_category | E77: NO Import! | F77: Rubrik | G77: Heading | H77: Rubriek | N77: field_799_1 | O77: trips | U77: NO Import! Legacy CMS field. | V77: OFFEN: "brox" Jargon (1.2). | AA77: 24.02. nicht mehr erforderlich (Relevanz für Katalogproduktion)
B78: brox_headline | E78: NO Import! | F78: Headline | G78: Headline | H78: Headline | N78: field_172_1 | O78: trips | U78: NO Import! Legacy CMS field. | V78: s.o. | AA78: 24.02. nicht mehr erforderlich (Relevanz für Katalogproduktion)
B79: brox_subline | E79: NO Import! | F79: Subline | G79: Sub-line | H79: Subline | N79: field_174_1 | O79: trips | U79: NO Import! Legacy CMS field. | V79: s.o. | AA79: 24.02. nicht mehr erforderlich (Relevanz für Katalogproduktion)
B80: url_alias | E80: NO Import! | F80: URL Alias | G80: URL Alias | H80: URL Alias | N80: field_1464_1 | O80: trips | U80: NO Import! | V80: Umbenannt 4.1: Produkt-Praefix entfernt (trips_url_alias -> url_alias) | AA80: 24.02. nicht mehr erforderlich (Nutzung von "real" URL in Typo3)
A82: Section (open) | B82: section_descriptions | C82: alias | D82: group-detail | F82: Beschreibung Rund-/Studienreise | G82: Tour Description | H82: Tourbeschrijving
B83: name_tour | C83: string | D83: text input | F83: Reise-Titel | G83: Tour Title | H83: Tourtitel | K83: Yes | L83: tours_descriptions_translations | N83: field_173_1 | O83: trips | V83: eher nach oben…?
B84: subline | C84: string | D84: text input | F84: Subline Reise | G84: Tour Subline | H84: Tour subline | K84: Yes | L84: tours_descriptions_translations | N84: field_507_1 | O84: trips | AA84: 07.04.: Muss erhalten bleiben.
B85: teaser | C85: text | D85: text area | F85: Einleitungstext | G85: Teaser Text | H85: Teaser text | I85: Max. 2 sentences describing: type and USPs. | K85: Yes | L85: tours_descriptions_translations | N85: field_175_1 | O85: trips
B86: at_a_glance | C86: text | D86: text area | F86: Auf einen Blick | G86: At a Glance | H86: In één oogopslag | K86: Yes | L86: tours_descriptions_translations | N86: field_1258_1 | O86: trips
B87: pictogram | C87: text | D87: text area | F87: Piktogramme | G87: Pictograms | H87: Pictogrammen | N87: field_1396_1 | O87: trips | U87: Import but hide this field. | AA87: 24.02. nicht mehr erforderlich (Relevanz für Katalogproduktion)
B88: additional_text | C88: text | D88: text area | F88: weiterer Text | G88: Additional Text | H88: Extra tekst | I88: Ausführlichere Beschreibung (Vermeidung von Dopplungen zum Teaser). | N88: field_901_1 | O88: trips | U88: Import but hide this field. | AA88: 24.02. nicht mehr erforderlich (Relevanz für Katalogproduktion)
B89: from_to | C89: text | D89: text area | F89: Von - Bis (Tour32) | G89: From - To (Tour32) | H89: Van - Tot (Tour32) | K89: Yes | L89: tours_descriptions_translations | N89: field_177_1 | O89: trips | Y89: Was ist Sinn dieses Feldes? - siehe Auswertung - Was Unterschied zu 214_1 und 1037_1?
A91: Section (closed) | B91: section_flight_info | C91: alias | D91: group-detail | F91: Flug-Infos (optional) | G91: Flight Info (optional) | H91: Vluchtinformatie (optioneel) | AA91: 07.04. "Ergänzende Beischreibungen" - KEIN Rich Text Editor.
B92: flight_service | C92: integer | D92: M2O | E92: flight_options | F92: Flug-Buchungsservice | G92: Flight Booking Service | H92: Vluchtboekingsservice | I92: Optionaler Hinweistext zum Flugbuchungs-Service. | K92: No | L92: tours_descriptions_translations | N92: field_1397_1 | O92: trips | U92: Generate unique text snippets based on todays data. | Y92: Was tun? Textbausteine? - siehe Auswertung
B93: airlines | C93: integer | D93: M2O | E93: airlines | F93: Airlines | G93: Airlines | H93: Luchtvaartmaatschappijen | K93: No (*) | L93: tours_descriptions_translations | N93: field_1401_1 | O93: trips | Y93: Was tun?
B94: departure_airports | C94: alias | D94: M2M | E94: airports | F94: Mögliche Abflughäfen | G94: Possible Departure Airports | H94: Mogelijke vertrekluchthavens | K94: No (*) | L94: tours_descriptions_translations | N94: field_1398_1 | O94: trips | V94: Umbenannt (Tippfehler): depature_airports -> departure_airports
B95: flights_recommended | C95: text | D95: text area | F95: Empfohlene Flüge | G95: Recommended Flights | H95: Aanbevolen vluchten | K95: Yes | L95: tours_descriptions_translations | N95: field_1399_1 | O95: trips
B96: additional_recommendations | C96: text | D96: text area | F96: Empfehlungen zur Flugbuchung | G96: Flight Booking Recommendations | H96: Aanbevelingen voor vluchtboeking | I96: Empfehlungen zum Flug. | K96: Yes | L96: tours_descriptions_translations | N96: field_1400_1 | O96: trips | V96: Umbenannt (Tippfehler): additonal -> additional_recommendations
A98: Builder (layer right side) | B98: description_supplementary | C98: json | D98: repeater (json) | F98: Ergänzende Beschreibungen | G98: Supplementary Descriptions | H98: Aanvullende beschrijvingen | K98: Yes | AA98: 07.04. "Ergänzende Beischreibungen" - KEIN Rich Text Editor.
B99: headline | C99: text | D99: text input (in repeater) | F99: Überschrift | G99: Headline | H99: Headline | K99: Yes | L99: tours_descriptions_translations | N99: field_222_1 | O99: trips | V99: local repeater key
B100: text | C100: text | D100: text area (in repeater) | F100: Text | G100: Text | H100: Tekst | K100: Yes | L100: tours_descriptions_translations | N100: field_223_1 | O100: trips | V100: local repeater key (field_224..1519 = weitere Eintraege)
B101: headline | C101: text | D101: text input (in repeater) | F101: Überschrift | G101: Headline | H101: Headline | K101: Yes | L101: tours_descriptions_translations | N101: field_224_1 | O101: trips | V101: local repeater key
B102: text | C102: text | D102: text area (in repeater) | F102: Text | G102: Text | H102: Tekst | K102: Yes | L102: tours_descriptions_translations | N102: field_225_1 | O102: trips | V102: local repeater key (field_224..1519 = weitere Eintraege)
B103: headline | C103: text | D103: text input (in repeater) | F103: Überschrift | G103: Headline | H103: Headline | K103: Yes | L103: tours_descriptions_translations | N103: field_226_1 | O103: trips | V103: local repeater key
B104: text | C104: text | D104: text area (in repeater) | F104: Text | G104: Text | H104: Tekst | K104: Yes | L104: tours_descriptions_translations | N104: field_227_1 | O104: trips | V104: local repeater key (field_224..1519 = weitere Eintraege)
B105: headline | C105: text | D105: text input (in repeater) | F105: Überschrift | G105: Headline | H105: Headline | K105: Yes | L105: tours_descriptions_translations | N105: field_1518_1 | O105: trips | V105: local repeater key
B106: text | C106: text | D106: text area (in repeater) | F106: Text | G106: Text | H106: Tekst | K106: Yes | L106: tours_descriptions_translations | N106: field_1519_1 | O106: trips | V106: local repeater key (field_224..1519 = weitere Eintraege)
A108: Tab | B108: tab_tour_programme | C108: alias | D108: group-raw | F108: Reiseprogramm | G108: Travel Programme | H108: Reisprogramma
A109: Section (open) | B109: section_tour_programme | C109: alias | D109: group-detail | F109: Reiseprogramm | G109: Travel Programme | H109: Reisprogramma
B110: tour_programme_disclaimer | C110: string | D110: text input | F110: Änderungsvorbehalt Reiseprogramm | G110: Disclaimer Travel Programme | H110: Voorbehoud wijzigingen reisprogramma | K110: Yes | L110: tours_programme_translations | N110: field_178_1 | O110: trips | U110: Need language-independent default text (DE: "Änderungen vorbehalten."). | V110: Umbenannt 1.3: programm -> programme | Y110: Hier gut platziert? - "Änderungen vorbehalten" muss immer stehen + Optionaler Text
A112: Builder (layer right side) | B112: tour_programme | C112: json | D112: repeater (json) | F112: Reiseprogramm | G112: Travel Programme | H112: Reisprogramma | AA112: 07.04. "Ergänzende Beischreibungen" - KEIN Rich Text Editor.
B113: day_destinations | C113: text | D113: repeater: text field | F113: Tagesziele (Ort/Region) | G113: Daily Destinations (place/region) | H113: Dagbestemmingen (plaats/regio) | K113: Yes | L113: tours_programme_translations | N113: field_180_1 to 1265_1 | O113: trips | V113: wie Sortierung / Nummerierung?
B114: day_description | C114: text | D114: repeater: text area | F114: Beschreibung Tagesprogramm | G114: Daily Programme Description | H114: Beschrijving dagprogramma | K114: Yes | L114: tours_programme_translations | N114: field_180_2 to 1265_2 | O114: trips
B115: day_accommodation_note | C115: text | D115: repeater: text area | F115: Übernachtungshinweis | G115: Accommodation Note | H115: Overnachtingsinfo | K115: Yes | L115: tours_programme_translations | N115: field_180_3 to 1265_3 | O115: trips | V115: Umbenannt (Tippfehler): accomodation -> accommodation
...

Sheet #5a rental_companies
A1: Collection | B1: rental_companies
A2: Remarks | B2: M20-collection for "vehicles". Data to be imported ONCE (!) from "rentalcars" and afterwards "camper". Companies and its data will exist more than once. Choose the data set with latest change date!
A3: Date / Update | B3: 46189
A5: Legend | B5: Checked | C5: Changes | D5: Analysis done | E5: Analysis tbd | F5: Hidden field. | G5: Legacy fields not imported.
A7: Details for Directus Set-up | K7: Translatable? | N7: Import Details "rentalcars" | Q7: Import Details "campers" | U7: Remarks / Comments | X7: Legacy | Z7: TOPS Bernd | AA7: TOPs Birgit | AB7: Notes Client
A8: Special field type | B8: field_key Directus | C8: data_type | D8: interface (characters max) | E8: Relation (Sub-Collection) | F8: Label DE | G8: Label GB | H8: Label NL | I8: Info-Text (below the field) | K8: Yes / No | L8: Naming Translation-Collection | N8: fieldid Primarix | O8: parent table | Q8: fieldid Primarix | R8: parent table | S8: field id | U8: Remarks for DEV (field set-up and Import) | V8: Remarks + Tasks internal | X8: Kill after import
A10: Above Tabs | B10: header | C10: alias | D10: header | F10: Header | G10: Header | H10: Header | I10: Page header above the tabs (title + subtitle) | K10: No
A11: Above Tabs | B11: sell_prices_status | C11: string | D11: select-dropdown | F11: Verkaufspreis-Status | G11: Sell Prices Status | H11: Verkoopprijsstatus | I11: Tracks async sell price calculation state | K11: No
A12: Above Tabs | B12: sell_prices_updated_at | C12: timestamp | D12: datetime | F12: Aktualisiert am | G12: Sell Prices Updated At | H12: Bijgewerkt op | I12: Last successful sell price calculation | K12: No
A13: Tab-Navigation | B13: ui_tabs | C13: alias | D13: tabs | F13: - | G13: - | H13: -
A15: Tab | B15: tab_master_data | C15: alias | D15: group-raw | F15: Stammdaten | G15: Master Data | H15: Stamgegevens
A16: Block | B16: block_publication | C16: alias | D16: group-raw | F16: - | G16: - | H16: -
A17: Section (open) | B17: section_publication | C17: alias | D17: group-detail | F17: Status & Veröffentlichung | G17: Status & Publication | H17: Status & publicatie
B18: object_id | C18: integer | D18: numerical | F18: Objekt-ID | G18: Object-ID | H18: Object-ID | K18: No | N18: oid | O18: rentalcars | Q18: oid | R18: campers | S18: object_id
A19: Field hidden | B19: object_info_primarix | C19: string | D19: text input | F19: Objekt Titel Primarix | G19: Object Title Primarix | H19: Objecttitel Primarix | K19: No | N19: object_info | O19: rentalcars | Q19: object_info | R19: campers | S19: object_info_primarix | U19: Non editable field | Z19: Angebots-Name
B20: season | C20: integer | D20: M2O | E20: seasons | F20: Saison-Gültigkeit | G20: Season Validity | H20: Seizoengeldigheid | K20: No | N20: season | O20: rentalcars | Q20: season | R20: campers | S20: season | U20: Transformed value from "object info": "25_" = "2025"
B21: status_primarix | C21: string | D21: dropdown | F21: Status Primarix | G21: Status Primarix | H21: Status Primarix | K21: No | N21: freigabe | O21: rentalcars | Q21: freigabe | R21: camper | S21: status_primarix
B22: internal_remarks | C22: text | D22: text area | F22: Interne Hinweise | G22: Internal Remarks | H22: Interne opmerking | I22: Internal Remarks from Primarix. - Please consider for the future the "Comments"-Feature (Icon on right side). | K22: No | N22: field_1331_1 | O22: rentalcars | Q22: field_1330_1 | R22: campers | S22: internal_remarks | U22: IMPORTANT: The field is in future NOT translatable. Within the import you need all "internal_remarks" into this field (also from other languages).
A23: Field hidden | B23: date_updated | C23: dateTime | D23: date | F23: Zuletzt aktualisiert | G23: Last Update | H23: Laatste update | K23: No | N23: lastupdate | O23: rentalcars | Q23: lastupdate | R23: camper | S23: date_updated
A24: Field hidden | B24: user_updated | C24: uuid | D24: M2O | E24: directus_users | F24: von | G24: by | H24: door | K24: No | N24: — | O24: — | Q24: — | R24: — | S24: user_updated | U24: Pls show the last editor if possible (in case information is not available in Primarix show "unknown" or similar)
A26: Section (closed) | B26: section_botg_companies | C26: alias | D26: group-detail | F26: BOTG-Firmen-Zuordnung | G26: BOTG Company Assignment | H26: BOTG-bedrijfstoewijzing
B27: partner_visibility | C27: string | D27: radio button (all / selected) | K27: No | N27: NEW | Q27: NEW | S27: partner_type
B28: partner_selected | C28: alias | D28: M2M | E28: partner | K28: No | N28: field_1104_1 | O28: rentalcars | Q28: field_1105_1 | R28: campers | S28: partner
A30: Block | B30: block_contacts | C30: alias | D30: group-raw | F30: - | G30: - | H30: -
A31: Section (open) | B31: section_address | C31: alias | D31: group-detail | F31: Adresse Vermieter | G31: Address Rental Company | H31: Adres verhuurder
B32: name_company | C32: string | D32: text input | F32: Name (Vermieter) | G32: Name (Rental Company) | H32: Naam (Verhuurder) | K32: No | N32: field_425_1 | O32: rentalcars | Q32: field_268_1 | R32: camper | S32: name
B33: rental_type | C33: string | D33: radio button | F33: Vermietete Fahrzeugarten | G33: Rented Vehicle Types | H33: Verhuurde voertuigtypes | K33: No | N33: NEW | Q33: - | R33: - | S33: - | U33: "Campers", "Rental Cars"
B34: street | C34: string | D34: text input | F34: Straße | G34: Street | H34: Straat | K34: No | N34: field_426_1 | O34: rentalcars | Q34: field_269_1 | R34: camper | S34: street
B35: street_number | C35: string | D35: text input | F35: Hausnummer | G35: Street Number | H35: Huisnummer | K35: No | N35: field_427_1 | O35: rentalcars | Q35: field_270_1 | R35: camper | S35: street_number
B36: zip_code | C36: string | D36: text input | F36: PLZ | G36: Postal Code | H36: Postcode | K36: No | N36: field_428_1 | O36: rentalcars | Q36: field_272_1 | R36: camper | S36: zip_code
B37: place | C37: integer | D37: auto complete | E37: places | F37: Ort | G37: City / Town | H37: Plaats | K37: No | N37: field_429_1 | O37: rentalcars | Q37: field_274_1 | R37: camper | S37: place | U37: Adapt import: Actually field contains text inputs. Match to entry in new collection. Report missing data separatly!
B38: location_tour32 | C38: integer | D38: M2O | E38: locations_tour32 | F38: Suchort (Tour User only) | G38: Search Location (Tour User only) | H38: Zoeklocatie (Tour User only) | K38: No | N38: field_1344_1 | O38: rentalcars | Q38: field_1343_1 | R38: camper | S38: location_tour32 | U38: Adapt import: Actually field contains text inputs. Match to entry in new collection. Report missing data separatly!
B39: country | C39: integer | D39: M2O | E39: countries | F39: Land | G39: Country | H39: Land | K39: No | N39: field_431_1 | O39: rentalcars | Q39: field_276_1 | R39: camper | S39: country | U39: Adapt import: Actually field contains text inputs. Match to entry in new collection. Report missing data separatly!
F40: Postfach Nr | N40: field_432_1 | O40: rentalcars | Q40: field_271_1 | R40: camper | S40: postbox_number | Z40: Erhalten od. weg?
F41: Postfach PLZ | N41: field_433_1 | O41: rentalcars | Q41: field_273_1 | R41: camper | S41: postbox_zip_code | Z41: Erhalten od. weg?
F42: Postfach Ort | N42: field_434_1 | O42: rentalcars | Q42: field_385_1 | R42: camper | S42: postbox_town | Z42: Erhalten od. weg?
B43: state | C43: integer | D43: M2O | E43: states | F43: Staat / Bundesland | G43: State / Province | H43: Staat / Provincie | K43: No | N43: field_430_1 | O43: rentalcars | Q43: field_275_1 | R43: camper | S43: state | U43: Adapt import: Actually field contains text inputs. Match to entry in new collection. Report missing data separatly!
B44: phone_general | C44: string | D44: phone number | F44: Telefon (allgemein) | G44: Phone (general) | H44: Telefoon (algemeen) | K44: No | N44: field_435_1 | O44: rentalcars | Q44: field_277_1 | R44: camper | S44: phone_general | V44: ggf. als "repeater (json)"
B45: phone_after_hours | C45: string | D45: phone number | F45: Telefon (after hours) | G45: Phone (after hours) | H45: Telefoon (na kantooruren) | K45: No | N45: field_436_1 | O45: rentalcars | Q45: field_386_1 | R45: camper | S45: phone_ah
D46: - | F46: Fax (allgemein) | G46: Fax (General) | H46: Fax (algemeen) | N46: field_437_1 | O46: rentalcars | Q46: field_278_1 | R46: camper | S46: fax_general | U46: NOT to be imported!
B47: email_general | C47: string | D47: mail | F47: E-Mail (allgemein) | G47: Email (general) | H47: E-mail (algemeen) | K47: No | N47: field_438_1 | O47: rentalcars | Q47: field_279_1 | R47: camper | S47: email_general
B48: website | C48: string | D48: url | F48: Webseite | G48: Website | H48: Homepage | K48: No | N48: field_439_1 | O48: rentalcars | Q48: field_280_1 | R48: camper | S48: website
A50: Section (open) | B50: section_booking_contact | C50: alias | D50: group-detail | F50: Buchung & Abwicklung | G50: Booking & Processing | H50: Boeking & Afhandeling | K50: No | Z50: Booking Partner andere als die Vermieter?
B51: booking_channel | C51: string | D51: radio button (checked) | K51: No | N51: NEW | Q51: NEW | S51: booking_partner | U51: Partner Booking OR Direct Booking
B52: booking_partner | C52: uuid | D52: M2O | E52: booking_partners | F52: Buchung über | G52: Booking via | H52: Boeking via | K52: No | N52: field_876_1 | O52: rentalcars | Q52: field_974_1 | R52: camper | S52: booking
D53: - | F53: Reservierung: Telefon | G53: Reservation: Telephone | H53: Reservering: Telefoon | N53: field_470_1 | O53: rentalcars | Q53: field_296_1 | R53: camper | S53: res_phone | U53: No seperate field anymore. Import into field "booking_info".
D54: - | F54: Reservierung: Fax | G54: Reservation: Fax | H54: Reservering: Fax | N54: field_471_1 | O54: rentalcars | Q54: field_297_1 | R54: camper | S54: res_fax | U54: NOT to be imported!
B55: email_booking | C55: string | D55: email | F55: E-Mail (Buchung) | G55: Email (Booking) | H55: E-mail (boeking) | K55: No | N55: field_472_1 | O55: rentalcars | Q55: field_298_1 | R55: camper | S55: booking_email
D56: - | F56: Reservierung: Email 2 | G56: Reservation: E-mail 2 | H56: Reservering: Email 2 | N56: field_473_1 | O56: rentalcars | Q56: field_299_1 | R56: camper | S56: res_email2 | U56: No seperate field anymore. Import into field "booking_info".
D57: - | F57: Reservierung: Kontakt Titel | G57: Reservation: Contact Title | H57: Reservering: Contactpersoon Titel | N57: field_474_1 | O57: rentalcars | Q57: field_300_1 | R57: camper | S57: contact_title | U57: No seperate field anymore. Import into field "booking_info".
D58: - | F58: Reservierung: Kontakt Anrede | G58: Reservation: Contact Salutation | H58: Reservering: Contactpersoon Aanhef | N58: field_475_1 | O58: rentalcars | Q58: field_301_1 | R58: camper | S58: contact_greeting | U58: No seperate field anymore. Import into field "booking_info".
D59: - | F59: Reservierung: Kontakt Vorname | G59: Reservation: Contact First Name | H59: Reservering: Contactpersoon Voornaam | N59: field_476_1 | O59: rentalcars | Q59: field_302_1 | R59: camper | S59: contact_firstname | U59: No seperate field anymore. Import into field "booking_info".
D60: - | F60: Reservierung: Kontakt Name | G60: Reservation: Contact Surname | H60: Reservering: Contactpersoon Naam | N60: field_477_1 | O60: rentalcars | Q60: field_303_1 | R60: camper | S60: contact_name | U60: No seperate field anymore. Import into field "booking_info".
B61: internal_remarks_reservation | C61: text | D61: text area | F61: Interne Buchungsinfos /-Hinweise | G61: Internal Reservation Infos / Remarks | H61: Interne boekingsinfo / -opmerkingen | K61: No | N61: field_478_1 | O61: rentalcars | Q61: field_393_1 | R61: camper | S61: internal_remarks_reservation | U61: Here all data fused from this field and the ones above. - <br> as separation.
A63: Tab | B63: tab_description | C63: alias | D63: group-raw | F63: Beschreibung | G63: Description | H63: Beschrijving
A64: Section (open) | B64: section_descriptions | C64: alias | D64: group-detail | F64: Beschreibung Vermieter | G64: Rental Company Description | H64: Beschrijving verhuurder
B65: countries | C65: integer | D65: M2M | E65: countries | F65: Länder | G65: Countries | H65: Landen | K65: No (*) | N65: field_1482_1 | O65: rentalcars | Q65: field_1480_1 | R65: camper | S65: country | U65: Attention: Countries (multiple) could be different to adress above.
F66: Farbwahl | G66: Colour Choice | H66: kleur | N66: field_668_1 | O66: rentalcars | Q66: field_667_1 | R66: camper | S66: colour | U66: NO Import! | AB66: 24.02. nicht mehr erforderlich (Relevanz für Katalogproduktion)
F67: Rubrik | G67: Heading | H67: Rubriek | N67: field_806_1 | O67: rentalcars | Q67: field_805_1 | R67: camper | S67: brox_category | U67: NO Import! | AB67: 24.02. nicht mehr erforderlich (Relevanz für Katalogproduktion)
F68: URL Alias | G68: URL Alias | H68: URL Alias | N68: field_1462_1 | O68: rentalcars | Q68: field_1461_1 | R68: camper | S68: camper_url_alias | U68: NO Import! | AB68: 24.02. nicht mehr erforderlich (Nutzung von "real" URL in Typo3)
N69: field_852_1 | O69: rentalcars | Q69: NEW | Z69: Keine Headline? (Mietwagen ja?) >> hier alles bei den Fahrzeugen?
B70: subline | C70: string | D70: text input | F70: Unterzeile | G70: Subline | H70: Subregel | K70: Yes | L70: rental_companies_descriptions_translations | N70: field_853_1 | O70: rentalcars | Q70: NEW | Z70: Keine Headline? (Mietwagen ja?) >> hier alles bei den Fahrzeugen?
B71: teaser | C71: text | D71: text area | F71: Einleitungstext | G71: Teaser Text | H71: Teaser text | K71: Yes | L71: rental_companies_descriptions_translations | N71: field_441_1 | O71: rentalcars | Q71: field_388_1 | R71: camper | S71: teaser
B72: text_positive | C72: text | D72: text area | F72: Pluspunkte | G72: Positive Aspects | H72: Pluspunten | K72: Yes | L72: rental_companies_descriptions_translations | N72: field_1452_1 | O72: rentalcars | Q72: field_389_1 | R72: camper | S72: text_positive
B73: text_negative | C73: text | D73: text area | F73: Minuspunkte | G73: Negative Aspects | H73: Minpunten | K73: Yes | L73: rental_companies_descriptions_translations | N73: field_1453_1 | O73: rentalcars | Q73: field_798_1 | R73: camper | S73: text_negative | Z73: Was würde hier stehen?
A75: Builder (layer right side) | B75: description_supplementary | C75: json | D75: repeater (json) | F75: Ergänzende Beschreibungen | G75: Supplementary Descriptions | H75: Aanvullende beschrijvingen | U75: Repeater for "Headline" + "Text" | AB75: 07.04. "Ergänzende Beischreibungen" - KEIN Rich Text Editor.
B76: headline | D76: text input (in repeater) | F76: Überschrift | G76: Headline | H76: Headline | K76: Yes | L76: rental_companies_descriptions_translations | N76: field_1298_1 | O76: rentalcars | Q76: field_1274_1 | R76: camper
B77: text | D77: text area (in repeater) | F77: Text | G77: Text | H77: Tekst | K77: Yes | L77: rental_companies_descriptions_translations | N77: field_1299_1 | O77: rentalcars | Q77: field_1275_1 | R77: camper
B78: headline | D78: text input (in repeater) | F78: Überschrift | G78: Headline | H78: Headline | K78: Yes | L78: rental_companies_descriptions_translations | N78: field_1300_1 | O78: rentalcars | Q78: field_1276_1 | R78: camper | U78: empty repeater sub-field – remove?
B79: text | D79: text area (in repeater) | F79: Text | G79: Text | H79: Tekst | K79: Yes | L79: rental_companies_descriptions_translations | N79: field_1301_1 | O79: rentalcars | Q79: field_1277_1 | R79: camper | U79: empty repeater sub-field – remove?
A81: Tab | B81: tab_rental_conditions | C81: alias | D81: group-raw | F81: Mietbedingungen | G81: Rental Conditions | H81: Huurvoorwaarden
A82: Section (open) | B82: section_attributes | C82: alias | D82: group-detail | F82: Merkmale (IT-Systeme) | G82: Attributes (System Inputs) | H82: Kenmerken (systeeminvoer)
B83: minimum_rental_days | C83: integer | D83: numeric (1-7) | F83: Mindestmietdauer (Zahl) | G83: Minimum Rental Period (Number) | H83: Minimum huurperiode (getal) | K83: No | N83: field_1065_1 | O83: rentalcars | Q83: field_1064_1 | R83: camper | S83: minimum_rental_days | Z83: Welche Werte?
B84: conditions_calculation_day | C84: string | D84: radio (per calendar day / 24h) | F84: Berechnungsvorgabe Tag | G84: Calculation Guideline_Day | H84: Uitleg calculatie Dag | K84: No | N84: field_1334_1 | O84: rentalcars | Q84: field_1333_1 | R84: camper | S84: conditions_calculation_day
B85: conditions_calculation_season | C85: string | D85: drop down | F85: Berechnungsvorgabe Saison | G85: Calculation Guideline Season | H85: Uitleg calculatie Seizoen | K85: No | N85: field_1337_1 | O85: rentalcars | Q85: field_1336_1 | R85: camper | S85: conditions_calculation_season
A87: Section (open) | B87: section_conditions | C87: alias | D87: group-detail | F87: Details (mehrsprachig) | G87: Details (multilingual) | H87: Details (meertalig)
B88: conditions_driver | C88: string | D88: text input | F88: Fahrer | G88: Drivers | H88: Bestuurder | K88: Yes | L88: rental_companies_conditions_translations | N88: field_452_1 | O88: rentalcars | Q88: field_308_1 | R88: camper | S88: conditions_driver
B89: conditions_licence | C89: string | D89: text input | F89: Führerschein | G89: Driving Licence | H89: Rijbewijs | K89: Yes | L89: rental_companies_conditions_translations | N89: field_1421_1 | O89: rentalcars | Q89: field_800_1 | R89: camper | S89: conditions_licence
B90: conditions_calculation | C90: text | D90: text area | F90: Mietpreisberechnung | G90: Rental Price Calculation | H90: Berekening huurprijs | K90: Yes | L90: rental_companies_conditions_translations | N90: field_864_1 | O90: rentalcars | Q90: field_310_1 | R90: camper | S90: conditions_calculation
B91: conditions_oneway | C91: text | D91: text area | F91: Einwegmieten | G91: One-way Rentals | H91: One way rentals | K91: Yes | L91: rental_companies_conditions_translations | N91: field_456_1 | O91: rentalcars | Q91: field_311_1 | R91: camper | S91: conditions_oneway
B92: has_multi_rental_discount | C92: boolean | D92: boolean (Default: no) | F92: Mehrfachmieten | G92: Multiple Rentals | H92: Gecumuleerde huur | K92: Yes | L92: rental_companies_conditions_translations | N92: NEW | Q92: NEW
B93: conditions_multi_rental_discount | C93: text | D93: text area | F93: Mehrfachmiete Hinweise | G93: Multiple Rentals Remarks | H93: Opmerkingen meervoudige huur | K93: Yes | L93: rental_companies_conditions_translations | N93: field_457_1 | O93: rentalcars | Q93: field_420_1 | R93: camper | S93: conditions_cumulate | V93: Anmietung von mehreren Fahrzeugen für die gleiche Reise
B94: conditions_restricted_area | C94: text | D94: text area | F94: Fahrtgebiete | G94: Permitted Driving Areas | H94: Rijgebieden | K94: Yes | L94: rental_companies_conditions_translations | N94: field_458_1 | O94: rentalcars | Q94: field_313_1 | R94: camper | S94: conditions_restricted_area
B95: conditions_border_crossing | C95: text | D95: text area | F95: Grenzüberschreitungen | G95: Border Crossings | H95: Grensoverschrijdingen | K95: Yes | L95: rental_companies_conditions_translations | N95: field_907_1 | O95: rentalcars | Q95: field_1422_1 | R95: camper | S95: conditions_border_crossing
B96: conditions_insurance | C96: text | D96: text area | F96: Versicherung | G96: Insurance | H96: Verzekering | K96: Yes | L96: rental_companies_conditions_translations | N96: field_462_1 | O96: rentalcars | Q96: field_421_1 | R96: camper | S96: conditions_insurance
B97: conditions_insurance_options | C97: text | D97: text area | F97: Zusatzversicherung | G97: Additional Insurance | H97: Bijkomende verzekering | K97: Yes | L97: rental_companies_conditions_translations | N97: field_459_1 | O97: rentalcars | Q97: field_314_1 | R97: camper | S97: conditions_insurance_options
B98: conditions_all_inclusive | C98: text | D98: text area | F98: All-Inclusive-Paket | G98: All-Inclusive Package | H98: All-Inclusivepakket | K98: Yes | L98: rental_companies_conditions_translations | N98: - | Q98: field_1207_1 | R98: camper | S98: conditions_all_inclusive
B99: conditions_insurance_exclusions | C99: text | D99: text area | F99: Nicht versichert sind | G99: Not Included Are | H99: Er is geen verzekeringsdekking bij | K99: Yes | L99: rental_companies_conditions_translations | N99: field_460_1 | O99: rentalcars | Q99: field_1423_1 | R99: camper | S99: condidtions_insurance_exclusions
B100: conditions_deposit | C100: text | D100: text area | F100: Kaution | G100: Bond (Security Deposit) | H100: Waarborg | K100: Yes | L100: rental_companies_conditions_translations | N100: field_463_1 | O100: rentalcars | Q100: field_422_1 | R100: camper | S100: conditions_deposit
B101: minimum_rental_text | C101: text | D101: text area | F101: Mindestmietdauer | G101: Minimum Rental Period | H101: Minimum huurperiode | K101: Yes | L101: rental_companies_conditions_translations | N101: field_454_1 | O101: rentalcars | Q101: field_309_1 | R101: camper | S101: minimum_rental_text | X101: Kill (see "minimum_rental_days")
B102: conditions_notes | C102: text | D102: text area | F102: Besondere Hinweise | G102: Special Remarks | H102: Bijzondere opmerkingen | I102: Nur Mietwagen. | K102: Yes | L102: rental_companies_conditions_translations | N102: field_865_1 | O102: rentalcars | Q102: - | R102: -
A104: Builder (layer right side) | B104: conditions_supplementary | C104: json | D104: repeater (json) | F104: Ergänzende Beschreibungen | G104: Supplementary Descriptions | H104: Aanvullende beschrijvingen | U104: Repeater for "Headline" + "Text" | AB104: 07.04. "Ergänzende Beischreibungen" - KEIN Rich Text Editor.
B105: headline | C105: string | D105: text input (in repeater) | F105: Überschrift | G105: Headline | H105: Headline | K105: Yes | L105: rental_companies_conditions_translations | N105: field_1306_1 | O105: rentalcars | Q105: field_1282_1 | R105: camper | S105: headline 1
B106: text | C106: text | D106: text area (in repeater) | F106: Text | G106: Text | H106: Tekst | K106: Yes | L106: rental_companies_conditions_translations | N106: field_1307_1 | O106: rentalcars | Q106: field_1283_1 | R106: camper | S106: text 1
B107: headline | C107: string | D107: text input (in repeater) | F107: Überschrift | G107: Headline | H107: Headline | K107: Yes | L107: rental_companies_conditions_translations | N107: field_1308_1 | O107: rentalcars | Q107: field_1284_1 | R107: camper | S107: headline 2
B108: text | C108: text | D108: text area (in repeater) | F108: Text | G108: Text | H108: Tekst | K108: Yes | L108: rental_companies_conditions_translations | N108: field_1309_1 | O108: rentalcars | Q108: field_1285_1 | R108: camper | S108: text 2
B109: headline | C109: string | D109: text input (in repeater) | F109: Überschrift | G109: Headline | H109: Headline | K109: Yes | L109: rental_companies_conditions_translations | N109: field_1310_1 | O109: rentalcars | Q109: field_1286_1 | R109: camper | S109: headline 3
B110: text | C110: text | D110: text area (in repeater) | F110: Text | G110: Text | H110: Tekst | K110: Yes | L110: rental_companies_conditions_translations | N110: field_1311_1 | O110: rentalcars | Q110: field_1287_1 | R110: camper | S110: text 3
A112: Section (closed) | B112: section_car_conditions | C112: alias | D112: group-detail | F112: Mietwagen-spezifische Bedingungen | G112: Car-specific Conditions | H112: Autospecifieke voorwaarden
B113: conditions_hotel_delivery | C113: text | D113: text area | F113: Hotelanlieferung | G113: Hotel Delivery | H113: Leveren/ophalen bij hotel | I113: Nur Mietwagen. | K113: Yes | L113: rental_companies_conditions_translations | N113: field_861_1 | O113: rentalcars | Q113: - | R113: -
...

Sheet #5b rental_depots
A1: Collection | B1: rental_depots
A2: Remarks | B2: M20-collection for "vehicles". Data to be imported ONCE (!) from "rentalcars" and afterwards "camper". Companies and its data will exist more than once. Choose the data set with latest change date!
A3: Date / Update | B3: 46189
A5: Legend | B5: Checked | C5: Changes | D5: Analysis done | E5: Analysis tbd
A7: Details for Directus Set-up | K7: Translatable? | N7: Import Details "rentalcars" | Q7: Import Details "campers" | U7: Remarks / Comments | X7: Legacy
A8: Special field type | B8: field_key Directus | C8: data_type | D8: interface (characters max) | E8: Relation (Sub-Collection) | F8: Label DE | G8: Label GB | H8: Label NL | I8: Info-Text (below the field) | K8: Yes / No | L8: Naming Translation-Collection | N8: fieldid Primarix | O8: parent table | Q8: fieldid Primarix | R8: parent table | S8: field id | U8: Remarks for DEV (field set-up and Import) | V8: Remarks + Tasks internal | X8: Kill after import
A10: Above Tabs | B10: header | C10: alias | D10: header | F10: Header | G10: Header | H10: Header | I10: Page header above the tabs (title + subtitle) | K10: No
A11: Tab-Navigation | B11: ui_tabs | C11: alias | D11: tabs | F11: - | G11: - | H11: -
A13: Tab | B13: tab_master_data | C13: alias | D13: group-raw | F13: Stammdaten | G13: Master Data | H13: Stamgegevens
A14: Section (open) | B14: section_publication | C14: alias | D14: group-detail | F14: Status & Veröffentlichung | G14: Status & Publication | H14: Status & publicatie
B15: object_id | C15: integer | D15: numerical | F15: Objekt-ID | G15: Object-ID | H15: Object-ID | K15: No | N15: oid | O15: rentalcars_depots | Q15: oid | R15: campers | S15: object_id
B16: status_primarix | C16: string | D16: dropdown | F16: Status Primarix | G16: Status Primarix | H16: Status Primarix | K16: No | N16: status (?) | O16: rentalcars_depots | Q16: status (?) | R16: campers | S16: status_primarix
B17: date_updated | C17: dateTime | D17: date | F17: Zuletzt aktualisiert | G17: Last Update | H17: Laatste update | K17: No | N17: (?) | O17: rentalcars_depots | Q17: (?) | R17: campers | S17: date_updated
B18: user_updated | C18: uuid | D18: M2O | E18: directus_users | F18: von | G18: by | H18: door | K18: No | N18: (?) | O18: rentalcars_depots | Q18: (?) | R18: campers | S18: user_updated | U18: Pls show the last editor if possible (in case information is not available in Primarix show "unknown" or similar)
A20: Section (open) | B20: section_depot_details | C20: alias | D20: group-detail | F20: Depot-Daten | G20: Depot Details | H20: Depotgegevens
B21: name_depot | C21: string | D21: text input | F21: Name (Depot) | G21: Name (Depot) | H21: Naam (Depot) | K21: No | N21: field_1245_1 | O21: rentalcars_depots | Q21: field_409_1 | R21: camper_depots | S21: name_depot
A22: Field hidden | B22: depots | C22: alias | D22: M2M | F22: Depots | G22: Depots | H22: Depots | K22: No | N22: field_1327_1 | O22: rentalcars_depots | Q22: field_1024_1 | R22: camper | S22: depots | U22: Legacy import only – not actively used
B23: rental_company | C23: integer | D23: M2O | E23: rental_companies | F23: Vermieter | G23: Rental Company | H23: Verhuurder | K23: No | N23: NEW | Q23: NEW | U23: OID of Rental Company
B24: category | C24: integer | D24: M2O | E24: rental_depot_categories | F24: Kategorie Mietstation | G24: Depot Category | H24: Depotcategorie | K24: No | N24: NEW | Q24: NEW | U24: Import "solved" within by set-up of "rental_companies"
B25: rental_zone | C25: integer | D25: M2O | E25: vehicles_rental_zones | F25: Miet–Zone (Region) | G25: Rental Zone (Region) | H25: Huurzone (regio) | K25: No | N25: field_1246_1 | O25: rentalcars_depots | Q25: - | R25: - | S25: rental_zone | V25: Aktuell 4 Zonen in AUT.
B26: street | C26: string | D26: text input | F26: Straße | G26: Street | H26: Straat | K26: No | N26: field_1247_1 | O26: rentalcars_depots | Q26: field_410_1 | R26: camper_depots | S26: depot_street
B27: street_number | C27: string | D27: text input | F27: Hausnummer | G27: Street Number | H27: Huisnummer | K27: No | N27: field_1248_1 | O27: rentalcars_depots | Q27: field_411_1 | R27: camper_depots | S27: depot_street_number
B28: zip_code | C28: string | D28: text input | F28: PLZ | G28: Postal Code | H28: Postcode | K28: No | N28: field_1249_1 | O28: rentalcars_depots | Q28: field_412_1 | R28: camper_depots | S28: depot_zip_code | U28: Define as non-editable field. In case of editing in Directus the flag is being set automatically.
B29: place | C29: integer | D29: M2O | E29: places | F29: Ort | G29: City / Town | H29: Plaats | K29: No | N29: field_1250_1 | O29: rentalcars_depots | Q29: field_413_1 | R29: camper_depots | S29: depot_town
B30: state | C30: integer | D30: M2O | E30: states | F30: Bundesland | G30: State / Province | H30: Staat / Provincie | K30: No | N30: field_1251_1 | O30: rentalcars_depots | Q30: field_414_1 | R30: camper_depots | S30: depot_state
B31: country | C31: integer | D31: M2O | E31: countries | F31: Land | G31: Country | H31: Land | K31: No | N31: field_1252_1 | O31: rentalcars_depots | Q31: field_415_1 | R31: camper_depots | S31: depot_country
B32: phone_general | C32: string | D32: phone number | F32: Telefon (allgemein) | G32: Phone | H32: Telefoon | K32: No | N32: field_1253_1 | O32: rentalcars_depots | Q32: field_416_1 | R32: camper_depots | S32: depot_phone
B33: fax | D33: - | F33: Fax (allgemein) | N33: field_1254_1 | O33: rentalcars_depots | Q33: field_417_1 | R33: camper_depots | S33: fax
B34: email | C34: string | D34: mail | F34: E-Mail | G34: Email | H34: E-mail | K34: No | N34: field_1255_1 | O34: rentalcars_depots | Q34: field_418_1 | R34: camper_depots | S34: depot_email
B35: surcharge | C35: text | D35: text area | F35: Depot–Zuschlag (for web use) | G35: Depot surcharge (for web use) | H35: Depottoeslag (for web use) | N35: field_1256_1 | O35: rentalcars_depots | Q35: field_1091_1 | R35: camper_depots | S35: depot_surcharge
B36: office_hours_deviating | C36: text | D36: text area | F36: Abweichende Öffnungszeiten | G36: Deviating Opening Hours | H36: Afwijkende openingstijden | K36: Yes | L36: rental_depots_translations | N36: NEW | Q36: field_1403_1 | R36: camper_depots | S36: depot_office_hours_deviating | V36: Öffnungszeiten werden aktuell unter Vermieter "global" gepflegt.
A39: NOTE: | B39: No Image Badge, Media etc.

Sheet #5c vehicles
A1: Collection | B1: vehicles
A2: Remarks | B2: M20-collection for "vehicles". Dat to be imported ONCE (!) from "rentalcars" and aftewardd "camper". Companies and ist data will exist more than once. Choose the data set with latest change data!
A3: Date / Update | B3: 46189
A4: Legend | B4: Checked | C4: Changes | D4: Analysis done | E4: Analysis tbd
A6: Details for Directus Set-up | K6: Translatable? | N6: Import Details "rentalcars" | Q6: Import Details "campers" | U6: Remarks / Comments | X6: Legacy
A7: Special field type | B7: field_key Directus | C7: data_type | D7: interface (characters max) | E7: Relation (Sub-Collection) | F7: Label DE | G7: Label GB | H7: Label NL | I7: Info-Text (below the field) | K7: Yes / No | L7: Naming Translation-Collection | N7: fieldid Primarix | O7: parent table | Q7: fieldid Primarix | R7: parent table | S7: field id | U7: Remarks for DEV (field set-up and Import) | V7: Remarks + Tasks internal | X7: Kill after import
A9: Above Tabs | B9: header | C9: alias | D9: header | F9: Header | G9: Header | H9: Header | I9: Page header above the tabs (title + subtitle) | K9: No
A10: Tab-Navigation | B10: ui_tabs | C10: alias | D10: tabs | F10: - | G10: - | H10: -
A12: Tab | B12: tab_master_data | C12: alias | D12: group-raw | F12: Stammdaten | G12: Master Data | H12: Stamgegevens
A13: Block | B13: block_publication | C13: alias | D13: group-raw | F13: - | G13: - | H13: -
A14: Section (open) | B14: section_publication | C14: alias | D14: group-detail | F14: Status & Veröffentlichung | G14: Status & Publication | H14: Status & publicatie
B15: object_id | C15: integer | D15: numerical | F15: Objekt-ID | G15: Object-ID | H15: Object-ID | K15: No | N15: oid | O15: rentalcars_vehicle | Q15: oid | R15: campers | S15: object_id
B16: status_primarix | C16: string | D16: dropdown | F16: Status Primarix | G16: Status Primarix | H16: Status Primarix | K16: No | N16: status (?) | O16: rentalcars_vehicle | Q16: status (?) | R16: campers | S16: status_primarix
B17: date_updated | C17: dateTime | D17: date | F17: Zuletzt aktualisiert | G17: Last Update | H17: Laatste update | K17: No | N17: (?) | O17: rentalcars_vehicle | Q17: (?) | R17: campers | S17: date_updated
B18: user_updated | C18: uuid | D18: M2O | E18: directus_users | F18: von | G18: by | H18: door | K18: No | N18: (?) | O18: rentalcars_vehicle | Q18: (?) | R18: campers | S18: user_updated | U18: Pls show the last editor if possible (in case information is not available in Primarix show "unknown" or similar)
A20: Section (closed) | B20: section_botg_companies | C20: alias | D20: group-detail | F20: BOTG-Firmen-Zuordnung | G20: BOTG Company Assignment | H20: BOTG-bedrijfstoewijzing
B21: partner_visibility | C21: string | D21: radio button (all / selected) | K21: No | N21: NEW | Q21: NEW | S21: partner_type | U21: Default: "all"
B22: partner_selected | C22: alias | D22: M2M | E22: partner | K22: No | N22: field_1104_1 | O22: rentalcars | Q22: field_1105_1 | R22: campers | S22: partner
A24: Block | B24: block_vehicle_basics | C24: alias | D24: group-raw | F24: - | G24: - | H24: -
A25: Section (open) | B25: section_type_company | C25: alias | D25: group-detail | F25: Typ & Vermieter | G25: Type & Company | H25: Type & verhuurder
B26: rental_type | C26: string | D26: radio | F26: Typ | G26: Type | H26: Type | K26: No | N26: NEW | Q26: NEW | S26: rental_type | U26: "Car" or "Camper"
B27: name_vehicle | C27: string | D27: text input | F27: Name (Fahrzeug) | G27: Name (Vehicle) | H27: Naam (voertuig) | K27: No | N27: field_1033_1 | O27: rentalcars_vehicle | Q27: field_259_1 | R27: camper_vehicle | S27: vehicle_title
B28: rental_company | C28: integer | D28: M2O | E28: rental_companies | F28: Vermieter | G28: Rental Company | H28: Verhuurder | K28: No | N28: NEW | Q28: NEW | S28: rental_company | U28: OID of Rental Company
B29: category | C29: integer | D29: many to one | E29: vehicle_categories | F29: Fahrzeugkategorie | G29: Vehicle Category | H29: Voertuigcategorie | K29: No | N29: field_465_1 | O29: rentalcars_vehicle | Q29: - | R29: -
B30: supplier_product_code | C30: string | D30: text input | F30: Buchungscode Supplier | G30: Supplier Booking Code | H30: Supplier boekingscode | K30: No | N30: field_866_1 | O30: rentalcars_vehicle | Q30: field_877_1 | R30: camper_vehicle | S30: vehicle_supplier_product_code
B31: depot_availability | C31: string | D31: radio button (all / selected) | F31: Wagen an allen Depots verfügbar | G31: Available at all depots | H31: Beschikbaar op alle depots | K31: No | N31: NEW | Q31: NEW | U31: rentalcars: default "true"; campers: default "false"
B32: depots_selected | C32: alias | D32: M2M | E32: rental_depots | F32: Verfügbar an folgenden Stationen | G32: Available at the following stations | H32: Beschikbaar op de volgende stations | K32: No | N32: - | O32: - | Q32: field_1068_1 | R32: camper_vehicle | S32: depots_available
A34: Tab | B34: tab_description | C34: alias | D34: group-raw | F34: Beschreibung | G34: Description | H34: Beschrijving
A35: Section (open) | B35: section_attributes | C35: alias | D35: group-detail | F35: Merkmale | G35: Attributes | H35: Kenmerken
B36: drive_type | C36: string | D36: radio (2wd / 4wd) | F36: Antriebsart | G36: Drive type | H36: Aandrijving | K36: No | N36: field_1063_1 | O36: rentalcars_vehicle | Q36: field_1054_1 | R36: camper_vehicle | S36: drive_type
B37: persons_max | C37: integer | D37: numeric (1-6) | F37: Anzahl Personen maximal | G37: Maximum number of persons | H37: Maximaal aantal personen | K37: No | N37: field_1440_1 | O37: rentalcars_vehicle | Q37: field_1053_1 | R37: camper_vehicle | S37: vehicle_persons_max
B38: suitcase_big | C38: integer | D38: numerical | F38: Koffer groß | G38: Large suitcase | H38: Grote koffer | K38: No | N38: field_1441_1 | O38: rentalcars_vehicle | Q38: - | R38: - | S38: vehicle_suitcase_big
B39: suitcase_small | C39: integer | D39: numerical | F39: Koffer klein | G39: Small suitcase | H39: Kleine koffer | K39: No | N39: field_1442_1 | O39: rentalcars_vehicle | Q39: - | R39: - | S39: vehicle_suitcase_small
A41: Section (open) | B41: section_descriptions | C41: alias | D41: group-detail | F41: Beschreibungstexte | G41: Descriptions | H41: Beschrijvingen
B42: subline | C42: string | D42: text input | F42: Subline Fahrzeug | G42: Vehicle subline | H42: Voertuig subline | K42: Yes | L42: vehicles_descriptions_translations | N42: NEW | O42: - | Q42: field_260_1 | R42: camper_vehicle | S42: vehicle_subline
B43: teaser | C43: text | D43: text area | F43: Einleitungstext | G43: Introduction text | H43: Inleidende tekst | K43: Yes | L43: vehicles_descriptions_translations | N43: NEW | O43: - | Q43: field_261_1 | R43: camper_vehicle | S43: vehicle_teaser
B44: description | C44: text | D44: text area | F44: Fahrzeugbeschreibung | G44: Vehicle description | H44: Voertuigbeschrijving | K44: Yes | L44: vehicles_descriptions_translations | N44: field_466_1 | O44: rentalcars_vehicle | Q44: field_262_1 | R44: camper_vehicle | S44: vehicle_description
B45: equipment | C45: text | D45: text area | F45: Fahrzeugausstattung | G45: Vehicle equipment | H45: Voertuiguitrusting | K45: Yes | L45: vehicles_descriptions_translations | N45: field_899_1 | O45: rentalcars_vehicle | Q45: field_264_1 | R45: camper_vehicle | S45: vehicle_equipment
B46: bond | C46: text | D46: text area | F46: Abweichende Kautionsbdeingungen | G46: Additional notes | H46: Overige opmerkingen | I46: Warnungen od. andere Hinweise. | K46: Yes | L46: vehicles_descriptions_translations | N46: field_902_1 | O46: rentalcars_vehicle | Q46: - | R46: - | S46: bond
D47: - | G47: URL alias | H47: URL-alias | N47: - | Q47: field_1460_1 | R47: camper_vehicle
B48: descriptions_supplementary | C48: json | D48: repeater (json) | F48: Ergänzende Beschreibungen | G48: Supplementary Descriptions | H48: Aanvullende beschrijvingen | K48: Yes | L48: vehicles_descriptions_translations | S48: vehicles_descriptions_supplementary
A50: Builder (layer right side) | B50: description_supplementary | C50: json | D50: repeater (json) | F50: Ergänzende Beschreibungen | G50: Supplementary Descriptions | H50: Aanvullende beschrijvingen | U50: Repeater for "Headline" + "Text" | AB50: 07.04. "Ergänzende Beischreibungen" - KEIN Rich Text Editor.
B51: headline | D51: text input (in repeater) | F51: Überschrift | G51: Headline | H51: Headline | K51: Yes | L51: vehicles_descriptions_translations | N51: field_1243_1 | O51: rentalcars_vehicle | Q51: - | R51: - | S51: mietwagen fahrzeuge headline 1
B52: text | D52: text area (in repeater) | F52: Text | G52: Text | H52: Tekst | K52: Yes | L52: vehicles_descriptions_translations | N52: field_1244_1 | O52: rentalcars_vehicle | Q52: - | R52: - | S52: mietwagen fahrzeuge text 1
A54: Section (closed) | B54: section_camper_descriptions | C54: alias | D54: group-detail | F54: Camper Descriptions | G54: Camper Descriptions | H54: Camperbeschrijvingen
B55: bedsize | C55: string | D55: text input | F55: Bettenmaße | G55: Bed Dimensions | H55: Bedmaten | K55: Yes | L55: vehicles_descriptions_translations | N55: - | O55: - | Q55: field_263_1 | R55: camper_vehicle | S55: vehicle_bedsize
B56: camping_equipment | C56: string | D56: radio (non-equipped / equipped) | F56: Campingausstattung | G56: Camping equipment | H56: Kampeeruitrusting | K56: No* | L56: vehicles_descriptions_translations | N56: field_1455_1 | O56: rentalcars_vehicle | Q56: field_1454_1 | R56: camper_vehicle | S56: camping_equipment
A58: Tab | B58: tab_calculator_inputs | C58: alias | D58: group-raw | F58: Kalkulator-Eingaben | G58: Calculator Basics | H58: Calculator-basis
A59: COMMENT | B59: Tab should be a 1:1 copy from "rental_companies"
A60: Block | B60: block_price_basics | C60: alias | D60: group-raw | F60: - | G60: - | H60: -
A61: Section (closed) | B61: section_price_basic | C61: alias | D61: group-detail | F61: Preisgrundlagen | G61: Price Basics | H61: Prijsgrondslagen
A62: Builder (layer right side) | F62: Preis-Zonen | G62: Price Zones | H62: Prijszones | U62: Today data per "rental company!
A63: Note: These would be by default the data from "rental_companies". Ideally the user could add, edit and sort as well.
B64: ='#5a rental_companies'!B162 -> rental_period_zone | C64: ='#5a rental_companies'!C162 -> integer | D64: ='#5a rental_companies'!D162 -> M2O | E64: ='#5a rental_companies'!E162 -> vehicles_rental_zones | F64: ='#5a rental_companies'!F162 -> Preis-Zonen | G64: ='#5a rental_companies'!G162 -> Price Zones | H64: ='#5a rental_companies'!H162 -> Prijszones | I64: ='#5a rental_companies'!I162 -> 0 | K64: ='#5a rental_companies'!K162 -> No | L64: ='#5a rental_companies'!L162 -> 0 | N64: ='#5a rental_companies'!N162 -> field_875_1 | O64: ='#5a rental_companies'!O162 -> rentalcars_rental_period | U64: Data should be imported within set-up or rental companies!
A65: ='#5a rental_companies'!A163 -> COMMENT | B65: ='#5a rental_companies'!B163 -> Sortierung = Directus-System-Feld `sort` (kein eigenes Feld) | C65: ='#5a rental_companies'!C163 -> 0 | D65: ='#5a rental_companies'!D163 -> 0 | U65: Data should be imported within set-up or rental companies!
A67: Builder (layer right side) | F67: Preis-Zeiträume | G67: Price Periods | H67: Prijsperioden
A68: Note: These would be by default the data from "rental_companies". Ideally the user could add, edit and sort as well.
B69: ='#5a rental_companies'!B167 -> price_period_start | C69: ='#5a rental_companies'!C167 -> date | D69: ='#5a rental_companies'!D167 -> date (from - till) | E69: ='#5a rental_companies'!E167 -> vehicles_price_periods | F69: ='#5a rental_companies'!F167 -> von | G69: ='#5a rental_companies'!G167 -> from | H69: ='#5a rental_companies'!H167 -> van | I69: ='#5a rental_companies'!I167 -> 0 | K69: ='#5a rental_companies'!K167 -> No | L69: ='#5a rental_companies'!L167 -> 0 | N69: ='#5a rental_companies'!N167 -> field_467_1 | O69: ='#5a rental_companies'!O167 -> rentalcars_price_periods | Q69: ='#5a rental_companies'!Q167 -> field_392_1 | R69: ='#5a rental_companies'!R167 -> camper | S69: ='#5a rental_companies'!S167 -> price_period_start | U69: Data should be imported within set-up or rental companies!
B70: price_period_end | C70: date | D70: date (from - till) | E70: vehicles_price_periods | F70: bis | G70: to | H70: tot | K70: No | N70: field_467_2 | O70: rentalcars_price_periods | Q70: ='#5a rental_companies'!Q168 -> field_392_2 | R70: ='#5a rental_companies'!R168 -> camper | S70: price_period_end | U70: Data should be imported within set-up or rental companies!
B71: price_period_end | C71: date | D71: date (from - till) | E71: vehicles_price_periods | F71: bis | G71: to | H71: tot | K71: No | N71: field_467_2 | O71: rentalcars_price_periods | Q71: ='#5a rental_companies'!Q169 -> NEW | R71: ='#5a rental_companies'!R169 -> — | S71: price_period_end | U71: Data should be imported within set-up or rental companies!
A72: ='#5a rental_companies'!A170 -> COMMENT | B72: ='#5a rental_companies'!B170 -> Sortierung = Directus-System-Feld `sort` (kein eigenes Feld) | C72: ='#5a rental_companies'!C170 -> 0 | D72: ='#5a rental_companies'!D170 -> 0 | U72: Data should be imported within set-up or rental companies!
A74: Builder (layer right side) | F74: Mietdauern | G74: Rental Periods | H74: Huurperiodes
A75: Note: These would be by default the data from "rental_companies". Ideally the user could add, edit and sort as well.
B76: ='#5a rental_companies'!B174 -> rental_period_depot_category | C76: ='#5a rental_companies'!C174 -> integer | D76: ='#5a rental_companies'!D174 -> M2O | E76: ='#5a rental_companies'!E174 -> rental_depot_categories | F76: ='#5a rental_companies'!F174 -> Kategorie Mietstation | G76: ='#5a rental_companies'!G174 -> Depot Category | H76: ='#5a rental_companies'!H174 -> Depotcategorie | I76: ='#5a rental_companies'!I174 -> Nur Mietwagen. | K76: ='#5a rental_companies'!K174 -> No | L76: ='#5a rental_companies'!L174 -> 0 | N76: ='#5a rental_companies'!N174 -> field_875_1 | O76: ='#5a rental_companies'!O174 -> rentalcars_rental_period | Q76: ='#5a rental_companies'!Q174 -> - | R76: ='#5a rental_companies'!R174 -> - | S76: ='#5a rental_companies'!S174 -> 0 | U76: Data should be imported within set-up or rental companies!
B77: ='#5a rental_companies'!B175 -> rental_period_min | C77: ='#5a rental_companies'!C175 -> numeric | D77: ='#5a rental_companies'!D175 -> text input | E77: ='#5a rental_companies'!E175 -> vehicles_rental_periods | F77: ='#5a rental_companies'!F175 -> Tage Min. | G77: ='#5a rental_companies'!G175 -> Days min. | H77: ='#5a rental_companies'!H175 -> Dagen min. | I77: ='#5a rental_companies'!I175 -> 0 | K77: ='#5a rental_companies'!K175 -> No | L77: ='#5a rental_companies'!L175 -> 0 | N77: ='#5a rental_companies'!N175 -> field_468_1 | O77: ='#5a rental_companies'!O175 -> rentalcars_rental_period | Q77: ='#5a rental_companies'!Q175 -> field_423_1 | R77: ='#5a rental_companies'!R175 -> camper_rental_period | S77: ='#5a rental_companies'!S175 -> rental_period_min | U77: Data should be imported within set-up or rental companies!
B78: ='#5a rental_companies'!B176 -> rental_period_max | C78: ='#5a rental_companies'!C176 -> numeric | D78: ='#5a rental_companies'!D176 -> text input | E78: ='#5a rental_companies'!E176 -> vehicles_rental_periods | F78: ='#5a rental_companies'!F176 -> Tage Max. | G78: ='#5a rental_companies'!G176 -> Days max. | H78: ='#5a rental_companies'!H176 -> Dagen max. | I78: ='#5a rental_companies'!I176 -> 0 | K78: ='#5a rental_companies'!K176 -> No | L78: ='#5a rental_companies'!L176 -> 0 | N78: ='#5a rental_companies'!N176 -> field_469_1 | O78: ='#5a rental_companies'!O176 -> rentalcars_rental_period | Q78: ='#5a rental_companies'!Q176 -> field_424_1 | R78: ='#5a rental_companies'!R176 -> camper_rental_period | S78: ='#5a rental_companies'!S176 -> rental_period_min | U78: Data should be imported within set-up or rental companies!
B79: ='#5a rental_companies'!B177 -> rental_period_duration | C79: ='#5a rental_companies'!C177 -> text | D79: ='#5a rental_companies'!D177 -> text input | E79: ='#5a rental_companies'!E177 -> vehicles_rental_periods | F79: ='#5a rental_companies'!F177 -> Mietdauer | G79: ='#5a rental_companies'!G177 -> Rental Duration | H79: ='#5a rental_companies'!H177 -> Huurduur | I79: ='#5a rental_companies'!I177 -> Nur Mietwagen: Mietdauer-Staffel als Tagesbereich (z. B. „1-3", „4-6", „14+"). Einheitliches Format ohne Spracheinheit verwenden. | K79: ='#5a rental_companies'!K177 -> No | L79: ='#5a rental_companies'!L177 -> 0 | N79: ='#5a rental_companies'!N177 -> field_898_1 | O79: ='#5a rental_companies'!O177 -> rentalcars_rental_period | Q79: ='#5a rental_companies'!Q177 -> - | R79: ='#5a rental_companies'!R177 -> - | S79: ='#5a rental_companies'!S177 -> 0 | U79: Data should be imported within set-up or rental companies!
B80: ='#5a rental_companies'!B178 -> rental_period_from | C80: ='#5a rental_companies'!C178 -> boolean | D80: ='#5a rental_companies'!D178 -> checkbox (boolean) | E80: ='#5a rental_companies'!E178 -> vehicles_rental_periods | F80: ='#5a rental_companies'!F178 -> Ab-Preis | G80: ='#5a rental_companies'!G178 -> Starting Price | H80: ='#5a rental_companies'!H178 -> Vanafprijs | I80: ='#5a rental_companies'!I178 -> Definiert, dass dies die Grundlage für den Ab-Preis ist. | K80: ='#5a rental_companies'!K178 -> No | L80: ='#5a rental_companies'!L178 -> 0 | N80: ='#5a rental_companies'!N178 -> NEW | O80: ='#5a rental_companies'!O178 -> — | Q80: ='#5a rental_companies'!Q178 -> NEW | R80: ='#5a rental_companies'!R178 -> — | S80: ='#5a rental_companies'!S178 -> 0 | U80: Data should be imported within set-up or rental companies!
A81: ='#5a rental_companies'!A179 -> COMMENT | B81: ='#5a rental_companies'!B179 -> Sortierung = Directus-System-Feld `sort` (kein eigenes Feld) | C81: ='#5a rental_companies'!C179 -> 0 | D81: ='#5a rental_companies'!D179 -> 0 | U81: Data should be imported within set-up or rental companies!
A83: Block | B83: block_surcharges | C83: alias | D83: group-raw | F83: - | G83: - | H83: -
A84: Section (closed) | B84: section_surcharge_basics | C84: alias | D84: group-detail | F84: Grundlagen Zuschläge | G84: Basics Surcharges | H84: Basis toeslagen
A85: Builder (layer right side) | F85: Zuschläge | G85: Surcharges | H85: Toeslagen
A86: Note: These would be by default the data from "rental_companies". Ideally the user could add, edit and sort as well.
B87: ='#5a rental_companies'!B184 -> surcharge_booking_name | C87: ='#5a rental_companies'!C184 -> string | D87: ='#5a rental_companies'!D184 -> text input | E87: ='#5a rental_companies'!E184 -> vehicles_surcharges | F87: ='#5a rental_companies'!F184 -> Original-/Buchungsbezeichnung | G87: ='#5a rental_companies'!G184 -> Original / Booking Name | H87: ='#5a rental_companies'!H184 -> Originele / Boekingsbenaming | I87: ='#5a rental_companies'!I184 -> 0 | K87: ='#5a rental_companies'!K184 -> No | L87: ='#5a rental_companies'!L184 -> 0 | N87: ='#5a rental_companies'!N184 -> field_923_1 | O87: ='#5a rental_companies'!O184 -> rentalcars_surcharges | Q87: ='#5a rental_companies'!Q184 -> field_1475_1 | R87: ='#5a rental_companies'!R184 -> camper_surcharges | S87: ='#5a rental_companies'!S184 -> surcharge_booking_name | U87: Data should be imported within set-up or rental companies!
B88: ='#5a rental_companies'!B185 -> surcharge_description | C88: ='#5a rental_companies'!C185 -> text | D88: ='#5a rental_companies'!D185 -> text area | E88: ='#5a rental_companies'!E185 -> vehicles_surcharges | F88: ='#5a rental_companies'!F185 -> Beschreibung | G88: ='#5a rental_companies'!G185 -> Description | H88: ='#5a rental_companies'!H185 -> Beschrijving | I88: ='#5a rental_companies'!I185 -> 0 | K88: ='#5a rental_companies'!K185 -> Yes | L88: ='#5a rental_companies'!L185 -> rental_companies_surcharges_translations | N88: ='#5a rental_companies'!N185 -> field_921_1 | O88: ='#5a rental_companies'!O185 -> rentalcars_surcharges | Q88: ='#5a rental_companies'!Q185 -> field_971_1 | R88: ='#5a rental_companies'!R185 -> camper_surcharges | S88: ='#5a rental_companies'!S185 -> surcharge_description | U88: Data should be imported within set-up or rental companies!
B89: ='#5a rental_companies'!B186 -> surcharge_type | C89: ='#5a rental_companies'!C186 -> string | D89: ='#5a rental_companies'!D186 -> dropdown | E89: ='#5a rental_companies'!E186 -> vehicles_surcharges | F89: ='#5a rental_companies'!F186 -> Art des Zuschlags | G89: ='#5a rental_companies'!G186 -> Surcharge Type | H89: ='#5a rental_companies'!H186 -> Type toeslag | I89: ='#5a rental_companies'!I186 -> Obligatorisch oder optional? | K89: ='#5a rental_companies'!K186 -> No (*) | L89: ='#5a rental_companies'!L186 -> 0 | N89: ='#5a rental_companies'!N186 -> field_1393_1 | O89: ='#5a rental_companies'!O186 -> rentalcars_surcharges | Q89: ='#5a rental_companies'!Q186 -> field_1392_1 | R89: ='#5a rental_companies'!R186 -> camper_surcharges | S89: ='#5a rental_companies'!S186 -> surcharge_type | U89: Data should be imported within set-up or rental companies!
B90: ='#5a rental_companies'!B187 -> surcharge_calc_type | C90: ='#5a rental_companies'!C187 -> string | D90: ='#5a rental_companies'!D187 -> dropdown | E90: ='#5a rental_companies'!E187 -> vehicles_surcharges | F90: ='#5a rental_companies'!F187 -> Berechnungsart (für IT-Systeme) | G90: ='#5a rental_companies'!G187 -> Calculation Method (for IT Systems) | H90: ='#5a rental_companies'!H187 -> Berekeningswijze (voor IT-systemen) | I90: ='#5a rental_companies'!I187 -> 0 | K90: ='#5a rental_companies'!K187 -> No (*) | L90: ='#5a rental_companies'!L187 -> 0 | N90: ='#5a rental_companies'!N187 -> field_1449_1 | O90: ='#5a rental_companies'!O187 -> rentalcars_surcharges | Q90: ='#5a rental_companies'!Q187 -> field_1448_1 | R90: ='#5a rental_companies'!R187 -> camper_surcharges | S90: ='#5a rental_companies'!S187 -> surcharge_calc_type | U90: Data should be imported within set-up or rental companies!
A92: Tab | B92: tab_price_calculation | C92: alias | D92: group-raw | F92: Preise | G92: Prices | H92: Prijzen
A93: Section (open) | B93: section_units_margins | C93: alias | D93: group-detail | F93: Einheiten & Margen | G93: Units & Margins | H93: Eenheden & marges
A94: COMMENT | B94: calculator as developed for hotels
B95: buy_price_type | C95: string | D95: select-dropdown | E95: vehicles_price_calculation | F95: Einkaufspreis-Typ | G95: Buy Price Type | H95: Inkoopprijstype | K95: Yes | L95: vehicles_price_calculation_translations
B96: sell_price_type | C96: string | D96: select-dropdown | E96: vehicles_price_calculation | F96: Verkaufspreis-Typ | G96: Sell Price Type | H96: Verkoopprijstype | K96: Yes | L96: vehicles_price_calculation_translations
B97: percentage_type | C97: string | D97: select-dropdown | E97: vehicles_price_calculation | F97: Prozent-Typ | G97: Percentage Type | H97: Percentagetype | K97: Yes | L97: vehicles_price_calculation_translations
B98: provision_percentage | C98: float | D98: input | E98: vehicles_price_calculation | F98: Provision % | G98: Provision % | H98: Provisie % | I98: Only applies if "Buy Price Type" is set to "Gross". | K98: Yes | L98: vehicles_price_calculation_translations
B99: margin_percentage | C99: float | D99: input | E99: vehicles_price_calculation | F99: Marge % | G99: Margin % | H99: Marge % | K99: Yes | L99: vehicles_price_calculation_translations
B100: exchange_rate | C100: json | D100: collection-item-dropdown | E100: vehicles_price_calculation | F100: Wechselkurs | G100: Exchange Rate | H100: Wisselkoers | K100: Yes | L100: vehicles_price_calculation_translations
B101: from_price | C101: integer | D101: select-dropdown-m2o | E101: vehicles_price_calculation | F101: Ab-Preis | G101: From Price | H101: Vanafprijs | I101: This field will be auto-populated once price basics have been added and sell prices have been calculated. | K101: Yes | L101: vehicles_price_calculation_translations
A103: Section (open) | B103: section_vehicle_prices | C103: alias | D103: group-detail | F103: Fahrzeug-Preise | G103: Vehicle Prices | H103: Voertuigprijzen
A104: COMMENT | B104: calculator as developed for hotels
B105: vehicle_prices | C105: alias | D105: prices-table (extension) | E105: vehicles_price_calculation | F105: Fahrzeug-Preise | G105: Vehicle Prices | H105: Voertuigprijzen | K105: Yes | L105: vehicles_price_calculation_translations
B106: save_stay_vehicle | C106: alias | D106: save-and-stay-trigger-flow | E106: vehicles_price_calculation | F106: Speichern & bleiben | G106: Save & Stay | H106: Opslaan & blijven | K106: Yes | L106: vehicles_price_calculation_translations
A108: Tab | B108: tab_surcharge_calculation | C108: alias | D108: group-raw | F108: Zuschlagsberechnung | G108: Surcharge Calculation | H108: Toeslagberekening
A109: Section (open) | B109: section_units_margins | C109: alias | D109: group-detail | F109: Einheiten & Margen | G109: Units & Margins | H109: Eenheden & marges
A110: COMMENT | B110: calculator as developed for hotels
B111: surcharge_percentage_type | C111: string | D111: select-dropdown | E111: vehicles_surcharges_calculation | F111: Prozent-Typ | G111: Percentage Type | H111: Percentagetype | K111: Yes | L111: vehicles_surcharges_calculation_translations
B112: surcharge_provision_percentage | C112: float | D112: input | E112: vehicles_surcharges_calculation | F112: Provision % | G112: Provision % | H112: Provisie % | I112: Only applies if "Surcharge Buy Price Type" is set to "Gross". | K112: Yes | L112: vehicles_surcharges_calculation_translations
B113: surcharge_margin_percentage | C113: float | D113: input | E113: vehicles_surcharges_calculation | F113: Marge % | G113: Margin % | H113: Marge % | K113: Yes | L113: vehicles_surcharges_calculation_translations
B114: surcharge_exchange_rate | C114: json | D114: collection-item-dropdown | E114: vehicles_surcharges_calculation | F114: Wechselkurs | G114: Exchange Rate | H114: Wisselkoers | K114: Yes | L114: vehicles_surcharges_calculation_translations
A116: Section (open) | B116: section_surcharges | C116: alias | D116: group-detail | F116: Zuschläge | G116: Surcharges | H116: Toeslagen
A117: COMMENT | B117: calculator as developed for hotels
...

Sheet #5d camper_specs
A1: Collection | B1: camper_specs
A2: Remarks | B2: Sub-collection (O2O to vehicles, only rental_type=Camper). Source: Dreamtime factsheets + camper_vehicle.
A3: Date / Update | B3: 46189
A4: Legend | B4: Checked | C4: Changes | D4: Analysis done | E4: Analysis tbd
A6: Details for Directus Set-up | K6: Translatable? | N6: Import Details "rentalcars" | Q6: Import Details "campers" | U6: Remarks / Comments | X6: Legacy
A7: Special field type | B7: field_key Directus | C7: data_type | D7: interface (characters max) | E7: Relation (Sub-Collection) | F7: Label DE | G7: Label GB | H7: Label NL | I7: Info-Text (below the field) | K7: Yes / No | L7: Naming Translation-Collection | N7: fieldid Primarix | O7: parent table | Q7: fieldid Primarix | R7: parent table | S7: field id | U7: Remarks for DEV (field set-up and Import) | V7: Remarks + Tasks internal | X7: Kill after import
A9: Above Tabs | B9: header | C9: alias | D9: header | F9: Header | G9: Header | H9: Header | I9: Page header above the tabs (title + subtitle) | K9: No
A10: Tab-Navigation | B10: ui_tabs | C10: alias | D10: tabs | F10: - | G10: - | H10: -
A12: Tab | B12: tab_master_data | C12: alias | D12: group-raw | F12: Stammdaten | G12: Master Data | H12: Stamgegevens
A13: Section (open) | B13: section_status_relation | C13: alias | D13: group-detail | F13: Status & Relation | G13: Status & Relation | H13: Status & relatie
B14: vehicle | C14: integer | D14: O2O | E14: vehicles | F14: Fahrzeug | G14: Vehicle | H14: Voertuig | K14: No | Q14: NEW | R14: - | S14: vehicle | U14: Owner relation to vehicles (O2O; only rental_type=Camper)
B15: date_updated | C15: dateTime | D15: datetime | F15: Zuletzt aktualisiert | G15: Last Updated | H15: Laatst bijgewerkt | K15: No | S15: date_updated | U15: Directus standard
B16: user_updated | C16: uuid | D16: M2O | E16: directus_users | F16: von | G16: by | H16: door | K16: No | S16: user_updated | U16: Directus standard
A18: Tab | B18: tab_technical_data | C18: alias | D18: group-raw | F18: Technische Daten | G18: Technical Data | H18: Technische gegevens
A19: Section | B19: section_dimensions | C19: alias | D19: group-detail | F19: Maße & Kapazität | G19: Dimensions & Capacity | H19: Afmetingen & capaciteit
B20: berths_adults | C20: integer | D20: numerical | F20: Schlafplätze (Erw.) | G20: Berths (Adults) | H20: Slaapplaatsen (volw.) | K20: No | Q20: NEW | R20: Dreamtime | S20: berths_adults
B21: berths_children | C21: integer | D21: numerical | F21: Schlafplätze (Kinder) | G21: Berths (Children) | H21: Slaapplaatsen (kind.) | K21: No | Q21: NEW | R21: Dreamtime | S21: berths_children
B22: seats_cab | C22: integer | D22: numerical | F22: Sitzplätze Fahrerhaus | G22: Seats (Cab) | H22: Zitplaatsen (cabine) | K22: No | Q22: NEW | R22: Dreamtime | S22: seats_cab
B23: seats_living | C23: integer | D23: numerical | F23: Sitzplätze Wohnraum | G23: Seats (Living Area) | H23: Zitplaatsen (woonruimte) | K23: No | Q23: NEW | R23: Dreamtime | S23: seats_living
B24: length_m | C24: decimal | D24: numerical | F24: Länge | G24: Length | H24: Lengte | I24: in Metern (m) | K24: No | Q24: NEW | R24: Dreamtime | S24: length_m
B25: width_m | C25: decimal | D25: numerical | F25: Breite | G25: Width | H25: Breedte | I25: in Metern (m) | K25: No | Q25: NEW | R25: Dreamtime | S25: width_m
B26: height_m | C26: decimal | D26: numerical | F26: Höhe | G26: Height | H26: Hoogte | I26: in Metern (m) | K26: No | Q26: NEW | R26: Dreamtime | S26: height_m
B27: interior_height_m | C27: decimal | D27: numerical | F27: Innenhöhe | G27: Interior Height | H27: Binnenhoogte | I27: in Metern (m) | K27: No | Q27: NEW | R27: Dreamtime | S27: interior_height_m
A29: Section | B29: section_drivetrain | C29: alias | D29: group-detail | F29: Antrieb & Motor | G29: Drivetrain & Engine | H29: Aandrijving & motor
B30: transmission | C30: string | D30: select-dropdown | F30: Getriebe | G30: Transmission | H30: Transmissie | I30: Schalt / Automatik | K30: No | Q30: NEW | R30: Dreamtime | S30: transmission
B31: fuel_type | C31: string | D31: select-dropdown | F31: Treibstoff | G31: Fuel Type | H31: Brandstof | I31: Diesel / Benzin / … | K31: No | Q31: NEW | R31: Dreamtime | S31: fuel_type
B32: engine_power_kw | C32: integer | D32: numerical | F32: Motorleistung | G32: Engine Power | H32: Motorvermogen | I32: in kW | K32: No | Q32: NEW | R32: Dreamtime | S32: engine_power_kw
B33: fuel_tank_l | C33: integer | D33: numerical | F33: Treibstofftank | G33: Fuel Tank | H33: Brandstoftank | I33: in Litern (L) | K33: No | Q33: NEW | R33: Factsheet | S33: fuel_tank_l
A35: Section | B35: section_beds | C35: alias | D35: group-detail | F35: Betten | G35: Beds | H35: Bedden
B36: beds | C36: json | D36: repeater | F36: Betten | G36: Beds | H36: Bedden | K36: No | S36: beds | U36: Repeater 1..n. Legacy field_263_1 is free text - not auto-parsable into length/width
B37: bed_type | C37: string | D37: select-dropdown (repeater) | F37: Typ | G37: Type | H37: Type | I37: Festbett / Hubdach / … | K37: No | S37: bed_type | U37: Sub-field in beds repeater
B38: bed_length_cm | C38: integer | D38: numerical (repeater) | F38: Länge | G38: Length | H38: Lengte | I38: in cm | K38: No | S38: bed_length_cm | U38: Sub-field in beds repeater
B39: bed_width_cm | C39: integer | D39: numerical (repeater) | F39: Breite | G39: Width | H39: Breedte | I39: in cm | K39: No | S39: bed_width_cm | U39: Sub-field in beds repeater
A41: Section | B41: section_kitchen_water | C41: alias | D41: group-detail | F41: Küche & Wasser | G41: Kitchen & Water | H41: Keuken & water
B42: fridge_l | C42: integer | D42: numerical | F42: Kühlschrank | G42: Fridge | H42: Koelkast | I42: in Litern (L) | K42: No | Q42: NEW | R42: Dreamtime | S42: fridge_l
B43: freshwater_tank_l | C43: integer | D43: numerical | F43: Frischwassertank | G43: Fresh Water Tank | H43: Schoonwatertank | I43: in Litern (L) | K43: No | Q43: NEW | R43: Dreamtime | S43: freshwater_tank_l
B44: wastewater_tank_l | C44: integer | D44: numerical | F44: Abwassertank | G44: Waste Water Tank | H44: Afvalwatertank | I44: in Litern (L) | K44: No | Q44: NEW | R44: Dreamtime | S44: wastewater_tank_l
A46: Tab | B46: tab_equipment | C46: alias | D46: group-raw | F46: Ausstattung | G46: Equipment | H46: Uitrusting
A47: Section | B47: section_equipment_checklist | C47: alias | D47: group-detail | F47: Ausstattungs-Checkliste | G47: Equipment Checklist | H47: Uitrustingschecklist
B48: equipment_features | C48: alias | D48: M2M | E48: camper_equipment | F48: Ausstattung | G48: Equipment | H48: Uitrusting | K48: No | S48: equipment_features | U48: M2M via junction camper_specs_equipment; junction carries tri-state availability (available/optional/included)
A50: Section | B50: section_other | C50: alias | D50: group-detail | F50: Sonstiges | G50: Other | H50: Overig
B51: highlights | C51: json | D51: repeater | F51: Besonderheiten | G51: Highlights | H51: Bijzonderheden | K51: Yes | L51: camper_specs_translations | Q51: NEW | R51: Dreamtime | S51: highlights | U51: Free-text repeater, translatable
B52: rating_botg | C52: string | D52: select-dropdown | F52: BOTG-Bewertung | G52: BOTG Rating | H52: BOTG-beoordeling | I52: 1–5 | K52: No | Q52: NEW | R52: Dreamtime | S52: rating_botg

Sheet #5e camper_equipment
A1: Collection | B1: camper_equipment
A2: Remarks | B2: Lookup catalog (formerly camper_equipment_features). 35 features to import from equipment catalog. Linked to camper_specs via junction camper_specs_equipment (M2M).
A3: Date / Update | B3: 46189
A4: Legend | B4: Checked | C4: Changes | D4: Analysis done | E4: Analysis tbd
A6: Details for Directus Set-up | K6: Translatable? | N6: Import Details "rentalcars" | Q6: Import Details "campers" | U6: Remarks / Comments | X6: Legacy
A7: Special field type | B7: field_key Directus | C7: data_type | D7: interface (characters max) | E7: Relation (Sub-Collection) | F7: Label DE | G7: Label GB | H7: Label NL | I7: Info-Text (below the field) | K7: Yes / No | L7: Naming Translation-Collection | N7: fieldid Primarix | O7: parent table | Q7: fieldid Primarix | R7: parent table | S7: field id | U7: Remarks for DEV (field set-up and Import) | V7: Remarks + Tasks internal | X7: Kill after import
A9: COMMENT | B9: No Tabs
A11: Section (open) | B11: section_catalog | C11: alias | D11: group-detail | F11: Katalog-Felder | G11: Catalog Fields | H11: Catalogusvelden
B12: object_id | C12: integer | D12: numerical | F12: Objekt-ID | G12: Object-ID | H12: Object-ID | K12: No | S12: object_id
B13: name | C13: string | D13: text input | F13: Bezeichnung | G13: Name | H13: Naam | K13: Yes | L13: camper_equipment_translations | S13: name | U13: translatable (de/en/nl)
B14: category | C14: string | D14: select-dropdown | F14: Kategorie | G14: Category | H14: Categorie | I14: Küche / Schlafen / Bad / Strom & Tech / Klima & Fahrzeug / Camping | K14: No | S14: category | U14: controls grouping in checklist
B15: icon | C15: string | D15: text input | F15: Icon | G15: Icon | H15: Icon | K15: No | S15: icon | U15: optional symbol
B16: sort | C16: integer | D16: numerical | F16: Sortierung | G16: Sort | H16: Sortering | K16: No | S16: sort

Sheet #5f camper_specs_equipment
A1: Collection | B1: camper_specs_equipment
A2: Remarks | B2: Junction (M2M) linking camper_specs to camper_equipment; carries the per-vehicle availability tri-state.
A3: Date / Update | B3: 46189
A4: Legend | B4: Checked | C4: Changes | D4: Analysis done | E4: Analysis tbd
A6: Details for Directus Set-up | K6: Translatable? | N6: Import Details "rentalcars" | Q6: Import Details "campers" | U6: Remarks / Comments | X6: Legacy
A7: Special field type | B7: field_key Directus | C7: data_type | D7: interface (characters max) | E7: Relation (Sub-Collection) | F7: Label DE | G7: Label GB | H7: Label NL | I7: Info-Text (below the field) | K7: Yes / No | L7: Naming Translation-Collection | N7: fieldid Primarix | O7: parent table | Q7: fieldid Primarix | R7: parent table | S7: field id | U7: Remarks for DEV (field set-up and Import) | V7: Remarks + Tasks internal | X7: Kill after import
A9: COMMENT | B9: No Tabs
A11: Section | B11: section_junction | C11: alias | D11: group-detail | F11: Junction-Felder | G11: Junction Fields | H11: Koppelvelden
B12: object_id | C12: integer | D12: numerical | F12: Objekt-ID | G12: Object-ID | H12: Object-ID | K12: No | S12: object_id
B13: camper_specs | C13: integer | D13: M2O | E13: camper_specs | F13: Fahrzeug-Specs | G13: Camper Specs | H13: Camper specs | K13: No | S13: camper_specs | U13: Junction FK to camper_specs
B14: feature | C14: integer | D14: M2O | E14: camper_equipment | F14: Merkmal | G14: Feature | H14: Kenmerk | K14: No | S14: feature | U14: Junction FK to camper_equipment
B15: availability | C15: string | D15: select-dropdown | F15: Verfügbarkeit | G15: Availability | H15: Beschikbaarheid | I15: available / optional / included | K15: No | S15: availability | U15: Tri-state per vehicle x feature

Sheet Geografies
A1: Div. Collections | B1: geografies
A2: Remarks | B2: Geo-Collections: Bestand (Schema 26-06-19) + neue Felder (Media-Codes, Status). Tabs entfallen (1 Tab) - Sections direkt.
A3: Date / Update | B3: 2026-06-23
A4: Legend | B4: NEW = to be added | C4: Schema 26-06-19 = existing
A6: Details for Directus | K6: Translatable? | O6: Source
A7: Special field type | B7: field_key Directus | C7: data_type | D7: interface | E7: Relation (Sub-Collection) | F7: Label DE | G7: Label GB | H7: Label NL | I7: Info-Text (below the field) | K7: Yes / No | L7: Naming Translation-Collection | N7: fieldid Primarix | O7: Quelle (Schema / NEU)
A9: geografies > countries (Länder)
A11: Section (open) | B11: section_status_assignment | C11: alias | D11: group-detail | F11: Status & Zuordnung | G11: Status & Assignment | H11: Status & toewijzing
B12: status | C12: string | D12: select-dropdown (active, in Review, archived) | F12: Status | G12: Status | H12: Status | K12: No | O12: NEU
B13: name | C13: string | D13: input | F13: Name (Land) | G13: Name (Country) | H13: Naam (Land) | K13: Yes | L13: countries_translations | O13: Schema 26-06-19
B14: destination_id | C14: integer | D14: many to one | E14: destinations | F14: Reiseziel | G14: Destination | H14: Bestemming | I14: Zugeordnetes Reiseziel. | K14: No | O14: Schema 26-06-19
A16: Section (closed) | B16: section_iso | C16: alias | D16: group-detail | F16: ISO-Codes | G16: ISO Codes | H16: ISO-codes
B17: ISO | C17: string | D17: input (non-editable) | F17: ISO Alpha-2 (ISO 3166-1) | G17: ISO Alpha-2 (ISO 3166-1) | H17: ISO Alpha-2 (ISO 3166-1) | I17: 2-stelliger ISO-Code (als Referenz) | K17: No | O17: Schema 26-06-19
B18: ISO_alpha_3_code | C18: string | D18: input (non-editable) | F18: ISO Alpha-3 (ISO 3166-1) | G18: ISO Alpha-3 (ISO 3166-1) | H18: ISO Alpha-3 (ISO 3166-1) | I18: 3-stelliger ISO-Code (als Referenz) | K18: No | O18: Schema 26-06-19
A20: Section (open) | B20: section_media | C20: alias | D20: group-detail | F20: Medien-DB: Kürzel | G20: Media DB: Codes | H20: Media-DB: codes
B21: media_code | C21: string | D21: input | F21: Medien-Code | G21: Media Code | H21: Mediacode | I21: Maßgebliche BOTG-Kürzel für Bild-Benennung. | K21: No | O21: NEU
B22: media_code_legacy_botg | C22: string | D22: input | F22: Alt-Code BOTG | G22: Legacy Code BOTG | H22: Oude code BOTG | I22: Alt-Bildcode BOTG. Read-only. | K22: No | O22: NEU
B23: media_code_legacy_karawane | C23: string | D23: input | F23: Alt-Code Karawane | G23: Legacy Code Karawane | H23: Oude code Karawane | I23: Alt-Bildcode Karawane. Read-only. | K23: No | O23: NEU
A25: Section (closed) | B25: section_legacy | C25: alias | D25: group-detail | F25: Legacy (Primarix) | G25: Legacy (Primarix) | H25: Legacy (Primarix)
B26: cid_primarix | C26: integer | D26: numerical | F26: CID Primarix | G26: CID Primarix | H26: CID Primarix | I26: Herkunfts-ID (Migration). | K26: No | O26: Schema 26-06-19
B27: id_primarix | C27: integer | D27: numerical | F27: ID Primarix | G27: ID Primarix | H27: ID Primarix | I27: Herkunfts-ID (Migration). | K27: No | O27: Schema 26-06-19
B28: cid_px_karawane | C28: integer | D28: numerical | F28: CID Karawane | G28: CID Karawane | H28: CID Karawane | I28: Herkunfts-ID (Migration). | K28: No | O28: Schema 26-06-19
B29: id_px_karawane | C29: integer | D29: numerical | F29: ID Karawane | G29: ID Karawane | H29: ID Karawane | I29: Herkunfts-ID (Migration). | K29: No | O29: Schema 26-06-19
A31: geografies > destinations (Reiseziele)
A33: Section (open) | B33: section_status_assignment | C33: alias | D33: group-detail | F33: Status & Zuordnung | G33: Status & Assignment | H33: Status & toewijzing
B34: status | C34: string | D34: select-dropdown (active, in Review, archived) | F34: Status | G34: Status | H34: Status | K34: No | O34: NEU
B35: name | C35: string | D35: input | F35: Name (Reiseziel) | G35: Name (Destination) | H35: Naam (Bestemming) | K35: Yes | L35: destinations_translations | O35: Schema 26-06-19
B36: destinations_cluster_id | C36: integer | D36: many to one | E36: destinations_cluster | F36: Zielgebietsgruppe | G36: Destination Cluster | H36: Bestemmingscluster | I36: Übergeordnete Gruppe (bspw. für Bookmarks / Filter) | K36: No | O36: Schema 26-06-19
B37: short_code | C37: string | D37: input | F37: Kuerzel | G37: Short Code | H37: Afkorting | I37: Kurzcode | K37: No | O37: Schema 26-06-19
B38: is_non_geographic | C38: boolean | D38: boolean | F38: Keine Geografie | G38: Non-geographic | H38: Geen geografie | I38: Markiert nicht-geografische Reiseziele (Kreuzfahrten, Weltweit, Reiseleiter). | K38: No | O38: NEU
A40: Section (open) | B40: section_media | C40: alias | D40: group-detail | F40: Medien-DB: Kürzel | G40: Media DB: Codes | H40: Media-DB: codes
B41: media_code | C41: string | D41: input | F41: Medien-Code | G41: Media Code | H41: Mediacode | I41: Maßgebliche BOTG-Kürzel für Bild-Benennung. | K41: No | O41: NEU
B42: media_code_legacy_botg | C42: string | D42: input | F42: Alt-Code BOTG | G42: Legacy Code BOTG | H42: Oude code BOTG | I42: Alt-Bildcode BOTG. Read-only. | K42: No | O42: NEU
B43: media_code_legacy_karawane | C43: string | D43: input | F43: Alt-Code Karawane | G43: Legacy Code Karawane | H43: Oude code Karawane | I43: Alt-Bildcode Karawane. Read-only. | K43: No | O43: NEU
A45: geografies > states (Bundesstaaten)
A47: Section (open) | B47: section_status_assignment | C47: alias | D47: group-detail | F47: Status & Zuordnung | G47: Status & Assignment | H47: Status & toewijzing
B48: status | C48: string | D48: select-dropdown (active, in Review, archived) | F48: Status | G48: Status | H48: Status | K48: No | O48: NEU
B49: name | C49: string | D49: input | F49: Name (Bundesstaat o.ä.) | G49: Name (State or similar) | H49: Naam (deelstaat o.i.d.) | I49: Nur offizielle Staaten o.ä. - KEINE Regionen. | K49: Yes | L49: states_translations | O49: Schema 26-06-19
B50: country_id | C50: integer | D50: many to one | E50: countries | F50: Land | G50: Country | H50: Land | I50: Zugeordnetes Land. | K50: No | O50: Schema 26-06-19
B51: ISO | C51: string | D51: input (non-editable) | F51: ISO 3166-2 | G51: ISO 3166-2 | H51: ISO 3166-2 | I51: Subdivision-Code (z. B. NSW). | K51: No | O51: Schema 26-06-19
A53: Section (open) | B53: section_media | C53: alias | D53: group-detail | F53: Medien-DB: Kürzel | G53: Media DB: Codes | H53: Media-DB: codes
B54: media_code | C54: string | D54: input | F54: Medien-Code | G54: Media Code | H54: Mediacode | I54: Maßgebliche BOTG-Kürzel für Bild-Benennung. | K54: No | O54: NEU
B55: media_code_legacy_botg | C55: string | D55: input | F55: Alt-Code BOTG | G55: Legacy Code BOTG | H55: Oude code BOTG | I55: Alt-Bildcode BOTG. Read-only. | K55: No | O55: NEU
B56: media_code_legacy_karawane | C56: string | D56: input | F56: Alt-Code Karawane | G56: Legacy Code Karawane | H56: Oude code Karawane | I56: Alt-Bildcode Karawane. Read-only. | K56: No | O56: NEU
A58: geografies > destinations_cluster (Zielgebietsgruppen)
A60: Section (open) | B60: section_name | C60: alias | D60: group-detail | F60: Name | G60: Name | H60: Naam
B61: name | C61: string | D61: input | F61: Name (Zielgebietscluster) | G61: Name (Destination Cluster) | H61: Naam (bestemmingscluster) | K61: Yes | L61: destinations_cluster_translations | O61: Schema 26-06-19
B62: short_code | C62: string | D62: input | F62: Kuerzel | G62: Short Code | H62: Afkorting | I62: Kurzcode. | K62: No | O62: Schema 26-06-19
B63: ISO_alpha_3_code | C63: string | D63: input | F63: ISO Alpha-3 | G63: ISO Alpha-3 | H63: ISO Alpha-3 | I63: ISO 3166-1 Alpha-3 (sofern sinnvoll). | K63: No | O63: Schema 26-06-19
B64: is_non_geographic | C64: boolean | D64: boolean | F64: Keine Geografie | G64: Non-geographic | H64: Geen geografie | I64: Markiert nicht-geografische Cluster (z. B. Sonstiges). | K64: No | O64: NEU
A66: geografies > regions (Regionen)
A68: Section (open) | B68: section_name_assignment | C68: alias | D68: group-detail | F68: Name & Zuordnung | G68: Name & Assignment | H68: Naam & toewijzing
B69: status | C69: string | D69: select-dropdown (active, in Review, archived) | F69: Status | G69: Status | H69: Status | K69: No | O69: NEU
B70: name | C70: string | D70: input | F70: Name (Region) | G70: Name (Region) | H70: Naam (regio) | I70: Nur Regionen - keine offiziellen Staaten o.ä. | K70: Yes | L70: regions_translations | O70: Schema 26-06-19
B71: country_id | C71: alias | D71: many to many | E71: countries | F71: Länder | G71: Countries | H71: Landen | I71: Zugeordnete Länder | K71: No | O71: Schema 26-06-19
A73: Section (closed) | B73: section_legacy | C73: alias | D73: group-detail | F73: Legacy (Primarix) | G73: Legacy (Primarix) | H73: Legacy (Primarix)
B74: cid_primarix | C74: integer | D74: numerical | F74: CID Primarix | G74: CID Primarix | H74: CID Primarix | I74: Herkunfts-ID (Migration). | K74: No | O74: Schema 26-06-19
B75: id_primarix | C75: integer | D75: numerical | F75: ID Primarix | G75: ID Primarix | H75: ID Primarix | I75: Herkunfts-ID (Migration). | K75: No | O75: Schema 26-06-19
A77: geografies > places (Orte)
A79: Section (open) | B79: section_name_assignment | C79: alias | D79: group-detail | F79: Name & Zuordnung | G79: Name & Assignment | H79: Naam & toewijzing
B80: status | C80: string | D80: select-dropdown (active, in Review, archived) | F80: Status | G80: Status | H80: Status | K80: No | O80: NEU
B81: name | C81: string | D81: input | F81: Name (Stadt / Ort) | G81: Name (City / Place) | H81: Naam (stad / plaats) | K81: Yes | L81: places_translations | O81: Schema 26-06-19
B82: country_id | C82: integer | D82: many to one | E82: countries | F82: Land | G82: Country | H82: Land | I82: Zugeordnetes Land. | K82: No | O82: Schema 26-06-19
B83: state_id | C83: integer | D83: many to one | E83: states | F83: Bundesstaat | G83: State | H83: Staat | I83: Zugeordneter Bundesstaat (optional). | K83: No | O83: Schema 26-06-19
B84: region_id | C84: integer | D84: many to one | E84: regions | F84: Region | G84: Region | H84: Regio | I84: Zugeordnete Region (optional). | K84: No | O84: Schema 26-06-19
B85: location_tour32 | C85: integer | D85: many to one | E85: locations_tour32 | F85: Ort (Tour32) | G85: Location (Tour32) | H85: Locatie (Tour32) | I85: Zugeordneter Ort für Tour32-Import (optional). | K85: No | O85: Schema 26-06-19
A87: Section (closed) | B87: section_legacy | C87: alias | D87: group-detail | F87: Legacy (Primarix) | G87: Legacy (Primarix) | H87: Legacy (Primarix)
B88: cid_primarix | C88: integer | D88: numerical | F88: CID Primarix | G88: CID Primarix | H88: CID Primarix | I88: Herkunfts-ID (Migration). | K88: No | O88: Schema 26-06-19
B89: id_primarix | C89: integer | D89: numerical | F89: ID Primarix | G89: ID Primarix | H89: ID Primarix | I89: Herkunfts-ID (Migration). | K89: No | O89: Schema 26-06-19
A91: geografies > locations_tour32 (Orte Tour32, Legacy)
A93: Section (open) | B93: section_name | C93: alias | D93: group-detail | F93: Name | G93: Name | H93: Naam
B94: status | C94: string | D94: select-dropdown (active, in Review, archived) | F94: Status | G94: Status | H94: Status | K94: No | O94: NEU
B95: name | C95: string | D95: input | F95: Name (Stadt / Ort) | G95: Name (City / Place) | H95: Naam (stad / plaats) | I95: Ortsbezeichnung gem. Tour32 | K95: No | O95: Schema 26-06-19

Sheet booking_partners
A1: Collection | B1: booking_partners | M1: Collection-Meta: display_template=null → auf {{name_booking_partner}} setzen (sonst zeigen die M2O-Picker die UUID). note=null → Beschreibung ergänzen (SOLL-Remark). Anzeigename EN → "Agencies & Operator"; DE/NL ergänzen (Vorschlag DE "Agenturen & Veranstalter", NL "Agentschappen & touroperator"); nl-NL fehlt in translations. color #6B7785 ✓ (Stammdaten). Nav-Gruppe Hotels_Metadata – wird auch von rental_companies/excursions/tours genutzt (Nav-Entscheidung, Navigation-Doc).
A2: Remarks | B2: Reservation / booking partner data (Buchungsstelle). Target of the 'booking_partner' M2O in hotels/rental_companies.
A3: Date / Update | B3: 2026-06-29 00:00:00
A5: Legend | B5: Checked | C5: Changes | D5: Analysis done | E5: Analysis tbd | F5: Hidden field. | G5: Legacy fields not imported.
A7: Details for Directus Set-up | K7: Translatable?
A8: Special field type | B8: field_key Directus | C8: data_type | D8: interface (characters max) | E8: Relation (Sub-Collection) | F8: Label DE | G8: Label GB | H8: Label NL | I8: Info-Text (below the field) | K8: Yes / No | L8: Naming Translation-Collection | M8: Δ / Hinweis (IST↔SOLL)
A10: Section (open) | B10: section_publication | C10: alias | D10: group-detail | F10: Status & Veröffentlichung | G10: Status & Publication | H10: Status & publicatie | M10: IST: KEINE Sections – alle 17 Felder in EINEM generischen group-raw namens "group" (Verstoß §1.4 generischer Name / §3: group-raw statt group-detail). SOLL: 3 group-detail-Sections. Korrektur: "group" ersetzen durch section_publication / section_reservation / section_contact, Felder re-parenten UND umsortieren (IST mischt die Kontaktfelder zwischen name und supplier_booking_code/booking_info).
B11: status | C11: string | D11: select-dropdown | F11: Status | G11: Status | H11: Status | I11: Vorschlag: auf 4-Werte-Standard angleichen (Field-Configs §1.1: Draft/Published/Unpublished/Archived). | K11: No | M11: Status-Standard NEU "Sonstige Sub-Collections": Werte active / archived / deleted (deleted = i.S. Directus-Löschung). Default=active; archive_field=status, archive_value=archived, unarchive_value=active. IST: 3 Werte published/draft/archived, unarchive=draft → anpassen. IST: KEIN Label (translations=null) → Label "Status" DE/GB/NL ergänzen. KLÄREN: ist "deleted" ein Enum-Wert ODER echte Directus-Löschung (dann Enum nur active/archived)? Folgeschritt: Standard in Field-Configs kodifizieren + Regel-ID.
A12: Field hidden | B12: id | C12: uuid | D12: input | K12: No
A13: Field hidden | B13: sort | C13: integer | D13: input | K13: No
A14: Field hidden | B14: user_created | C14: uuid | D14: select-dropdown-m2o | E14: directus_users | K14: No
A15: Field hidden | B15: date_created | C15: timestamp | D15: datetime | K15: No
A16: Field hidden | B16: user_updated | C16: uuid | D16: select-dropdown-m2o | E16: directus_users | K16: No
A17: Field hidden | B17: date_updated | C17: timestamp | D17: datetime | K17: No
A19: Section (open) | B19: section_reservation | C19: alias | D19: group-detail | F19: Buchungsstelle | G19: Booking Partner | H19: Boekingspartner | M19: → neue group-detail-Section (Umbau s. r10).
B20: agency_type | C20: string | D20: radio button
B21: booking_partner | C21: string | D21: input | F21: Name (Buchungspartner) | G21: Name (Booking Partner) | H21: Naam (Boekingspartner) | K21: No | M21: Rename §4.1: booking_partner → name_booking_partner (primäres Namensfeld). Zieht M2O-Templates nach: booking_partner (hotels/rental_companies) + operator_linked (excursions/tours) → {{name_booking_partner}}. Label: IST nur EN-GB ("Booking partner") → DE/NL ergänzen, EN an SOLL ("Name (Booking Partner)").
B22: supplier_booking_code | C22: string | D22: input | F22: Buchungscode Supplier | G22: Supplier Booking Code | H22: Supplier boekingscode | K22: No | M22: Label: IST nur EN-GB ("Supplier booking code") → DE/NL ergänzen (EN Title-Case "Supplier Booking Code").
B23: booking_info | C23: text | D23: input-multiline | F23: Buchungshinweise | G23: Booking Info | H23: Boekingsinfo | K23: No | M23: Label: IST nur EN-GB ("Booking info") → DE/NL ergänzen (EN "Booking Info"). Interface/Breite ✓ (input-multiline, softLength 1000, full).
A25: Section (open) | B25: section_contact | C25: alias | D25: group-detail | F25: Kontakt (Reservierung) | G25: Contact (reservation) | H25: Contact (reservering) | M25: → neue group-detail-Section (Umbau s. r10). IST-Kontext: In hotels sind die äquivalenten Kontaktfelder ausgegraut/legacy – booking_partners ist deren eigentliches Zuhause.
B26: res_contact_titel | C26: string | D26: input | F26: Titel | G26: Title | H26: Titel | K26: No | M26: Rename: res_contact_titel → booking_contact_title (fixt Deutsch-im-Key "titel", §1.1 en-GB; "booking"-Thema). Label: IST nur EN-GB → DE/NL ergänzen (EN "Title").
B27: res_contact_greeting | C27: string | D27: input | F27: Anrede | G27: Salutation | H27: Aanhef | K27: No | M27: Rename: res_contact_greeting → booking_contact_greeting. Label: IST nur EN-GB → DE/NL ergänzen (EN "Salutation").
B28: res_contact_firstname | C28: string | D28: input | F28: Vorname | G28: First Name | H28: Voornaam | K28: No | M28: Rename: res_contact_firstname → booking_contact_firstname. Label: IST nur EN-GB → DE/NL ergänzen (EN "First Name").
B29: res_contact_name | C29: string | D29: input | F29: Nachname | G29: Last Name | H29: Achternaam | K29: No | M29: Rename: res_contact_name → booking_contact_name (= Nachname; Label "Last Name"). Label: IST nur EN-GB → DE/NL ergänzen.
B30: res_phone | C30: string | D30: input | F30: Telefon (Reservierung) | G30: Phone (reservation) | H30: Telefoon (reservering) | K30: No | M30: Rename §4.3 (Kanal-first): res_phone → phone_booking. Label: IST nur EN-GB → DE/NL ergänzen (EN "Phone (reservation)").
B31: res_email_1 | C31: string | D31: input | F31: E-Mail (Reservierung) | G31: Email (reservation) | H31: E-mail (reservering) | K31: No | M31: Rename §4.3: res_email_1 → email_booking (wie hotels email_booking). Label: IST nur EN-GB → DE/NL ergänzen (EN "Email (reservation)").
B32: res_email_2 | C32: string | D32: input | F32: E-Mail 2 (Reservierung) | G32: Email 2 (reservation) | H32: E-mail 2 (reservering) | K32: No | M32: Rename §4.3: res_email_2 → email_booking_2 (zweite Reservierungs-Mail; alt. email_booking_alt). Label: IST nur EN-GB → DE/NL ergänzen (EN "Email 2 (reservation)").
B33: res_fax | C33: string | D33: input | I33: Fax = Kill (Field-Configs §5.3 / Build Spec §5) — nicht anlegen. | K33: No | M33: IST: nicht vorhanden → Kill korrekt umgesetzt, nichts zu tun.

Sheet # Media
A1: Media
B3: Allgemeine Felder
B5: Title
B6: Description
B7: Tags
B8: Publication Status (Auswahlfeld, aktuell "Published")
B9: Generated File Name (z. B. UNK_UNK_20260616_CED_001)
B11: Geographies
B13: Place
B14: State
B15: Region
B16: Country
B17: Destination
... B43: Direct Link / Share Links

Sheet field_dictionary
A1: Collection | B1: field_dictionary
A2: Remarks | B2: Field Dictionary — Mapping Primarix BOTG + Karawane → ContentHub (Doku / Crosswalk)
A3: Date / Update | B3: 2026-06-30
A4: Legend | B4: Checked | C4: Changes | D4: Analysis done | E4: Analysis tbd
A6: Details for Directus Set-up | K6: Translatable?
A7: Special field type | B7: field_key Directus | C7: data_type | D7: interface (characters max) | E7: Relation (Sub-Collection) | F7: Label DE | G7: Label GB | H7: Label NL | I7: Info-Text (below the field) | K7: Yes / No | L7: Naming Translation-Collection
A9: COMMENT only | B9: Scope: 1 Zeile je neuem Feld. Zusätzlich erhalten in Primarix aktiv genutzte, aber NICHT importierte Felder (im Brief durchgestrichen/ausgegraut) eigene Zeilen mit status=outdated — Block „Ziel" leer, nur Herkunft/Transformation gefüllt.
A10: COMMENT only | B10: Erweiterung des bestehenden field_dictionary. Magenta = neu/geändert: primarix_botg_table/_field_name = umbenannte Bestandsspalten (primarix_table / primarix_field_name); alle primarix_karawane_* + *_label_de sind neu.
A12: Field hidden | B12: id | C12: uuid | D12: input | F12: ID | G12: ID | H12: ID | I12: Primärschlüssel (UUID, auto). | K12: No
A13: Field hidden | B13: sort | C13: integer | D13: input | F13: Sortierung | G13: Sort | H13: Sortering | I13: Manuelle Sortier-Reihenfolge. | K13: No
A14: Field hidden | B14: user_created | C14: uuid | D14: select-dropdown-m2o | F14: Erstellt von | G14: Created by | H14: Aangemaakt door | I14: Audit: anlegender User. | K14: No
A15: Field hidden | B15: date_created | C15: timestamp | D15: datetime | F15: Erstellt am | G15: Created at | H15: Aangemaakt op | I15: Audit: Anlagedatum. | K15: No
A16: Field hidden | B16: user_updated | C16: uuid | D16: select-dropdown-m2o | F16: Geändert von | G16: Updated by | H16: Bijgewerkt door | I16: Audit: letzter Bearbeiter. | K16: No
A17: Field hidden | B17: date_updated | C17: timestamp | D17: datetime | F17: Geändert am | G17: Updated at | H17: Bijgewerkt op | I17: Audit: letzte Änderung. | K17: No
A19: Tab-Navigation | B19: ui_tabs | C19: alias | D19: tabs | F19: - | G19: - | H19: -
A20: Tab | B20: tab_target | C20: alias | D20: group-raw | F20: Ziel | G20: Target | H20: Doel
A21: Section (open) | B21: section_target | C21: alias | D21: group-detail | F21: Ziel — ContentHub (neues Modell) | G21: Target — ContentHub (new model) | H21: Doel — ContentHub (nieuw model)
B22: target_collection | C22: string | D22: select-dropdown | F22: Ziel-Collection | G22: Target Collection | H22: Doel-collectie | I22: Produkt-/Ziel-Collection im ContentHub (hotels, tours, …). | K22: No
B23: field_name | C23: string | D23: input | F23: Feldname (neu) | G23: Field Name (new) | H23: Veldnaam (nieuw) | I23: Technischer Directus-Feldkey (snake_case) — die „nach"-Seite. Leer bei nicht importierten Legacy-Feldern (status=outdated). | K23: No
B24: data_type | C24: string | D24: select-dropdown | F24: Datentyp | G24: Data Type | H24: Gegevenstype | I24: Directus-Datentyp (string, integer, text, …). | K24: No
B25: interface | C25: string | D25: select-dropdown | F25: Interface | G25: Interface | H25: Interface | I25: Directus-Interface (input, select-dropdown, …). | K25: No
B26: label_de | C26: string | D26: input | F26: Label DE | G26: Label DE | H26: Label DE | I26: Neue dt. Bezeichnung. | K26: No
B27: label_en | C27: string | D27: input | F27: Label EN | G27: Label EN | H27: Label EN | I27: Neue engl. Bezeichnung. | K27: No
B28: label_nl | C28: string | D28: input | F28: Label NL | G28: Label NL | H28: Label NL | I28: Neue nl. Bezeichnung. | K28: No
B29: tab | C29: string | D29: input | F29: Tab | G29: Tab | H29: Tab | I29: UI-Tab im Zielformular (Doku). | K29: No
B30: section | C30: string | D30: input | F30: Section | G30: Section | H30: Sectie | I30: UI-Section im Zielformular (Doku). | K30: No
A32: Tab | B32: tab_api_governance | C32: alias | D32: group-raw | F32: API & Governance | G32: API & Governance | H32: API & governance
A33: Section (open) | B33: section_api_governance | C33: alias | D33: group-detail | F33: API & Governance | G33: API & Governance | H33: API & Governance
B34: api_field_name | C34: string | D34: input | F34: API-Feldname | G34: API Field Name | H34: API-veldnaam | I34: Name im Dump/in der API (post-Transformer) — die „nach"-Seite für Konsumenten. | K34: No
B35: audience | C35: string | D35: select-dropdown | F35: Sichtbarkeit (API) | G35: Audience | H35: Zichtbaarheid (API) | I35: public / backoffice / internal — steuert die externe Projektion (default-deny). | K35: No
B36: status | C36: string | D36: select-dropdown | F36: Status | G36: Status | H36: Status | I36: active / renamed / new / outdated. „outdated" = in Primarix genutzt, aber NICHT importiert. | K36: No
B37: since_version | C37: string | D37: input | F37: Ab Version | G37: Since Version | H37: Vanaf versie | I37: Einführungs-Version (v0 / v1). | K37: No
B38: convention_ref | C38: csv | D38: tags | E38: — | F38: Konventions-Verweis | G38: Convention Reference | H38: Conventieverwijzing | I38: 0…n stabile Regel-IDs (Slugs) aus Konventionen + Field-Configs; nur bei regelgebundenen Feldern. Keine Abschnittsnummern. Später M2M auf standards-Collection. | K38: No
A40: Tab | B40: tab_origins_transform | C40: alias | D40: group-raw | F40: Herkunft & Transformation | G40: Origins & Transformations | H40: Herkomst & transformatie
A41: Section (open) | B41: section_origin | C41: alias | D41: group-detail | F41: Herkunft — Primarix-Quellen | G41: Origin — Primarix Sources | H41: Herkomst — Primarix-bronnen
B42: primarix_sources | C42: json | D42: list (repeater) | E42: — | F42: Primarix-Quellen | G42: Primarix Sources | H42: Primarix-bronnen | I42: 0…n Quellen je Zielfeld. Eintrag: system (botg/karawane) · table · fieldid · field_name (uid) · label_de. Cars&Camper = 2× BOTG (rentalcars+camper); Cruises = Karawane. | K42: No
A44: Section (open) | B44: section_transform | C44: alias | D44: group-detail | F44: Hinweise — Daten-Transformation | G44: Notes — Data Transformation | H44: Notities — Datatransformatie
B45: transform_note | C45: text | D45: input-multiline | F45: Transformations-Hinweis | G45: Transform Note | H45: Transformatie-notitie | I45: Transformation alt→neu (z. B. na→NULL, #value# entpackt, HTML-Separator→Array). | K45: No
B46: field_comment | C46: text | D46: input-multiline | F46: Kommentar | G46: Comment | H46: Opmerking | I46: Freier Kommentar / offene Punkte. | K46: No

Sheet Field Lists v2
A1: BOTG: Set-up new Sub-collections
A2: Update | C2: 46163
A4: Status | C4: Cluster | D4: Directus | F4: Source Primarix today | I4: Fields + Values Directus | J4: Fields + Values Directus | P4: Remarks / Comments
A5: Ready to implement? | D5: Name new "sub-collection" | F5: Table | G5: Field | I5: field name | J5: values + translations (text inputs) | M5: cid_primarix | N5: id_primarix | P5: Remarks for DEV | Q5: Remarks internal
J6: de-DE | K6: en-GB | L6: nl-NL | M6: numerical | N6: numerical
C8: sub-collection relevant for "hotels"
A10: yes | D10: hotels_rooms_occupancies | F10: hotels_room_occupancy | G10: field_620_1 | I10: occupancy | M10: - | N10: -
J11: 1 Pers. | K11: 1 Pers. | L11: 1 pers. | M11: no field for cid | N11: no field for id
J12: 2 Pers. | K12: 2 Pers. | L12: 2 pers.
J13: 3 Pers. | K13: 3 Pers. | L13: 3 pers.
J14: 4 Pers. | K14: 4 Pers. | L14: 4 pers.
J15: 5 Pers. | K15: 5 Pers. | L15: 5 pers.
J16: 6 Pers. | K16: 6 Pers. | L16: 6 pers.
J17: 7 Pers. | K17: 7 Pers. | L17: 7 pers.
J18: Erw. | K18: Adult | L18: Volw.
J19: Kind | K19: Child | L19: Kind
J20: Kind 2-11 | K20: Child 2-11 | L20: Kind 2-11
J21: Kind 2-17 | K21: Child 2-17 | L21: Kind 2-17
J22: Kind 3-11 | K22: Child 3-11 | L22: Kind 3-11
J23: Kind 3-12 | K23: Child 3-12 | L23: Kind 3-12
... J34: Verl. Nacht 2 | K34: Ext. Night 2 | L34: Verl. nacht 2
A36: yes | D36: hotels_activities | F36: px_feldlisten | G36: cid 36 | I36: activity | M36: -
J37: Angeln | K37: Fishing | L37: Vissen | M37: 36 | N37: 598
J38: Baden | K38: Swimming | L38: Zwemmen | M38: 36 | N38: 599
J39: Golf | K39: Golf | L39: Golf | M39: 36 | N39: 603
J40: Flitterwochen | K40: Honeymoon | L40: Huwelijksreis | M40: 36 | N40: 121353
J41: Reiten | K41: Horse Riding | L41: Paardrijden | M41: 36 | N41: 580
J42: Schnorcheln | K42: Snorkelling | L42: Snorkelen | M42: 36 | N42: 600
J43: Segeln | K43: Sailing | L43: Zeilen | M43: 36 | N43: 578
J44: Surfen | K44: Surfing | L44: Surfen | M44: 36 | N44: 579
J45: Tauchen | K45: Diving | L45: Duiken | M45: 36 | N45: 577
J46: Tennis | K46: Tennis | L46: Tennis | M46: 36 | N46: 581
J47: Wandern | K47: Hiking | L47: Wandelen | M47: 36 | N47: 601
J48: Wellness | K48: Wellness | L48: Wellness | M48: 36 | N48: 602
A50: yes | D50: hotels_classification | F50: px_feldlisten | G50: cid 15 | I50: classification | M50: -
J51: 0.0 | K51: no translation! | L51: no translation! | M51: 15 | N51: 626
J52: 0.5 | K52: - | L52: - | M52: 15 | N52: 627
J53: 1.0 | K53: - | L53: - | M53: 15 | N53: 565
J54: 1.5 | K54: - | L54: - | M54: 15 | N54: 5
J55: 2.0 - 3.0 | K55: - | L55: - | M55: 15 | N55: 3547
J56: 2.0 - 3.5 | K56: - | L56: - | M56: 15 | N56: 121611
J57: 2.0 - 4.0 | K57: - | L57: - | M57: 15 | N57: 3546
J58: 2.0 - 5.0 | K58: - | L58: - | M58: 15 | N58: 3545
J59: 2.0 | K59: - | L59: - | M59: 15 | N59: 6
J60: 2.5 | K60: - | L60: - | M60: 15 | N60: 7
J61: 3.0 | K61: - | L61: - | M61: 15 | N61: 8
J62: 3.0 - 5.0 | K62: - | L62: - | M62: 15 | N62: 103548
... J68: 6.0 | K68: - | L68: - | M68: 15 | N68: 9461
A70: yes | D70: hotels_catering | F70: px_feldlisten | G70: cid 95 | I70: mealplans | M70: -
F71: Note:
F72: Used in "Room categories" and "Surcharges"
J73: ohne | K73: without | L73: zonder | M73: 95 | N73: 103532
J74: Frühstück | K74: Breakfast | L74: Ontbijt | M74: 95 | N74: 103533
J75: Tropisches Frühstück | K75: Tropical Breakfast | L75: Tropisch ontbijt | M75: 95 | N75: 103559
J76: Kontinentales Frühstück | K76: Continental Breakfast | L76: Continentaal ontbijt | M76: 95 | N76: 103534
J77: Amerikanisches Frühstück | K77: American Breakfast | L77: Amerikaans ontbijt | M77: 95 | N77: 103557
J78: Büffet-Frühstück | K78: Buffet Breakfast | L78: Ontbijtbuffet | M78: 95 | N78: 103558
J79: Frühstückskorb 1. Morgen | K79: Breakfast Basket 1st Morning | L79: Ontbijtmand 1e ochtend | M79: 95 | N79: 103570
J80: Frühstückskorb täglich | K80: Breakfast Basket Daily | L80: Ontbijtmand dagelijks | M80: 95 | N80: 103569
J81: Halbpension | K81: Half Board | L81: Halfpension | M81: 95 | N81: 103972
J82: Halbpension und Aktivitäten | K82: Half Board and Activities | L82: Halfpension en activiteiten | M82: 95 | N82: 103561
J83: Halbpension (Frühstück und Mittagessen) | K83: Half Board (Breakfast and Lunch) | L83: Halfpension (ontbijt en lunch) | M83: 95 | N83: 103535
J84: Halbpension (Frühstück und Abendessen) | K84: Half Board (Breakfast and Dinner) | L84: Halfpension (ontbijt en diner) | M84: 95 | N84: 103556
... J96: All Inclusive, ausgewählte Getränke und Aktivitäten | K96: All Inclusive, Selected Beverages and Activities | L96: All Inclusive, geselecteerde dranken en activiteiten | M96: 95 | N96: 119585
A98: yes | D98: surcharge_calc_type (DROP DOWN ONLY) | F98: px_feldlisten | G98: cid 111 | M98: -
J99: bitte wählen | M99: 111 | N99: 121664
J100: einmalig pro Einheit | M100: 111 | N100: 121665
J101: einmalig pro Person | M101: 111 | N101: 121666
J102: pro Einheit und Nacht | M102: 111 | N102: 121667
J103: pro Person und Nacht | M103: 111 | N103: 121668
D105: hotels_rooms_category_names | F105: Open texts until today
J106: Standardzimmer | K106: Standard Room | L106: Standaard kamer
J107: Superior-Zimmer | K107: Superior Room | L107: Superior kamer
J108: Deluxe-Zimmer | K108: Deluxe Room | L108: Deluxe kamer
J109: Junior Suite | K109: Junior Suite | L109: Junior suite
J110: Suite | K110: Suite | L110: Suite / Luxe suite
J111: Studio | K111: Studio | L111: Studio
J112: Bungalow / Gartenbungalow / Strandbungalow | K112: Bungalow | L112: Bungalow
J113: Chalet | K113: Chalet | L113: Chalet
J114: Safarizelt | K114: Safari Tent | L114: Safaritent
J115: Villa / Strandvilla | K115: Villa | L115: Villa
J116: Cottage | K116: Cottage | L116: Cottage
J117: Overwater-Bungalow | K117: Overwater Bungalow | L117: Overwater bungalow
... J121: 2 Schlafzimmer Apartment | K121: 2 Bedroom Apartment | L121: 2 Slaapkamer Appartement
D124: DROP DOWN only | F124: Open texts until today
J125: 1 Nacht | K125: 1 Night | L125: 1 nacht
J126: 2 Nächte | K126: 2 Nights | L126: 2 nachten
J127: 3 Nächte | K127: 3 Nights | L127: 3 nachten
J128: 4 Nächte | K128: 4 Nights | L128: 4 nachten
J129: 3 Nächte | K129: 3 Nights | L129: 3 nachten
J130: 5 Nächte | K130: 5 Nights | L130: 5 nachten
J131: 6 Nächte | K131: 6 Nights | L131: 6 nachten
J132: 7 Nächte | K132: 7 Nights | L132: 7 nachten
A135: yes | D135: travel_categories | F135: px_feldlisten | G135: cid 17 | M135: -
J136: Flitterwochen | M136: 17 | N136: 121354 | Q136: Merge mit Karawane!
J137: Tauchreisen / Inselaufenthalte | M137: 17 | N137: 121347
J138: Tauchkreuzfahrten | M138: 17 | N138: 121346
J139: Tauchreisen | M139: 17 | N139: 560 | Q139: Tauchen
J140: Länderkombinationen | M140: 17 | N140: 98059
J141: Verlängerungsprogramm | M141: 17 | N141: 116512
...

Sheet Field Types
B1: Field types
B2: text input
B3: text area
B4: email
B5: phone number
B6: md-editor
B7: drop down | C7: 1 realtuion to sub-table or field value
B8: multi select
B9: repeater | C9: wiederhole immer das selbe
B10: repeater (json)
B11: text area (in repeater)
B12: checkbox (boolean)
A14: M2M | B14: mant to many (Mehrfachauswahl)
A15: M2O | B15: many to one (DropDown)
